Workbook

Sheet Sheet3
B3: WORKERS | O3: Upah & Astek | P3: Total &
A4: ESTATE/DIVISION | D4: 50000 | E4: 20000 | F4: 10000 | G4: 5000 | H4: 1000 | I4: 500 | J4: 100 | K4: 50 | L4: OTHERS | M4: TOTAL | P4: Rata-rata
A5: AR. MAINTENANCE
M6: =SUM(D6:L6) -> 0
A7: 1 | B7: 14 | C7: 280 | D7: 14650000 | E7: 100000 | F7: 40000 | G7: 15000 | H7: 42000 | L7: 9549 | M7: =SUM(D7:L7) -> 14856549 | O7: =5769904+225865 -> 5995769
A8: Sub Total | B8: =B6+B7 -> 14 | C8: =C6+C7 -> 280 | D8: =D6+D7 -> 14650000 | E8: =E6+E7 -> 100000 | F8: =F6+F7 -> 40000 | G8: =G6+G7 -> 15000 | H8: =H6+H7 -> 42000 | I8: =I6+I7 -> 0 | ... M8: =M6+M7 -> 14856549
A10: AR. HARVESTING 2
M11: =SUM(D11:L11) -> 0
A12: 1 | B12: 10 | C12: 215 | D12: 10800000 | E12: 160000 | F12: 30000 | G12: 30000 | H12: 20000 | L12: 5612 | M12: =SUM(D12:L12) -> 11045612
A13: Sub Total | B13: =B11+B12 -> 10 | C13: =C11+C12 -> 215 | D13: =D11+D12 -> 10800000 | E13: =E11+E12 -> 160000 | F13: =F11+F12 -> 30000 | G13: =G11+G12 -> 30000 | H13: =H11+H12 -> 20000 | I13: =I11+I12 -> 0 | ... M13: =M11+M12 -> 11045612
A18: Sub Total | B18: =B17 -> 0 | C18: =C17 -> 0 | D18: =D17 -> 0 | E18: =E17 -> 0 | F18: =F17 -> 0 | G18: =G17 -> 0 | H18: =H17 -> 0 | I18: =I17 -> 0 | ... M18: =M17 -> 0
A21: AR. TRANSPORT 1
A22: 1 | B22: 7 | C22: 143 | D22: 14250000 | E22: 20000 | F22: 30000 | G22: 20000 | H22: 17000 | L22: 4264 | M22: =SUM(D22:L22) -> 14341264 | O22: =5062955+180692 -> 5243647
A23: Sub Total | B23: =B22 -> 7 | C23: =C22 -> 143 | D23: =D22 -> 14250000 | E23: =E22 -> 20000 | F23: =F22 -> 30000 | G23: =G22 -> 20000 | H23: =H22 -> 17000 | I23: =I22 -> 0 | ... M23: =M22 -> 14341264
A28: Sub Total | B28: =B27 -> 0 | C28: =C27 -> 0 | D28: =D27 -> 0 | E28: =E27 -> 0 | F28: =F27 -> 0 | G28: =G27 -> 0 | H28: =H27 -> 0 | I28: =I27 -> 0 | ... M28: =M27 -> 0
A30: AR. LC PHT
A31: 1 | B31: 71 | C31: 1455 | D31: 75400000 | E31: 520000 | F31: 220000 | G31: 90000 | H31: 205000 | L31: 42723 | M31: =SUM(D31:L31) -> 76477723
A32: Sub Total | B32: =B31 -> 71 | C32: =C31 -> 1455 | D32: =D31 -> 75400000 | E32: =E31 -> 520000 | F32: =F31 -> 220000 | G32: =G31 -> 90000 | H32: =H31 -> 205000 | I32: =I31 -> 0 | ... M32: =M31 -> 76477723
A35: BIBITAN
A36: 1 | B36: 38 | C36: 755 | D36: 40100000 | E36: 260000 | F36: 210000 | G36: 65000 | H36: 93000 | L36: 27608 | M36: =SUM(D36:L36) -> 40755608
A37: Sub Total | B37: =B36 -> 38 | C37: =C36 -> 755 | D37: =D36 -> 40100000 | E37: =E36 -> 260000 | F37: =F36 -> 210000 | G37: =G36 -> 65000 | H37: =H36 -> 93000 | I37: =I36 -> 0 | ... M37: =M36 -> 40755608
P39: =SUM(O5:O39) -> 11239416
A40: TOTAL | B40: =B37+B32+B28+B23+B18+B13+B8 -> 140 | C40: =C37+C32+C28+C23+C18+C13+C8 -> 2848 | D40: =D37+D32+D28+D23+D18+D13+D8 -> 155200000 | E40: =E37+E32+E28+E23+E18+E13+E8 -> 1060000 | F40: =F37+F32+F28+F23+F18+F13+F8 -> 530000 | G40: =G37+G32+G28+G23+G18+G13+G8 -> 220000 | H40: =H37+H32+H28+H23+H18+H13+H8 -> 377000 | I40: =I37+I32+I28+I23+I18+I13+I8 -> 0 | ... M40: =M37+M32+M28+M23+M18+M13+M8 -> 157476756 | P40: =P39/C40 -> 3946.4242 | Q40: Upah rata-rata / HK | S40: =SUM(D40:L40) -> 157476756
B46: WORKERS
A47: ESTATE/DIVISION | D47: 50000 | E47: 20000 | F47: 10000 | G47: 5000 | H47: 1000 | I47: 500 | J47: 100 | K47: 50 | L47: OTHERS | M47: TOTAL
A48: AR. MAINTENANCE
M49: =SUM(D49:L49) -> 0
A50: 1
A51: Sub Total
A53: AR. HARVESTING 2
A55: 1
A56: Sub Total
A59: AR. Maintenance AB
A60: 1 | B60: 75 | C60: 1487 | D60: 76750000 | E60: 660000 | F60: 360000 | G60: 230000 | H60: 217000 | L60: 49609 | M60: =SUM(D60:L60) -> 78266609
A61: Sub Total | B61: =B60 -> 75 | C61: =C60 -> 1487 | D61: =D60 -> 76750000 | E61: =E60 -> 660000 | F61: =F60 -> 360000 | G61: =G60 -> 230000 | H61: =H60 -> 217000 | I61: =I60 -> 0 | ... M61: =M60 -> 78266609
A64: AR. TRANSPORT 1
A65: 1
A66: Sub Total | B66: =B65 -> 0 | C66: =C65 -> 0 | D66: =D65 -> 0 | E66: =E65 -> 0 | F66: =F65 -> 0 | G66: =G65 -> 0 | H66: =H65 -> 0 | I66: =I65 -> 0 | ... M66: =M65 -> 0
A69: AR. TRANSPORT A
A70: 1 | B70: 1 | C70: 23 | D70: 1750000 | L70: 571 | M70: =SUM(D70:L70) -> 1750571
A71: Sub Total | B71: =B70 -> 1 | C71: =C70 -> 23 | D71: =D70 -> 1750000 | E71: =E70 -> 0 | F71: =F70 -> 0 | G71: =G70 -> 0 | H71: =H70 -> 0 | I71: =I70 -> 0 | ... M71: =M70 -> 1750571
A73: AR. LC PHT
A74: 1
A75: Sub Total
A78: BIBITAN
A79: 1
A80: Sub Total | B80: =B79 -> 0 | C80: =C79 -> 0 | D80: =D79 -> 0 | E80: =E79 -> 0 | F80: =F79 -> 0 | G80: =G79 -> 0 | H80: =H79 -> 0 | I80: =I79 -> 0 | ... M80: =M79 -> 0
A83: TOTAL | B83: =B80+B75+B71+B66+B61+B56+B51 -> 76 | C83: =C80+C75+C71+C66+C61+C56+C51 -> 1510 | D83: =D80+D75+D71+D66+D61+D56+D51 -> 78500000 | E83: =E80+E75+E71+E66+E61+E56+E51 -> 660000 | F83: =F80+F75+F71+F66+F61+F56+F51 -> 360000 | G83: =G80+G75+G71+G66+G61+G56+G51 -> 230000 | H83: =H80+H75+H71+H66+H61+H56+H51 -> 217000 | I83: =I80+I75+I71+I66+I61+I56+I51 -> 0 | ... M83: =M80+M75+M71+M66+M61+M56+M51 -> 80017180

Sheet SEPTEMBER DIBAYAR OKT 2025 
B3: PT. REBINMAS JAYA
B4: DENOMINATION FOR OKTOBER 2025
B6: ESTATE/DIVISION | C6: WORKERS | D6: HK | G6: JUMLAH | H6: BERAS | I6: JABATAN | J6: MASA KERJA | K6: TUNJ. LAIN | L6: JKK | M6: KOREKSI | N6: JKK | O6: BPJS | Q6: TOTAL PPH 21 | R6: TOTAL PPH | S6: POT | T6: TOTAL PREMI | U6: TOTAL LEMBUR | V6: TOTAL MANUAL | W6: Upah & Astek | X6: Total & | AA6: THUMB PRINT | AB6: SELISIH | AD6: PRUNNING | AF6: Koreksi | AG6: Insentif | AH6: Kontanan | AJ6: PREMI ( Rp ) | AL6: Ember | AN6: Pengembalian Tiket
D7: Ifest | E7: Cekroll | F7: Selisih | L7: JKM | N7: JKM | O7: Kes & Pen | Q7: (MASA OKTOBER 2025) | R7: EX-GRATIA | S7: SPSI | X7: Rata-rata | AJ7: TBS | AK7: BRDL
AA8: 878370277 | AB8: =V35-AA8 -> 0.0050001144
B9: PHASE IA MAINTENANCE KHT AIK HIJAU | C9: 22 | E9: 668 | Q9: 73888 | S9: 84000 | T9: 231010 | U9: 3193152.9 | V9: 89293007 | AL9: =AK9/1050 -> 0
B11: PHASE IA OPERATOR AIK HIJAU | C11: 8 | E11: 240 | Q11: 595803 | S11: 32000 | T11: 14437260 | U11: 8716747.8 | V11: 54307923 | AL11: =AK11/1050 -> 0
B13: PHASE IA HARVESTING AIK HIJAU | C13: 30 | E13: 920 | Q13: 347060 | S13: 64000 | T13: =3639444+64000+AM13 -> 33136125 | U13: 0 | V13: 1.6501079e+08 | AD13: 4903600 | AF13: 787069 | AG13: =7050000+2217478 -> 9267478 | AJ13: 14151681 | AK13: 15281000 | AL13: =AK13/1050 -> 14553.333 | AM13: =AJ13+AK13 -> 29432681
B15: PHASE IA HARVESTING AIK HIJAU masa percobaan | C15: 2 | E15: 62 | Q15: 28987 | S15: 0 | T15: =AM15 -> 2218345 | U15: 0 | V15: 10390586 | AJ15: 1103595 | AK15: 1114750 | AL15: =AK15/1050 -> 1061.6667 | AM15: =AJ15+AK15 -> 2218345
B17: PHASE IA HARVESTING KHT AIK BATU | C17: 33 | E17: 1007 | Q17: 121625 | S17: 120000 | T17: =AM17+2629000 -> 17797944 | U17: 918731.76 | V17: 1.6053064e+08 | AD17: 10563150 | AF17: 1095499 | AG17: 4977896 | AJ17: 6390944 | AK17: 8778000 | AL17: =AK17/1050 -> 8360 | AM17: =AJ17+AK17 -> 15168944
B19: PHASE IA MAINTENANCE KHT AIK BATU | C19: 24 | E19: 715 | Q19: 85836 | S19: 92000 | T19: 110000 | U19: 4190313.1 | V19: 96038461 | AL19: =AK19/1050 -> 0
B21: PHASE IA HARVESTING AIK BATU masa percobaan | AL21: =AK21/1050 -> 0
B23: PHASE IA OPERATOR AIK BATU | C23: 4 | E23: 124 | Q23: 154187 | S23: 16000 | T23: 5464385 | U23: 4190313.2 | V23: 26028565 | AL23: =AK23/1050 -> 0
B25: PHASE IA HARVESTING KHT AIK KUNDO | C25: 0 | AL25: =AK25/1050 -> 0
B27: PHASE IA MAINTENANCE KHT AIK KUNDO | C27: 66 | E27: 1967 | Q27: 13690 | S27: 260000 | T27: 0 | U27: 4033456.5 | V27: 2.572098e+08 | AL27: =AK27/1050 -> 0
B29: PHASE IA OPERATOR AIK KUNDO | C29: 2 | E29: 59 | Q29: 16020 | S29: 8000 | T29: 1289450 | U29: 2588134.6 | V29: 11735747 | AL29: =AK29/1050 -> 0
B31: PHASE IA HARVESTING AIK KUNDO masa percobaan | AL31: =AK31/1050 -> 0
B33: PHASE 1A MAINTENANCE AIR KUNDO masa percobaan | C33: 2 | E33: 62 | Q33: 0 | S33: 0 | T33: 0 | U33: 123244.5 | V33: 7824756.5
B35: TOTAL | C35: =SUM(C8:C34) -> 193 | D35: =SUM(D8:D34) -> 0 | E35: =SUM(E8:E34) -> 5824 | F35: =SUM(F8:F34) -> 0 | G35: =SUM(G8:G34) -> 0 | H35: =SUM(H8:H34) -> 0 | I35: =SUM(I8:I34) -> 0 | J35: =SUM(J8:J34) -> 0 | ... V35: =SUM(V8:V34) -> 8.7837028e+08 | X35: =#REF!/#REF! -> #REF! | Y35: Upah rata-rata/ hk | AA35: =AA8 -> 878370277 | AB35: =AB8 -> 0.0050001144 | AD35: =SUM(AD8:AD34) -> 15466750 | AF35: =SUM(AF9:AF34) -> 1882568 | AG35: =SUM(AG9:AG34) -> 14245374 | AH35: =SUM(AH9:AH34) -> 0 | AJ35: =SUM(AJ9:AJ34) -> 21646220 | AK35: =SUM(AK8:AK34) -> 25173750 | AL35: =SUM(AL8:AL34) -> 23975
B41: DIBUAT OLEH : | C41: DIPERIKSA OLEH : | L41: DISETUJUI OLEH :
B50: PT. REBINMAS JAYA
B51: =B4 -> DENOMINATION FOR OKTOBER 2025
B53: ESTATE/DIVISION | C53: WORKERS | D53: HK | G53: JUMLAH | H53: BERAS | I53: JABATAN | J53: MASA KERJA | K53: TUNJ. LAIN | L53: JKK | M53: KOREKSI | N53: JKK | O53: BPJS | Q53: TOTAL PPH 21 | R53: TOTAL PPH | S53: POT | T53: =T6 -> TOTAL PREMI | U53: =U6 -> TOTAL LEMBUR | V53: TOTAL MANUAL | W53: Upah & Astek | X53: Total & | AA53: THUMB PRINT | AB53: SELISIH | AD53: PRUNNING | AF53: Koreksi | AG53: Insentif | AH53: Kontanan | AJ53: PREMI | AN53: Pokok Prunning
D54: Ifest | E54: Cekroll | F54: Selisih | L54: JKM | N54: JKM | O54: Kes & Pen | Q54: =Q7 -> (MASA OKTOBER 2025) | R54: EX-GRATIA | S54: SPSI | X54: Rata-rata | AJ54: TBS | AK54: BRDL
AA55: 695391805 | AB55: =V90-AA90 -> 0.44148147
B56: PHASE IB OPERATOR GUNUNG RUM | C56: 6 | E56: 185 | Q56: 97618 | S56: 24000 | T56: 2020515 | U56: 5321921.8 | V56: 31980345 | AL56: =AK56/1050 -> 0
B58: PHASE IB HARVESTING KHT GUNUNG RUM | AL58: =AK58/1050 -> 0 | AN58: =AD58/550 -> 0
AN59: =AD59/550 -> 0
B60: PHASE IB MAINTENANCE KHT GUNUNG RUM | C60: 61 | E60: 1831 | Q60: 86107 | S60: 240000 | T60: 0 | U60: 3249173.2 | V60: 2.3875984e+08 | AL60: =AK60/1050 -> 0 | AN60: =AD60/550 -> 0
AN61: =AD61/550 -> 0
B62: PHASE IB MAINTENANCE GUNUNG RUM masa percobaan | AL62: =AK62/1050 -> 0 | AN62: =AD62/550 -> 0
AL63: =AK63/1050 -> 0
B64: PHASE IB HARVESTING KHT GUNUNG RUM | C64: 22 | E64: 654 | Q64: 28278 | S64: 88000 | T64: =2328889+AM64 -> 8987701 | U64: 0 | V64: 85913667 | AD64: 0 | AF64: 7496127.4 | AG64: 2328888.9 | AJ64: 1340562 | AK64: 5318250 | AL64: =AK64/1050 -> 5065 | AM64: =AJ64+AK64 -> 6658812
B66: PHASE IB HARVESTING GUNUNG RUM ( masa percobaan ) | AL66: =AK66/1050 -> 0
B68: PHASE IB MAINTENANCE KHT PADANG TEMBALUN | C68: 72 | E68: 2187 | Q68: 157349 | S68: 284000 | T68: 0 | U68: 5277105.4 | V68: 2.8630553e+08 | AL68: =AK68/1050 -> 0 | AM68: =AJ68+AK68 -> 0
B70: PHASE IB PLASMA PADANG TEMBALUN
B72: PHASE IB MAINTENANCE PADANG TEMBALUN masa percobaan | C72: 6 | E72: 182 | Q72: 0 | S72: 0 | T72: 0 | U72: 0 | V72: 22587656 | AL72: =AK72/1050 -> 0
B74: PHASE IB OPERATOR PADANG TEMBALUN | C74: 5 | E74: 155 | Q74: 181988 | S74: 20000 | T74: 2287431 | U74: 7237813.6 | V74: 29844767 | AL74: =AK74/1050 -> 0
AL76: =AK76/1050 -> 0
AL78: =AK78/1050 -> 0
B80: PHASE IB HARVESTING PADANG TEMBALUN | AL80: =AK80/1050 -> 0
AL82: =AK82/1050 -> 0
AL84: =AK84/1050 -> 0
AL86: =AK86/1050 -> 0 | AP86: 795000
AL88: =AK88/1050 -> 0
B90: TOTAL | C90: =SUM(C56:C89) -> 172 | D90: =SUM(D56:D89) -> 0 | E90: =SUM(E56:E89) -> 5194 | F90: =D90-E90 -> -5194 | G90: =SUM(G56:G89) -> 0 | H90: =SUM(H56:H89) -> 0 | I90: =SUM(I56:I89) -> 0 | J90: =SUM(J56:J89) -> 0 | Q90: =SUM(Q56:Q89) -> 551340 | R90: =SUM(R56:R89) -> 0 | S90: =SUM(S56:S89) -> 656000 | T90: =SUM(T56:T89) -> 13295647 | U90: =SUM(U56:U89) -> 21086014 | V90: =SUM(V56:V89) -> 6.9539181e+08 | AA90: =AA55 -> 695391805 | AB90: =AB55 -> 0.44148147 | AD90: =SUM(AD56:AD89) -> 0 | AF90: =SUM(AF55:AF89) -> 7496127.4 | AG90: =SUM(AG55:AG89) -> 2328888.9 | AH90: =SUM(AH55:AH89) -> 0 | AJ90: =SUM(AJ58:AJ89) -> 1340562 | AK90: =SUM(AK58:AK89) -> 5318250 | AL90: =AK90/1050 -> 5065 | AN90: =SUM(AN54:AN89) -> 0
B96: DIBUAT OLEH : | C96: DIPERIKSA OLEH : | L96: DISETUJUI OLEH :
B105: PT. REBINMAS JAYA
B106: =B4 -> DENOMINATION FOR OKTOBER 2025
B108: ESTATE/DIVISION | C108: WORKERS | D108: HK | G108: JUMLAH | H108: BERAS | I108: JABATAN | J108: MASA KERJA | Q108: TOTAL PPH 21 | R108: TOTAL PPH | S108: POT | T108: =T6 -> TOTAL PREMI | U108: =U6 -> TOTAL LEMBUR | V108: TOTAL MANUAL | W108: Upah & Astek | X108: Total & | AA108: THUMB PRINT | AB108: SELISIH | AD108: PRUNNING | AF108: Koreksi | AG108: Insentif | AH108: Kontanan+piket lebaran | AJ108: PREMI
D109: Ifest | E109: Cekroll | F109: Selisih | Q109: =Q54 -> (MASA OKTOBER 2025) | R109: EX-GRATIA | S109: SPSI | X109: Rata-rata | AJ109: TBS | AK109: BRDL
AA110: 804360365 | AB110: =V135-AA135 -> -1.7399998
B111: PHASE IIA MAINTENANCE KHT AIK JANGKAT 1 | C111: 29 | E111: 892 | Q111: 53637 | S111: 100000 | T111: 250000 | U111: 3708539 | V111: 1.1915608e+08 | AL111: =AK111/1050 -> 0
B113: PHASE IIA HARVESTING KHT AIK JANGKAT 1 | C113: 20 | E113: 614 | Q113: 111916 | S113: 36000 | T113: =2716667+3450500+AM113 -> 15958944 | U113: 0 | V113: 99926945 | AD113: 3709000 | AG113: 1292317 | AJ113: 4023777 | AK113: 5768000 | AL113: =AK113/1050 -> 5493.3333 | AM113: =AJ113+AK113 -> 9791777
B115: PHASE IIA OPERATOR AIK JANGKAT | C115: 4 | E115: 124 | Q115: 253539 | S115: 16000 | T115: 5476085 | U115: 5411555.3 | V115: 27206945 | AL115: =AK115/1050 -> 0
B117: PHASE IIA HARVESTING AIK JANGKAT ( masa percobaan ) | AL117: =AK117/1050 -> 0 | AM117: =AJ117+AK117 -> 0
AN118: KLAIM TIKET
B119: PHASE IIA HARVESTING KHT AIK BETANGAN | C119: 31 | E119: 940 | Q119: 0 | S119: 120000 | T119: =2701667+AM119 -> 12495208 | U119: 380937.56 | V119: 1.3424178e+08 | AD119: 0 | AF119: 721566 | AG119: 533407.5 | AJ119: 355791 | AK119: 9437750 | AL119: =AK119/1050 -> 8988.3333 | AM119: =AJ119+AK119 -> 9793541
B121: PHASE IIA MAINTENANCE KHT AIK BETANGAN 2 | C121: 21 | E121: 644 | Q121: 86231 | S121: 80000 | T121: 0 | U121: 2711379 | V121: 85609954 | AL121: =AK121/1050 -> 0
B123: PHASE IIA OPERATOR AIK BETANGAN | C123: 6 | E123: 186 | Q123: 284480 | S123: 24000 | T123: 6814360 | U123: 6834468 | V123: 37964924 | AL123: =AK123/1050 -> 0
B125: PHASE IIA HARVESTING Masa Percobaan AIK BETANGAN | AL125: =AK125/1050 -> 0 | AM125: =AJ125+AK125 -> 0
B127: PHASE IIA MAINTENANCE KHT AIK PAPAN 3 | C127: 26 | E127: 793 | Q127: 0 | S127: 104000 | T127: 0 | U127: 526590.14 | V127: 1.0287413e+08 | AL127: =AK127/1050 -> 0
B129: PHASE IIA OPERATOR AIK PAPAN | C129: 6 | E129: 185 | Q129: 338023 | S129: 24000 | T129: 9685250 | U129: 7125773.2 | V129: 41070496 | AL129: =AK129/1050 -> 0
B131: PHASE IIA HARVESTING AIK PAPAN masa percobaan | C131: 2 | E131: 59 | Q131: 0 | S131: 0 | T131: =AM131 -> 395500 | U131: 0 | V131: 7378234 | AD131: 91000 | AF131: 422118 | AG131: 0 | AJ131: 0 | AK131: 395500 | AL131: =AK131/1050 -> 376.66667 | AM131: =AJ131+AK131 -> 395500
AN132: KLAIM TIKET
B133: PHASE IIA HARVESTING AIK PAPAN 3 | C133: 31 | E133: 933 | Q133: 85826 | S133: 100000 | T133: =2769444+AM133 -> 18769183 | V133: 1.4893088e+08 | AD133: 12482050 | AF133: 3954132 | AG133: 991468.45 | AJ133: 522739 | AK133: 15477000 | AL133: =AK133/1050 -> 14740 | AM133: =AJ133+AK133 -> 15999739
B135: TOTAL | C135: =SUM(C111:C134) -> 176 | D135: =SUM(D111:D134) -> 0 | E135: =SUM(E111:E134) -> 5370 | F135: =SUM(F111:F134) -> 0 | Q135: =SUM(Q111:Q134) -> 1213652 | S135: =SUM(S111:S134) -> 604000 | T135: =SUM(T111:T134) -> 69844530 | U135: =SUM(U111:U134) -> 26699242 | V135: =SUM(V111:V134) -> 8.0436036e+08 | AA135: =AA110 -> 804360365 | AB135: =AB110 -> -1.7399998 | AD135: =SUM(AD111:AD134) -> 16282050 | AF135: =SUM(AF111:AF134) -> 5097816 | AG135: =SUM(AG110:AG134) -> 2817193 | AH135: =SUM(AH110:AH134) -> 0 | AJ135: =SUM(AJ111:AJ134) -> 4902307 | AK135: =SUM(AK111:AK134) -> 31078250 | AL135: =AK135/1050 -> 29598.333
B141: DIBUAT OLEH : | C141: DIPERIKSA OLEH : | L141: DISETUJUI OLEH :
B149: PT. REBINMAS JAYA
B150: =B4 -> DENOMINATION FOR OKTOBER 2025
B152: ESTATE/DIVISION | C152: WORKERS | D152: HK | G152: JUMLAH | H152: BERAS | I152: JABATAN | J152: MASA KERJA | K152: TUNJ. LAIN | L152: JKK | M152: KOREKSI | N152: JKK | O152: BPJS | Q152: TOTAL PPH 21 | R152: TOTAL PPH | S152: POT | T152: =T108 -> TOTAL PREMI | U152: =U108 -> TOTAL LEMBUR | V152: TOTAL MANUAL | W152: Upah & Astek | X152: Total & | AA152: THUMB PRINT | AB152: SELISIH | AD152: PRUNNING | AF152: Koreksi | AG152: Insentif | AH152: Kontanan+Piket lebaran | AJ152: PREMI
D153: Ifest | E153: Cekroll | F153: Selisih | L153: JKM | N153: JKM | O153: Kes & Pen | Q153: =Q109 -> (MASA OKTOBER 2025) | R153: EX-GRATIA | S153: SPSI | X153: Rata-rata | AJ153: TBS | AK153: BRDL
AA154: 594505798 | AB154: =V175-AA154 -> 0.47682667 | AN154: pot. Tiket
B155: PHASE IIB HARVESTING AIR LIMPAS | C155: 36 | E155: 1092 | Q155: 465196 | S155: 140000 | T155: =7441815+AM155 -> 34716535 | U155: 1109200.6 | V155: 1.7884745e+08 | AF155: 2226891.3 | AG155: 4752848.8 | AJ155: 6453220 | AK155: 20821500 | AL155: =AK155/1050 -> 19830 | AM155: =AJ155+AK155 -> 27274720
B157: PHASE IIB MAINTENANCE AIR LIMPAS | C157: 21 | E157: 642 | Q157: 0 | S157: 84000 | T157: 0 | U157: 1400505.8 | V157: 84050302 | AL157: =AK157/1050 -> 0
AN158: Pot. Pembuatan SIM
B159: PHASE IIB OPERATOR AIK LIMPAS | C159: 8 | E159: 241 | Q159: 398647 | S159: 32000 | T159: 12519235 | U159: 7730791.9 | V159: 51736648 | AL159: =AK159/1050 -> 0
B161: PHASE IIB HARVESTING AIR LIMPAS masa percobaan | AL161: =AK161/1050 -> 0
B163: PHASE IIB MAINTENANCE AIK KUNYAL | C163: 22 | E163: 678 | Q163: 54695 | S163: 84000 | T163: 467358 | U163: 3876599.7 | V163: 92265765 | AL163: =AK163/1050 -> 0
B165: PHASE IIB MAINT AIK KUNYAL masa percobaan | AL165: =AK165/1050 -> 0
AN166: Pot. Pembuatan SIM
B167: PHASE IIB OPERATOR AIK KUNYAL | C167: 5 | E167: 153 | Q167: 257434 | S167: 20000 | T167: 4391696 | U167: 6565570.8 | V167: 30972483 | AL167: =AK167/1050 -> 0
AN168: pot. Tiket
B169: PHASE IIB HARVESTING AIR KUNYAL | C169: 27 | E169: 828 | Q169: 136062 | S169: 108000 | T169: =3489259+431660+AM169 -> 15803652 | U169: 459365.88 | V169: 1.3168724e+08 | AD169: 8599500 | AF169: 2022409.9 | AG169: 1154883.5 | AJ169: 834983 | AK169: 11047750 | AL169: =AK169/1050 -> 10521.667 | AM169: =AJ169+AK169 -> 11882733 | AN169: 766770
B171: PHASE IIB HARVESTING AIR KUNYAL ( masa percobaan ) | AL171: =AK171/1050 -> 0
B173: PHASE IIB HARVESTING ( Plasma ) | C173: 6 | E173: 186 | Q173: 0 | S173: 24000 | T173: =AM173 -> 761250 | U173: 0 | V173: 24945906 | AD173: 0 | AE173: 0 | AF173: 0 | AG173: 0 | AJ173: 0 | AK173: 761250 | AL173: =AK173/1050 -> 725 | AM173: =AJ173+AK173 -> 761250
B175: TOTAL | C175: =SUM(C154:C174) -> 125 | D175: =SUM(D155:D174) -> 0 | E175: =SUM(E154:E174) -> 3820 | F175: =D175-E175 -> -3820 | G175: =SUM(G154:G174) -> 0 | H175: =SUM(H154:H174) -> 0 | I175: =SUM(I154:I174) -> 0 | J175: =SUM(J154:J174) -> 0 | K175: =SUM(K154:K174) -> 0 | L175: =SUM(L154:L174) -> 0 | M175: =SUM(M154:M174) -> 0 | N175: =SUM(N154:N174) -> 0 | P175: =SUM(P154:P174) -> 0 | Q175: =SUM(Q154:Q174) -> 1312034 | R175: =SUM(R154:R174) -> 0 | S175: =SUM(S154:S174) -> 492000 | T175: =SUM(T154:T174) -> 68659726 | U175: =SUM(U154:U174) -> 21142035 | V175: =SUM(V154:V174) -> 5.945058e+08 | X175: =#REF!/#REF! -> #REF! | Y175: Upah rata-rata / HK | AA175: =AA154 -> 594505798 | AB175: =AB154 -> 0.47682667 | AD175: =SUM(AD155:AD174) -> 8599500 | AF175: =SUM(AF155:AF174) -> 4249301.2 | AG175: =SUM(AG155:AG174) -> 5907732.3 | AH175: =SUM(AH154:AH174) -> 0 | AJ175: =SUM(AJ155:AJ174) -> 7288203 | AK175: =SUM(AK155:AK174) -> 32630500 | AL175: =AK175/1050 -> 31076.667
AH179: =AH178-AH175 -> 0
B182: DIBUAT OLEH : | C182: DIPERIKSA OLEH : | L182: DISETUJUI OLEH :
B190: PT. REBINMAS JAYA
B191: =B4 -> DENOMINATION FOR OKTOBER 2025
B193: ESTATE/DIVISION | C193: WORKERS | D193: HK | G193: JUMLAH | H193: BERAS | I193: JABATAN | J193: MASA KERJA | K193: TUNJ. LAIN | L193: JKK | M193: KOREKSI | N193: JKK | O193: BPJS | Q193: TOTAL PPH 21 | R193: TOTAL PPH | S193: POT | T193: =T152 -> TOTAL PREMI | U193: =U152 -> TOTAL LEMBUR | V193: TOTAL MANUAL | W193: Upah & Astek | X193: Total & | AA193: THUMB PRINT | AB193: SELISIH | AD193: PRUNNING | AF193: Koreksi | AG193: Insentif | AH193: Kontanan | AJ193: PREMI
D194: Ifest | E194: Cekroll | F194: Selisih | L194: JKM | N194: JKM | O194: Kes & Pen | Q194: =Q153 -> (MASA OKTOBER 2025) | R194: EX-GRATIA | S194: SPSI | X194: Rata-rata | AJ194: TBS | AK194: BRDL
AA195: 966927557 | AB195: =V226-AA195 -> 0.39999998 | AN195: POT. UANG TIKET
B196: DME HARVESTING KHT AIK CENDONG | C196: 30 | E196: 852 | Q196: 819606 | S196: 116000 | T196: =6550000+AM196 -> 27905877 | U196: 0 | V196: 162586398 | AD196: 21342200 | AF196: 2768689 | AG196: 4050000 | AJ196: 4130627 | AK196: 17225250 | AL196: =AK196/1050 -> 16405 | AM196: =AJ196+AK196 -> 21355877 | AN196: 3381632
AN197: POT. UANG TIKET
B198: DME HARVESTING masa percobaan AIK CENDONG | C198: 1 | E198: 29 | Q198: 0 | S198: 4000 | T198: =AM198 -> 1739611 | U198: 0 | V198: 5706700 | AD198: 212300 | AF198: 133527 | AG198: 300000 | AJ198: 771861 | AK198: 967750 | AL198: =AK198/1050 -> 921.66667 | AM198: =AJ198+AK198 -> 1739611
B200: DME OPERATOR AIK CENDONG | AL200: =AK200/1050 -> 0
B202: DME MAINTENANCE KHT AIK CENDONG | C202: 29 | E202: 897 | Q202: 52407 | S202: 116000 | T202: 0 | U202: 3327601 | V202: 1.1940379e+08 | AL202: =AK202/1050 -> 0
B204: DME MAINTENANCE KHT AIK KANDIS | C204: 33 | E204: 1007 | Q204: 33174 | S204: 132000 | T204: 0 | U204: 3237969 | V204: 132985633 | AL204: =AK204/1050 -> 0
...

Sheet Sheet8
A3: SUMMARY - WAGES MEI 2022
A6: ESTATE/DIVISION | B6: 26-30 April 2022 | C6: 01-31 Mei 2022 | D6: TOTAL
A8: PHASE IA | B8: 123600328 | C8: ='SEPTEMBER DIBAYAR OKT 2025 '!V522 -> 8.7837028e+08 | D8: =B8+C8 -> 1.0019706e+09
A10: PHASE IB | B10: 113089408 | C10: ='SEPTEMBER DIBAYAR OKT 2025 '!V524 -> 6.9539181e+08 | D10: =B10+C10 -> 8.0848121e+08
A12: PHASE IIA | B12: 1.2795668e+08 | C12: ='SEPTEMBER DIBAYAR OKT 2025 '!V526 -> 8.0436036e+08 | D12: =B12+C12 -> 9.3231704e+08
A14: PHASE IIB | B14: 85491957 | C14: ='SEPTEMBER DIBAYAR OKT 2025 '!V528 -> 5.945058e+08 | D14: =B14+C14 -> 6.7999776e+08
A16: DARUL MAKMUR | B16: 126346301 | C16: ='SEPTEMBER DIBAYAR OKT 2025 '!V530 -> 9.6692756e+08 | D16: =B16+C16 -> 1.0932739e+09
A18: WORKSHOP PGE | B18: 9966517 | C18: ='SEPTEMBER DIBAYAR OKT 2025 '!V532 -> 87891747 | D18: =B18+C18 -> 97858264
A20: INFRASTUKTUR | B20: 17796309 | C20: ='SEPTEMBER DIBAYAR OKT 2025 '!V534 -> 1.611283e+08 | D20: =B20+C20 -> 1.7892461e+08
A22: MILL PKS | C22: ='SEPTEMBER DIBAYAR OKT 2025 '!V538 -> 1234277949 | D22: =B22+C22 -> 1234277949
A24: MILL Bioplant | C24: ='SEPTEMBER DIBAYAR OKT 2025 '!V540 -> 0 | D24: =B24+C24 -> 0
A26: Sub Total | B26: 6.042475e+08 | C26: =SUM(C8:C25) -> 5.4228538e+09 | D26: =B26+C26 -> 6.0271013e+09
A28: ARE - A | B28: 96906533 | C28: ='SEPTEMBER DIBAYAR OKT 2025 '!V544 -> 6.866745e+08 | D28: =B28+C28 -> 7.8358103e+08
A30: ARE - B1 | B30: 89304800 | C30: ='SEPTEMBER DIBAYAR OKT 2025 '!V546 -> 6.7607006e+08 | D30: =B30+C30 -> 7.6537486e+08
A32: ARE - B2 | B32: 89209566 | C32: ='SEPTEMBER DIBAYAR OKT 2025 '!V548 -> 6.2822493e+08 | D32: =B32+C32 -> 7.1743449e+08
A34: ARE - C | B34: 1.8974675e+08 | C34: ='SEPTEMBER DIBAYAR OKT 2025 '!V550 -> 1.2824897e+09 | D34: =B34+C34 -> 1.4722365e+09
A36: WORKSHOP ARE | B36: 3546165.8 | C36: ='SEPTEMBER DIBAYAR OKT 2025 '!V552 -> 28906719 | D36: =B36+C36 -> 32452885
A38: TOTAL C/ROLL | B38: =SUM(B26:B37) -> 1.0729613e+09 | C38: =SUM(C26:C37) -> 8.7252197e+09 | D38: =SUM(D26:D37) -> 9.798181e+09
A40: BLT + AM | B40: 30426819 | C40: ='SEPTEMBER DIBAYAR OKT 2025 '!V556 -> 2.2267996e+08 | D40: =B40+C40 -> 2.5310678e+08

Sheet SUMMARY - WAGES IJL
A1: PT.IMPIAN JAYA LESTARI
A3: SUMMARY - WAGES OKTOBER 2025
A5: ESTATE/DIVISION | N5: WORKERS | Y5: WORKERS | Z5: TOTAL PPH PASAL 21 | AA5: TOTAL | AB5: TOTAL | AC5: TOTAL | AD5: TOTAL | AE5: TOTAL | AF5: TOTAL | AG5: THUMB PRINT | AH5: SELISIH | AI5: NAIK/TURUN
N6: JULI 2025 | O6: 100000 | P6: 50000 | Q6: 20000 | R6: 10000 | S6: 5000 | T6: 1000 | U6: 500 | V6: 100 | W6: 50 | X6: OTHERS | Y6: SEPT 2025 | Z6: (MASA SEPT 2025) | AA6: SPSI | AB6: PREMI OKT 2025 | AC6: PRUNNING | AD6: LEMBUR | AE6: SEPT 2025 | AF6: OKT 2025
A8: BLT + AM | N8: 43 | Y8: ='SEPTEMBER DIBAYAR OKT 2025 '!C556 -> 43 | Z8: ='SEPTEMBER DIBAYAR OKT 2025 '!Q556 -> 1269044 | AA8: ='SEPTEMBER DIBAYAR OKT 2025 '!S456 -> 430000 | AB8: ='SEPTEMBER DIBAYAR OKT 2025 '!T556 -> 43738652 | AC8: ='SEPTEMBER DIBAYAR OKT 2025 '!AD556 -> 0 | AD8: ='SEPTEMBER DIBAYAR OKT 2025 '!U556 -> 9994008.8 | AE8: 236957607 | AF8: ='SEPTEMBER DIBAYAR OKT 2025 '!V556 -> 2.2267996e+08 | AG8: ='SEPTEMBER DIBAYAR OKT 2025 '!AA556 -> 222679965 | AH8: ='SEPTEMBER DIBAYAR OKT 2025 '!AB556 -> -0.16000003 | AI8: =AF8-AE8 -> -14277642
A10: Grand Total | N10: 43 | O10: =SUM(O8:O9) -> 0 | P10: =SUM(P8:P9) -> 0 | Q10: =SUM(Q8:Q9) -> 0 | R10: =SUM(R8:R9) -> 0 | S10: =SUM(S8:S9) -> 0 | T10: =SUM(T8:T9) -> 0 | U10: =SUM(U8:U9) -> 0 | V10: =SUM(V8:V9) -> 0 | ... AD10: =SUM(AD8:AD9) -> 9994008.8 | AE10: =AE8 -> 236957607 | AF10: =SUM(AF8:AF9) -> 2.2267996e+08 | AG10: =SUM(AG8:AG9) -> 222679965 | AH10: =SUM(AH8:AH9) -> -0.16000003 | AI10: =SUM(AI8:AI9) -> -14277642
AD14: TONASE | AE14: 480.87 | AF14: 587.88 | AI14: =AF14-AE14 -> 107.01
A18: DIBUAT OLEH : | N18: DIPERIKSA OLEH: | AC18: DISETUJUI OLEH:
A62: PT.IMPIAN JAYA LESTARI
A63: =A3 -> SUMMARY - WAGES OKTOBER 2025
A64: 01-31 MEI 2022 & 26-30 APRIL 2022
A66: ESTATE/DIVISION | N66: WORKERS | Y66: WORKERS | Z66: TOTAL PPH PASAL 21 | AA66: TOTAL | AB66: TOTAL | AC66: TOTAL | AD66: TOTAL | AE66: TOTAL | AF66: TOTAL | AI66: NAIK/TURUN
N67: APR 2022 | O67: 100000 | P67: 50000 | Q67: 20000 | R67: 10000 | S67: 5000 | T67: 1000 | U67: 500 | V67: 100 | W67: 50 | X67: OTHERS | Y67: MEI 2022 | Z67: (MASA MEI 2022) | AA67: SPSI | AB67: PREMI 2022 | AC67: PRUNNING | AD67: LEMBUR | AE67: APR 2022 | AF67: MEI 2022
A69: BLT + AM | N69: 44 | Y69: =Y8 -> 43 | Z69: =Z8 -> 1269044 | AA69: =AA8 -> 430000 | AB69: =AB8 -> 43738652 | AC69: =AC8 -> 0 | AD69: =AD8 -> 9994008.8 | AE69: =145808894 -> 145808894 | AF69: =Sheet8!D40 -> 2.5310678e+08 | AI69: =AF69-AE69 -> 1.0729789e+08
A71: Grand Total | N71: 44 | Y71: =SUM(Y69:Y70) -> 43 | Z71: =SUM(Z69:Z70) -> 1269044 | AA71: =SUM(AA69:AA70) -> 430000 | AB71: =SUM(AB69:AB70) -> 43738652 | AC71: =SUM(AC69:AC70) -> 0 | AD71: =SUM(AD69:AD70) -> 9994008.8 | AE71: =SUM(AE69:AE70) -> 145808894 | AF71: =SUM(AF69:AF70) -> 2.5310678e+08 | AI71: =SUM(AI69:AI70) -> 1.0729789e+08
AD75: TONASE | AE75: 630.58 | AF75: 572.82 | AI75: =AF75-AE75 -> -57.76
A78: DIBUAT OLEH : | N78: DIPERIKSA OLEH: | AC78: DISETUJUI OLEH:

Sheet SUMMARY - WAGES PT.RJ
A1: PT. REBINMAS JAYA
A2: ='SUMMARY - WAGES IJL'!A3 -> SUMMARY - WAGES OKTOBER 2025
A4: ESTATE/DIVISION | N4: WORKERS | Y4: WORKERS | Z4: TOTAL PPH 21 | AA4: POT | AB4: TOTAL | AC4: TOTAL | AD4: TOTAL | AE4: TOTAL | AF4: SEPTEMBER 2025 | AH4: OKTOBER 2025 | AK4: SELISIH | AL4: NAIK/TURUN | AP4: SELISIH | AQ4: NAIK/TURUN | AT4: PG IA | AU4: 2008.47 | AW4: Ton | AX4: =AU4/1000 -> 2.00847
N5: SEPT 2025 | O5: 100000 | P5: 50000 | Q5: 20000 | R5: 10000 | S5: 5000 | T5: 1000 | U5: 500 | V5: 100 | W5: 50 | X5: OTHERS | Y5: OKT 2025 | Z5: (MASA OKT 2025) | AA5: SPSI | AB5: PAJAK EX-GRATIA | AC5: PREMI OKT 2025 | AD5: PRUNNING | AE5: LEMBUR | AF5: GAJI | AG5: TBS ( Ton ) | AH5: GAJI | AI5: TBS ( Ton ) | AJ5: THUMB PRINT | AT5: PG IB | AW5: Ton | AX5: =AU5/1000 -> 0
AT6: PG IIA | AW6: Ton | AX6: =AU6/1000 -> 0
A7: PHASE IA | N7: 195 | Y7: ='SEPTEMBER DIBAYAR OKT 2025 '!C522 -> 193 | Z7: ='SEPTEMBER DIBAYAR OKT 2025 '!Q522 -> 1437096 | AA7: ='SEPTEMBER DIBAYAR OKT 2025 '!S522 -> 676000 | AC7: ='SEPTEMBER DIBAYAR OKT 2025 '!T522 -> 74684519 | AD7: ='SEPTEMBER DIBAYAR OKT 2025 '!AD522 -> 15466750 | AE7: ='SEPTEMBER DIBAYAR OKT 2025 '!U522 -> 27954094 | AF7: 9.0199714e+08 | AG7: 1204.65 | AH7: ='SEPTEMBER DIBAYAR OKT 2025 '!V522 -> 8.7837028e+08 | AI7: 1480.67 | AJ7: ='SEPTEMBER DIBAYAR OKT 2025 '!AA522 -> 878370277 | AK7: ='SEPTEMBER DIBAYAR OKT 2025 '!AB522 -> 0.0050001144 | AL7: =AH7-AF7 -> -23626867 | AP7: =AH7-AJ7 -> 0.0050001144 | AQ7: =AH7-AF7 -> -23626867 | AT7: PG IIB | AW7: Ton | AX7: =AU7/1000 -> 0
AJ8: ='SEPTEMBER DIBAYAR OKT 2025 '!AA523 -> 0 | AK8: ='SEPTEMBER DIBAYAR OKT 2025 '!AB523 -> 0 | AL8: =AH8-AF8 -> 0 | AT8: DME A | AW8: Ton | AX8: =AU8/1000 -> 0
A9: PHASE IB | N9: 171 | Y9: ='SEPTEMBER DIBAYAR OKT 2025 '!C524 -> 172 | Z9: ='SEPTEMBER DIBAYAR OKT 2025 '!Q524 -> 551340 | AA9: ='SEPTEMBER DIBAYAR OKT 2025 '!S524 -> 656000 | AC9: ='SEPTEMBER DIBAYAR OKT 2025 '!T524 -> 13295647 | AD9: ='SEPTEMBER DIBAYAR OKT 2025 '!AD524 -> 0 | AE9: ='SEPTEMBER DIBAYAR OKT 2025 '!U524 -> 21086014 | AF9: 6.722109e+08 | AG9: 162.57 | AH9: ='SEPTEMBER DIBAYAR OKT 2025 '!V524 -> 6.9539181e+08 | AI9: 231.69 | AJ9: ='SEPTEMBER DIBAYAR OKT 2025 '!AA524 -> 695391805 | AK9: ='SEPTEMBER DIBAYAR OKT 2025 '!AB524 -> 0.44148147 | AL9: =AH9-AF9 -> 23180910 | AP9: =AH9-AJ9 -> 0.44148147 | AQ9: =AH9-AF9 -> 23180910 | AT9: DME B | AW9: Ton
AJ10: ='SEPTEMBER DIBAYAR OKT 2025 '!AA525 -> 0 | AK10: ='SEPTEMBER DIBAYAR OKT 2025 '!AB525 -> 0 | AL10: =AH10-AF10 -> 0 | AU10: =SUM(AU4:AU9) -> 2008.47 | AW10: Ton
A11: PHASE IIA | N11: 177 | Y11: ='SEPTEMBER DIBAYAR OKT 2025 '!C526 -> 176 | Z11: ='SEPTEMBER DIBAYAR OKT 2025 '!Q526 -> 1213652 | AA11: ='SEPTEMBER DIBAYAR OKT 2025 '!S526 -> 604000 | AC11: ='SEPTEMBER DIBAYAR OKT 2025 '!T526 -> 69844530 | AD11: ='SEPTEMBER DIBAYAR OKT 2025 '!AD526 -> 16282050 | AE11: ='SEPTEMBER DIBAYAR OKT 2025 '!U526 -> 26699242 | AF11: 8.0045532e+08 | AG11: 1241.79 | AH11: ='SEPTEMBER DIBAYAR OKT 2025 '!V526 -> 8.0436036e+08 | AI11: 1501.58 | AJ11: ='SEPTEMBER DIBAYAR OKT 2025 '!AA526 -> 804360365 | AK11: ='SEPTEMBER DIBAYAR OKT 2025 '!AB526 -> -1.7399998 | AL11: =AH11-AF11 -> 3905046 | AP11: =AH11-AJ11 -> -1.7399998 | AQ11: =AH11-AF11 -> 3905046
AJ12: ='SEPTEMBER DIBAYAR OKT 2025 '!AA527 -> 0 | AK12: ='SEPTEMBER DIBAYAR OKT 2025 '!AB527 -> 0 | AL12: =AH12-AF12 -> 0 | AT12: ARE A | AW12: Ton
A13: PHASE IIB | N13: 124 | Y13: ='SEPTEMBER DIBAYAR OKT 2025 '!C528 -> 125 | Z13: ='SEPTEMBER DIBAYAR OKT 2025 '!Q528 -> 1312034 | AA13: ='SEPTEMBER DIBAYAR OKT 2025 '!S528 -> 492000 | AC13: ='SEPTEMBER DIBAYAR OKT 2025 '!T528 -> 68659726 | AD13: ='SEPTEMBER DIBAYAR OKT 2025 '!AD528 -> 8599500 | AE13: ='SEPTEMBER DIBAYAR OKT 2025 '!U528 -> 21142035 | AF13: 6.3890182e+08 | AG13: 1132.97 | AH13: ='SEPTEMBER DIBAYAR OKT 2025 '!V528 -> 5.945058e+08 | AI13: 1433.46 | AJ13: ='SEPTEMBER DIBAYAR OKT 2025 '!AA528 -> 594505798 | AK13: ='SEPTEMBER DIBAYAR OKT 2025 '!AB528 -> 0.47682667 | AL13: =AH13-AF13 -> -44396022 | AP13: =AH13-AJ13 -> 0.47682667 | AQ13: =AH13-AF13 -> -44396022 | AT13: ARE B1 | AW13: Ton
AJ14: ='SEPTEMBER DIBAYAR OKT 2025 '!AA529 -> 0 | AK14: ='SEPTEMBER DIBAYAR OKT 2025 '!AB529 -> 0 | AL14: =AH14-AF14 -> 0 | AT14: ARE B2 | AW14: Ton
A15: DARUL MAKMUR | N15: 204 | Y15: ='SEPTEMBER DIBAYAR OKT 2025 '!C530 -> 205 | Z15: ='SEPTEMBER DIBAYAR OKT 2025 '!Q530 -> 2694867 | AA15: ='SEPTEMBER DIBAYAR OKT 2025 '!S530 -> 812000 | AC15: ='SEPTEMBER DIBAYAR OKT 2025 '!T530 -> 110461585 | AD15: ='SEPTEMBER DIBAYAR OKT 2025 '!AD530 -> 45629800 | AE15: ='SEPTEMBER DIBAYAR OKT 2025 '!U530 -> 25029838 | AF15: 9.4818318e+08 | AG15: 2224.25 | AH15: ='SEPTEMBER DIBAYAR OKT 2025 '!V530 -> 9.6692756e+08 | AI15: 2564.16 | AJ15: ='SEPTEMBER DIBAYAR OKT 2025 '!AA530 -> 966927557 | AK15: ='SEPTEMBER DIBAYAR OKT 2025 '!AB530 -> 0.39999998 | AL15: =AH15-AF15 -> 18744380 | AP15: =AH15-AJ15 -> 0.39999998 | AQ15: =AH15-AF15 -> 18744380 | AT15: ARE C | AW15: Ton
AJ16: ='SEPTEMBER DIBAYAR OKT 2025 '!AA531 -> 0 | AK16: ='SEPTEMBER DIBAYAR OKT 2025 '!AB531 -> 0 | AL16: =AH16-AF16 -> 0 | AU16: =SUM(AU12:AU15) -> 0 | AW16: Ton
A17: WORKSHOP PGE | N17: 14 | Y17: ='SEPTEMBER DIBAYAR OKT 2025 '!C532 -> 14 | Z17: ='SEPTEMBER DIBAYAR OKT 2025 '!Q532 -> 614448 | AA17: ='SEPTEMBER DIBAYAR OKT 2025 '!S532 -> 24000 | AC17: ='SEPTEMBER DIBAYAR OKT 2025 '!T532 -> 0 | AD17: ='SEPTEMBER DIBAYAR OKT 2025 '!AD532 -> 0 | AE17: ='SEPTEMBER DIBAYAR OKT 2025 '!U532 -> 34289981 | AF17: 80279506 | AH17: ='SEPTEMBER DIBAYAR OKT 2025 '!V532 -> 87891747 | AJ17: ='SEPTEMBER DIBAYAR OKT 2025 '!AA532 -> 87891672 | AK17: ='SEPTEMBER DIBAYAR OKT 2025 '!AB532 -> 75.22 | AL17: =AH17-AF17 -> 7612241.2 | AP17: =AH17-AJ17 -> 75.22 | AQ17: =AH17-AF17 -> 7612241.2
AJ18: ='SEPTEMBER DIBAYAR OKT 2025 '!AA533 -> 0 | AK18: ='SEPTEMBER DIBAYAR OKT 2025 '!AB533 -> 0 | AL18: =AH18-AF18 -> 0
A19: INFRASTUKTUR | N19: 29 | Y19: ='SEPTEMBER DIBAYAR OKT 2025 '!C534 -> 29 | Z19: ='SEPTEMBER DIBAYAR OKT 2025 '!Q534 -> 1010024 | AA19: ='SEPTEMBER DIBAYAR OKT 2025 '!S534 -> 116000 | AC19: ='SEPTEMBER DIBAYAR OKT 2025 '!T534 -> 3117520 | AD19: ='SEPTEMBER DIBAYAR OKT 2025 '!AD534 -> 0 | AE19: ='SEPTEMBER DIBAYAR OKT 2025 '!U534 -> 45947790 | AF19: 163108145 | AH19: ='SEPTEMBER DIBAYAR OKT 2025 '!V534 -> 1.611283e+08 | AJ19: ='SEPTEMBER DIBAYAR OKT 2025 '!AA534 -> 161128233 | AK19: ='SEPTEMBER DIBAYAR OKT 2025 '!AB534 -> 67.28 | AL19: =AH19-AF19 -> -1979844.7 | AN19: =AF19-AJ19 -> 1979912 | AP19: =AH19-AJ19 -> 67.28 | AQ19: =AH19-AF19 -> -1979844.7 | AT19: G.TOTAL RMJ | AU19: =AU10+AU16 -> 2008.47 | AW19: Ton
AJ20: ='SEPTEMBER DIBAYAR OKT 2025 '!AA535 -> 0 | AK20: ='SEPTEMBER DIBAYAR OKT 2025 '!AB535 -> 0 | AL20: =AH20-AF20 -> 0
A21: NURSERY | N21: 18 | Y21: =+'SEPTEMBER DIBAYAR OKT 2025 '!C536 -> 18 | Z21: =+'SEPTEMBER DIBAYAR OKT 2025 '!Q536 -> 389632 | AA21: =+'SEPTEMBER DIBAYAR OKT 2025 '!S536 -> 72000 | AC21: =+'SEPTEMBER DIBAYAR OKT 2025 '!T536 -> 0 | AD21: 0 | AE21: =+'SEPTEMBER DIBAYAR OKT 2025 '!U536 -> 20581832 | AF21: 88815910 | AH21: ='SEPTEMBER DIBAYAR OKT 2025 '!V536 -> 90844468 | AJ21: ='SEPTEMBER DIBAYAR OKT 2025 '!AA536 -> 90844403 | AK21: ='SEPTEMBER DIBAYAR OKT 2025 '!AB536 -> 64.75 | AL21: =AH21-AF21 -> 2028557.8 | AP21: =AH21-AJ21 -> 64.75 | AQ21: =AH21-AF21 -> 2028557.8
AJ22: ='SEPTEMBER DIBAYAR OKT 2025 '!AA537 -> 0 | AK22: ='SEPTEMBER DIBAYAR OKT 2025 '!AB537 -> 0 | AL22: =AH22-AF22 -> 0
A23: MILL PKS | N23: 167 | Y23: ='SEPTEMBER DIBAYAR OKT 2025 '!C538 -> 167 | Z23: ='SEPTEMBER DIBAYAR OKT 2025 '!Q538 -> 15090000 | AA23: ='SEPTEMBER DIBAYAR OKT 2025 '!S538 -> 604000 | AB23: ……………………………………………………………………………………………………………………………………………………………………………………………………………………………………………………………………………………………………………………………………………………………………………………………………………………………………………………………………………………………………………………………………………………………………………………………………………………………………………………………………………………………….................................................................................................................................................................................................................................................................................................................................................................................................................................................................................................................................................................................................................................................................................................................................................................................................................................................................................................................................................................................................................................................................................................................................................................................................................................................. | AC23: ='SEPTEMBER DIBAYAR OKT 2025 '!T538 -> 0 | AD23: ='SEPTEMBER DIBAYAR OKT 2025 '!AD538 -> 0 | AE23: ='SEPTEMBER DIBAYAR OKT 2025 '!U538 -> 587803801 | AF23: 1207391151 | AH23: ='SEPTEMBER DIBAYAR OKT 2025 '!V538 -> 1234277949 | AJ23: ='SEPTEMBER DIBAYAR OKT 2025 '!AA538 -> 1234277949 | AK23: ='SEPTEMBER DIBAYAR OKT 2025 '!AB538 -> 0 | AL23: =AH23-AF23 -> 26886798 | AN23: =AF23-AJ23 -> -26886798 | AO23: =AF23/37*7 -> 2.2842535e+08 | AP23: =AH23-AJ23 -> 0 | AQ23: =AH23-AF23 -> 26886798 | AT23: PT.IJL | AW23: Ton
AJ24: ='SEPTEMBER DIBAYAR OKT 2025 '!AA539 -> 0 | AL24: =AH24-AF24 -> 0 | AX24: 1593610
A25: Mill Bioplant | N25: 0 | Y25: ='SEPTEMBER DIBAYAR OKT 2025 '!C540 -> 0 | Z25: ='SEPTEMBER DIBAYAR OKT 2025 '!Q540 -> 0 | AA25: 0 | AC25: 0 | AD25: 0 | AE25: ='SEPTEMBER DIBAYAR OKT 2025 '!U540 -> 0 | AF25: 0 | AH25: 0 | AJ25: ='SEPTEMBER DIBAYAR OKT 2025 '!AA540 -> 0 | AL25: =AH25-AF25 -> 0 | AQ25: =AH25-AF25 -> 0
A27: SUB TOTAL | N27: 1099 | O27: =SUM(O7:O23) -> 0 | P27: =SUM(P7:P23) -> 0 | Q27: =SUM(Q7:Q23) -> 0 | R27: =SUM(R7:R23) -> 0 | S27: =SUM(S7:S23) -> 0 | T27: =SUM(T7:T23) -> 0 | U27: =SUM(U7:U23) -> 0 | V27: =SUM(V7:V23) -> 0 | ... X27: =SUM(X7:X23) -> 0 | Y27: =SUM(Y7:Y26) -> 1099 | Z27: =SUM(Z7:Z26) -> 24313093 | AA27: =SUM(AA7:AA26) -> 4056000 | AB27: =SUM(AB7:AB26) -> 0 | AC27: =SUM(AC7:AC26) -> 340063527 | AD27: =SUM(AD7:AD26) -> 85978100 | AE27: =SUM(AE7:AE26) -> 8.1053463e+08 | AF27: 5.5013431e+09 | AG27: 5966.23 | AH27: =SUM(AH7:AH26) -> 5.5136983e+09 | AI27: =SUM(AI7:AI26) -> 7211.56 | AJ27: =SUM(AJ7:AJ26) -> 5513698059 | AK27: =SUM(AK7:AK26) -> 206.83331 | AL27: =SUM(AL7:AL26) -> 12355198 | AN27: =SUM(AN7:AN26) -> -24906886 | AO27: =SUM(AO7:AO26) -> 2.2842535e+08 | AP27: =SUM(AP7:AP26) -> 206.83331 | AQ27: =SUM(AQ7:AQ26) -> 12355198
AX28: 456610
A29: ARE - A | N29: 141 | Y29: ='SEPTEMBER DIBAYAR OKT 2025 '!C544 -> 140 | Z29: ='SEPTEMBER DIBAYAR OKT 2025 '!Q544 -> 2070117 | AA29: ='SEPTEMBER DIBAYAR OKT 2025 '!S544 -> 428000 | AC29: ='SEPTEMBER DIBAYAR OKT 2025 '!T544 -> 80854039 | AD29: ='SEPTEMBER DIBAYAR OKT 2025 '!AD544 -> 26023250 | AE29: ='SEPTEMBER DIBAYAR OKT 2025 '!U544 -> 24267963 | AF29: 6.6607642e+08 | AG29: 1428.52 | AH29: ='SEPTEMBER DIBAYAR OKT 2025 '!V544 -> 6.866745e+08 | AI29: 1825.69 | AJ29: ='SEPTEMBER DIBAYAR OKT 2025 '!AA544 -> 686674495 | AK29: ='SEPTEMBER DIBAYAR OKT 2025 '!AB544 -> 1.61 | AL29: =AH29-AF29 -> 20598080 | AN29: =AF29-AJ29 -> -20598078 | AO29: =AJ29-AF29 -> 20598078 | AP29: =AH29-AJ29 -> 1.61 | AQ29: =AH29-AF29 -> 20598080
AJ30: ='SEPTEMBER DIBAYAR OKT 2025 '!AA545 -> 0 | AK30: ='SEPTEMBER DIBAYAR OKT 2025 '!AB545 -> 0 | AL30: =AH30-AF30 -> 0 | AO30: =AJ30-AF30 -> 0
A31: ARE - B1 | N31: 139 | Y31: ='SEPTEMBER DIBAYAR OKT 2025 '!C546 -> 139 | Z31: ='SEPTEMBER DIBAYAR OKT 2025 '!Q546 -> 1653863 | AA31: ='SEPTEMBER DIBAYAR OKT 2025 '!S546 -> 556000 | AC31: ='SEPTEMBER DIBAYAR OKT 2025 '!T546 -> 71495925 | AD31: ='SEPTEMBER DIBAYAR OKT 2025 '!AD546 -> 29981600 | AE31: ='SEPTEMBER DIBAYAR OKT 2025 '!U546 -> 23931842 | AF31: 668699821 | AG31: 1697.47 | AH31: ='SEPTEMBER DIBAYAR OKT 2025 '!V546 -> 6.7607006e+08 | AI31: 1996.52 | AJ31: ='SEPTEMBER DIBAYAR OKT 2025 '!AA546 -> 676070056 | AK31: ='SEPTEMBER DIBAYAR OKT 2025 '!AB546 -> 0.35000002 | AL31: =AH31-AF31 -> 7370235.4 | AN31: =AF31-AJ31 -> -7370235 | AO31: =AJ31-AF31 -> 7370235 | AP31: =AH31-AJ31 -> 0.35000002 | AQ31: =AH31-AF31 -> 7370235.4
AJ32: ='SEPTEMBER DIBAYAR OKT 2025 '!AA547 -> 0 | AK32: ='SEPTEMBER DIBAYAR OKT 2025 '!AB547 -> 0 | AL32: =AH32-AF32 -> 0 | AO32: =AJ32-AF32 -> 0
A33: ARE - B2 | N33: 128 | Y33: ='SEPTEMBER DIBAYAR OKT 2025 '!C548 -> 124 | Z33: ='SEPTEMBER DIBAYAR OKT 2025 '!Q548 -> 2327867 | AA33: ='SEPTEMBER DIBAYAR OKT 2025 '!S548 -> 484000 | AC33: ='SEPTEMBER DIBAYAR OKT 2025 '!T548 -> 81408652 | AD33: ='SEPTEMBER DIBAYAR OKT 2025 '!AD548 -> 20870600 | AE33: ='SEPTEMBER DIBAYAR OKT 2025 '!U548 -> 34295584 | AF33: 622111088 | AG33: 1437.68 | AH33: ='SEPTEMBER DIBAYAR OKT 2025 '!V548 -> 6.2822493e+08 | AI33: 1806.87 | AJ33: ='SEPTEMBER DIBAYAR OKT 2025 '!AA548 -> 657131647 | AK33: ='SEPTEMBER DIBAYAR OKT 2025 '!AB548 -> -28906719 | AL33: =AH33-AF33 -> 6113840.3 | AN33: =AF33-AJ33 -> -35020559 | AO33: =AJ33-AF33 -> 35020559 | AP33: =AH33-AJ33 -> -28906719 | AQ33: =AH33-AF33 -> 6113840.3
AJ34: ='SEPTEMBER DIBAYAR OKT 2025 '!AA549 -> 0 | AK34: ='SEPTEMBER DIBAYAR OKT 2025 '!AB549 -> 0 | AL34: =AH34-AF34 -> 0 | AO34: =AJ34-AF34 -> 0
A35: ARE - C | N35: 264 | Y35: ='SEPTEMBER DIBAYAR OKT 2025 '!C550 -> 260 | Z35: ='SEPTEMBER DIBAYAR OKT 2025 '!Q550 -> 4625191 | AA35: ='SEPTEMBER DIBAYAR OKT 2025 '!S550 -> 996000 | AC35: ='SEPTEMBER DIBAYAR OKT 2025 '!T550 -> 1.5532868e+08 | AD35: ='SEPTEMBER DIBAYAR OKT 2025 '!AD550 -> 45028000 | AE35: ='SEPTEMBER DIBAYAR OKT 2025 '!U550 -> 57555184 | AF35: 1.2927092e+09 | AG35: 2211.9 | AH35: ='SEPTEMBER DIBAYAR OKT 2025 '!V550 -> 1.2824897e+09 | AI35: 2533.65 | AJ35: ='SEPTEMBER DIBAYAR OKT 2025 '!AA550 -> 1282489712 | AK35: ='SEPTEMBER DIBAYAR OKT 2025 '!AB550 -> 0.050000191 | AL35: =AH35-AF35 -> -10219467 | AN35: =AF35-AJ35 -> 10219467 | AO35: =AJ35-AF35 -> -10219467 | AP35: =AH35-AJ35 -> 0.050000191 | AQ35: =AH35-AF35 -> -10219467 | AS35: =AF7+AF9+AF11+AF13+AF15+AF17+AF19+AF29+AF31+AF33+AF35+AF37 -> 7.4815384e+09 | AT35: GAJI PT RJ
AJ36: ='SEPTEMBER DIBAYAR OKT 2025 '!AA551 -> 0 | AK36: ='SEPTEMBER DIBAYAR OKT 2025 '!AB551 -> 0 | AL36: =AH36-AF36 -> 0 | AO36: =AJ36-AF36 -> 0
A37: WORKSHOP ARE | N37: 5 | Y37: ='SEPTEMBER DIBAYAR OKT 2025 '!C552 -> 5 | Z37: ='SEPTEMBER DIBAYAR OKT 2025 '!Q552 -> 78309 | AA37: ='SEPTEMBER DIBAYAR OKT 2025 '!S552 -> 20000 | AC37: ='SEPTEMBER DIBAYAR OKT 2025 '!T552 -> 400000 | AD37: ='SEPTEMBER DIBAYAR OKT 2025 '!AD552 -> 0 | AE37: ='SEPTEMBER DIBAYAR OKT 2025 '!U552 -> 8358218 | AF37: 26805912 | AH37: ='SEPTEMBER DIBAYAR OKT 2025 '!V552 -> 28906719 | AJ37: 0 | AK37: ='SEPTEMBER DIBAYAR OKT 2025 '!AB552 -> 28906719 | AL37: =AH37-AF37 -> 2100807 | AN37: =AF37-AJ37 -> 26805912 | AO37: =AJ37-AF37 -> -26805912 | AP37: =AH37-AJ37 -> 28906719 | AQ37: =AH37-AF37 -> 2100807 | AS37: =AS35+AF23 -> 8.6889296e+09 | AT37: GAJI PT RJ + MILL
AL38: =AF38-AH38 -> 0
A39: SUB TOTAL | N39: 677 | O39: =SUM(O29:O37) -> 0 | P39: =SUM(P29:P37) -> 0 | Q39: =SUM(Q29:Q37) -> 0 | R39: =SUM(R29:R37) -> 0 | S39: =SUM(S29:S37) -> 0 | T39: =SUM(T29:T37) -> 0 | U39: =SUM(U29:U37) -> 0 | V39: =SUM(V29:V37) -> 0 | ... AB39: =SUM(AB29:AB37) -> 0 | AC39: =SUM(AC28:AC38) -> 3.894873e+08 | AD39: =SUM(AD28:AD38) -> 121903450 | AE39: =SUM(AE28:AE38) -> 1.4840879e+08 | AF39: 3.2764024e+09 | AG39: 6775.57 | AH39: =SUM(AH28:AH38) -> 3.3023659e+09 | AI39: =SUM(AI28:AI38) -> 8162.73 | AJ39: =SUM(AJ28:AJ38) -> 3302365910 | AK39: =SUM(AK28:AK38) -> 2.3800003 | AL39: =SUM(AL28:AL38) -> 25963496 | AN39: =SUM(AN28:AN38) -> -25963493 | AO39: =SUM(AO28:AO38) -> 25963493 | AP39: =SUM(AP28:AP38) -> 2.3800003 | AQ39: =SUM(AQ28:AQ38) -> 25963496
A41: Grand Total | N41: 1776 | O41: =O39+O27 -> 0 | P41: =P39+P27 -> 0 | Q41: =Q39+Q27 -> 0 | R41: =R39+R27 -> 0 | S41: =S39+S27 -> 0 | T41: =T39+T27 -> 0 | U41: =U39+U27 -> 0 | V41: =V39+V27 -> 0 | ... AE41: =AE39+AE27 -> 9.5894342e+08 | AF41: 8.7777455e+09 | AG41: 12741.8 | AH41: =AH39+AH27 -> 8.8160642e+09 | AI41: =AI39+AI27 -> 15374.29 | AJ41: =AJ39+AJ27 -> 8816063969 | AK41: =AK39+AK27 -> 209.21331 | AL41: =AL39+AL27 -> 38318694 | AN41: =AN39+AN27 -> -50870379 | AO41: =AO39+AO27 -> 2.5438885e+08 | AP41: =AP39+AP27 -> 209.21331 | AQ41: =AQ39+AQ27 -> 38318694
AI42: =#REF!-AG41 -> #REF! | AL42: =AG41-AI41 -> -2632.49
X43: ESTATE | AE43: ESTATE | AF43: =AF7+AF9+AF11+AF13+AF15+AF17+AF19+AF29+AF31+AF33+AF35+AF37+AF21 -> 7.5703543e+09 | AH43: =AH7+AH9+AH11+AH13+AH15+AH17+AH19+AH29+AH31+AH33+AH35+AH37+AH21 -> 7.5817862e+09 | AJ43: =AH41-AJ41 -> 209.21331 | AL43: =AF43-AH43 -> -11431896 | AO43: =AF43-#REF! -> #REF! | AS43: =AO43/#REF!*100 -> #REF!
AO44: =AF44-#REF! -> #REF!
X45: MILL | AE45: MILL | AF45: =AF23+AF25 -> 1207391151 | AH45: =AH23+AH25 -> 1234277949 | AL45: =AF45-AH45 -> -26886798 | AO45: =AF45-#REF! -> #REF! | AS45: =AO45/#REF!*100 -> #REF!
AO46: =AF46-#REF! -> #REF!
AE47: TONASE | AF47: =+AG41 -> 12741.8 | AH47: =+AI41 -> 15374.29 | AL47: =AF47-AH47 -> -2632.49 | AO47: =AF47-#REF! -> #REF! | AS47: =AO47/#REF!*100 -> #REF!
AG48: =AH47-AF47 -> 2632.49
A51: DIBUAT OLEH : | AA51: DIPERIKSA OLEH: | AF51: DISETUJUI OLEH:

Sheet IMPACT RMJ
A1: MONTH OF OKTOBER 2025
A3: Estate | B3: Luas Ha Productive | C3: Jumlah Karyawan | G3: Nilai Gaji ( All) | K3: Tonase TBS | M3: % Gaji Naik/Turun | P3: % TBS Naik / Turun
C4: 45931 | D4: 45901 | E4: Diff | F4: 45931 | G4: 45901 | H4: Diff | I4: 45931 | J4: 45901 | K4: Diff | L4: (Okt`25 - Sept`25 )
A5: PGE 1A | B5: 1188.85 | C5: ='SUMMARY - WAGES PT.RJ'!Y7 -> 193 | D5: 195 | E5: =C5-D5 -> -2 | F5: ='SUMMARY - WAGES PT.RJ'!AH7 -> 8.7837028e+08 | G5: 9.0199714e+08 | H5: =F5-G5 -> -23626867 | I5: ='SUMMARY - WAGES PT.RJ'!AI7 -> 1480.67 | J5: 1204.65 | K5: =I5-J5 -> 276.02 | L5: =K5/J5*100 -> 22.912879 | M5: =H5/G5*100 -> -2.6193949
A6: PGE 1B | B6: 61.83 | C6: ='SUMMARY - WAGES PT.RJ'!Y9 -> 172 | D6: 171 | E6: =C6-D6 -> 1 | F6: ='SUMMARY - WAGES PT.RJ'!AH9 -> 6.9539181e+08 | G6: 6.722109e+08 | H6: =F6-G6 -> 23180910 | I6: ='SUMMARY - WAGES PT.RJ'!AI9 -> 231.69 | J6: 162.57 | K6: =I6-J6 -> 69.12 | L6: =K6/J6*100 -> 42.51707 | M6: =H6/G6*100 -> 3.4484579
A7: PGE 2A | B7: 1491.97 | C7: ='SUMMARY - WAGES PT.RJ'!Y11 -> 176 | D7: 177 | E7: =C7-D7 -> -1 | F7: ='SUMMARY - WAGES PT.RJ'!AH11 -> 8.0436036e+08 | G7: 8.0045532e+08 | H7: =F7-G7 -> 3905046 | I7: ='SUMMARY - WAGES PT.RJ'!AI11 -> 1501.58 | J7: 1241.79 | K7: =I7-J7 -> 259.79 | L7: =K7/J7*100 -> 20.920607 | M7: =H7/G7*100 -> 0.48785309
A8: PGE 2B | B8: 982.11 | C8: ='SUMMARY - WAGES PT.RJ'!Y13 -> 125 | D8: 124 | E8: =C8-D8 -> 1 | F8: ='SUMMARY - WAGES PT.RJ'!AH13 -> 5.945058e+08 | G8: 6.3890182e+08 | H8: =F8-G8 -> -44396022 | I8: ='SUMMARY - WAGES PT.RJ'!AI13 -> 1433.46 | J8: 1132.97 | K8: =I8-J8 -> 300.49 | L8: =K8/J8*100 -> 26.522326 | M8: =H8/G8*100 -> -6.9488019
A9: DME | B9: 1518.88 | C9: ='SUMMARY - WAGES PT.RJ'!Y15 -> 205 | D9: 204 | E9: =C9-D9 -> 1 | F9: ='SUMMARY - WAGES PT.RJ'!AH15 -> 9.6692756e+08 | G9: 9.4818318e+08 | H9: =F9-G9 -> 18744380 | I9: ='SUMMARY - WAGES PT.RJ'!AI15 -> 2564.16 | J9: 2224.25 | K9: =I9-J9 -> 339.91 | L9: =K9/J9*100 -> 15.282005 | M9: =H9/G9*100 -> 1.9768733
A10: ARE A | B10: 1158.2 | C10: ='SUMMARY - WAGES PT.RJ'!Y29 -> 140 | D10: 141 | E10: =C10-D10 -> -1 | F10: ='SUMMARY - WAGES PT.RJ'!AH29 -> 6.866745e+08 | G10: 6.6607642e+08 | H10: =F10-G10 -> 20598080 | I10: ='SUMMARY - WAGES PT.RJ'!AI29 -> 1825.69 | J10: 1428.52 | K10: =I10-J10 -> 397.17 | L10: =K10/J10*100 -> 27.802901 | M10: =H10/G10*100 -> 3.09245
A11: ARE B1 | B11: 1210.1 | C11: ='SUMMARY - WAGES PT.RJ'!Y31 -> 139 | D11: 139 | E11: =C11-D11 -> 0 | F11: ='SUMMARY - WAGES PT.RJ'!AH31 -> 6.7607006e+08 | G11: 668699821 | H11: =F11-G11 -> 7370235.4 | I11: ='SUMMARY - WAGES PT.RJ'!AI31 -> 1996.52 | J11: 1697.47 | K11: =I11-J11 -> 299.05 | L11: =K11/J11*100 -> 17.617395 | M11: =H11/G11*100 -> 1.102174
A12: ARE B2 | B12: 1056.13 | C12: ='SUMMARY - WAGES PT.RJ'!Y33 -> 124 | D12: 128 | E12: =C12-D12 -> -4 | F12: ='SUMMARY - WAGES PT.RJ'!AH33 -> 6.2822493e+08 | G12: 622111088 | H12: =F12-G12 -> 6113840.3 | I12: ='SUMMARY - WAGES PT.RJ'!AI33 -> 1806.87 | J12: 1437.68 | K12: =I12-J12 -> 369.19 | L12: =K12/J12*100 -> 25.679567 | M12: =H12/G12*100 -> 0.98275701
A13: ARE C | B13: 1824.94 | C13: ='SUMMARY - WAGES PT.RJ'!Y35 -> 260 | D13: 264 | E13: =C13-D13 -> -4 | F13: ='SUMMARY - WAGES PT.RJ'!AH35 -> 1.2824897e+09 | G13: 1.2927092e+09 | H13: =F13-G13 -> -10219467 | I13: ='SUMMARY - WAGES PT.RJ'!AI35 -> 2533.65 | J13: 2211.9 | K13: =I13-J13 -> 321.75 | L13: =K13/J13*100 -> 14.546318 | M13: =H13/G13*100 -> -0.79054649
A14: MILL PKS | C14: ='SUMMARY - WAGES PT.RJ'!Y23 -> 167 | D14: 167 | E14: =C14-D14 -> 0 | F14: ='SUMMARY - WAGES PT.RJ'!AH23 -> 1234277949 | G14: 1207391151 | H14: =F14-G14 -> 26886798 | I14: 0 | J14: 0 | K14: =I14-J14 -> 0 | L14: 0 | M14: =H14/G14*100 -> 2.2268507
A15: BIBITAN | C15: ='SUMMARY - WAGES PT.RJ'!Y21 -> 18 | D15: 18 | E15: =C15-D15 -> 0 | F15: ='SUMMARY - WAGES PT.RJ'!AH21 -> 90844468 | G15: 88815910 | H15: =F15-G15 -> 2028557.8 | I15: 0 | J15: 0 | K15: =I15-J15 -> 0 | L15: 0 | M15: =H15/G15*100 -> 2.2840027
A16: Workshop ARE | C16: ='SUMMARY - WAGES PT.RJ'!Y37 -> 5 | D16: 5 | E16: =C16-D16 -> 0 | F16: ='SUMMARY - WAGES PT.RJ'!AH37 -> 28906719 | G16: 26805912 | H16: =F16-G16 -> 2100807 | I16: 0 | J16: 0 | K16: =I16-J16 -> 0 | L16: 0 | M16: =H16/G16*100 -> 7.8371034
A17: Workshop PGE | C17: ='SUMMARY - WAGES PT.RJ'!Y17 -> 14 | D17: 14 | E17: =C17-D17 -> 0 | F17: ='SUMMARY - WAGES PT.RJ'!AH17 -> 87891747 | G17: 80279506 | H17: =F17-G17 -> 7612241.2 | I17: 0 | J17: 0 | K17: =I17-J17 -> 0 | L17: 0 | M17: =H17/G17*100 -> 9.4821725
A18: Infrastruktur | C18: ='SUMMARY - WAGES PT.RJ'!Y19 -> 29 | D18: 29 | E18: =C18-D18 -> 0 | F18: ='SUMMARY - WAGES PT.RJ'!AH19 -> 1.611283e+08 | G18: 163108145 | H18: =F18-G18 -> -1979844.7 | I18: 0 | J18: 0 | K18: =I18-J18 -> 0 | L18: 0 | M18: =H18/G18*100 -> -1.2138233
B19: =SUM(B5:B18) -> 10493.01 | C19: =SUM(C5:C18) -> 1767 | D19: 1776 | E19: =SUM(E5:E18) -> -9 | F19: =SUM(F5:F18) -> 8.8160642e+09 | G19: 8.7777455e+09 | H19: =SUM(H5:H18) -> 38318694 | I19: =SUM(I5:I18) -> 15374.29 | J19: 12741.8 | K19: =SUM(K5:K18) -> 2632.49 | L19: =K19/J19*100 -> 20.660268 | M19: =H19/G19*100 -> 0.43654369
A21: Prunning
A23: Estate | B23: This Month
C24: Premi | D24: Total | I24: TURUN HK (Okt'25 - Sept'25 ) | M24: =K39 -> 180132680
A25: PGE 1A | C25: ='SUMMARY - WAGES PT.RJ'!AD7 -> 15466750 | D25: =C25+B25 -> 15466750 | I25: Premi Estate TURUN dari bulan lalu | L25: ( Lampiran I) | M25: =Rekapitulasi!F282 -> -59993946
A26: PGE 1B | C26: ='SUMMARY - WAGES PT.RJ'!AD9-C37 -> 0 | D26: =C26+B26 -> 0 | I26: OT Estate + Mill TURUN dari bulan lalu | L26: ( Lampiran I) | M26: =Rekapitulasi!G282 -> -5940259.2
A27: PGE 2A | C27: ='SUMMARY - WAGES PT.RJ'!AD11 -> 16282050 | D27: =C27+B27 -> 16282050 | I27: Progressive Pruning TURUN dari bulan lalu | L27: ( Lampiran II ) | M27: =Prunning!G16 -> -134517050
A28: PGE 2B | C28: ='SUMMARY - WAGES PT.RJ'!AD13-C38 -> 8599500 | D28: =C28+B28 -> 8599500 | I28: Insentif Panen NAIK dari bulan lalu | M28: =M37 -> 62481733
A29: DME | C29: ='SUMMARY - WAGES PT.RJ'!AD15 -> 45629800 | D29: =C29+B29 -> 45629800
A30: ARE A | C30: ='SUMMARY - WAGES PT.RJ'!AD29 -> 26023250 | D30: =C30+B30 -> 26023250 | I30: TOTAL | M30: =SUM(M24:M29) -> 42163158 | P30: =M30-H19 -> 3844464.2
A31: ARE B1 | C31: ='SUMMARY - WAGES PT.RJ'!AD31 -> 29981600 | D31: =C31+B31 -> 29981600
A32: ARE B2 | C32: ='SUMMARY - WAGES PT.RJ'!AD33 -> 20870600 | D32: =C32+B32 -> 20870600 | I32: Tonase TBS NAIK dari bulan lalu | M32: =K19 -> 2632.49 | N32: Ton
A33: ARE C | C33: ='SUMMARY - WAGES PT.RJ'!AD35-C39-C40 -> 45028000 | D33: =C33+B33 -> 45028000
C34: =SUM(C25:C33) -> 207881550 | D34: =SUM(D25:D33) -> 207881550
A35: Prunning | I35: Hk September | J35: 51837 | K35: =J35*129220 -> 6698377140 | L35: Insentif September 2025 | M35: 41467455
A36: PLASMA | C36: Premi | D36: Total | I36: Hk Oktober | J36: ='SEPTEMBER DIBAYAR OKT 2025 '!E554 -> 53231 | K36: =J36*129220 -> 6878509820 | L36: Insentif Oktober 2025 | M36: ='SEPTEMBER DIBAYAR OKT 2025 '!AG554 -> 1.0394919e+08
A37: AIR BATU | C37: 0 | D37: =SUM(C37) -> 0 | J37: =J36-J35 -> 1394 | K37: =K36-K35 -> 180132680 | M37: =M36-M35 -> 62481733
A38: CENDIL | C38: 0 | D38: =SUM(C38) -> 0 | I38: Pengurangan Koreksi
A39: TUNGKUP | C39: 0 | D39: =SUM(C39) -> 0 | K39: =K37+K38 -> 180132680
A40: SIMPANG TIGE | C40: 0 | D40: =SUM(C40) -> 0
C41: =SUM(C37:C40) -> 0 | D41: =SUM(D37:D40) -> 0
A46: Month of MEI 2022
A48: Estate | B48: Luas Ha Productive | C48: Jumlah Karyawan | F48: Nilai Gaji ( All) | I48: Tonase TBS | L48: % TBS Naik / Turun | M48: % Gaji Naik/Turun
C49: 44682 | D49: 44652 | E49: Diff | F49: 44682 | G49: 44652 | H49: Diff | I49: 44682 | J49: 44652 | K49: Diff | L49: (Mei `22 - Apr`22 )
A50: PGE 1A | B50: 1560.39 | C50: 228 | D50: 239 | E50: -11 | F50: ='SUMMARY - WAGES PT.RJ'!#REF! -> #REF! | G50: 623862226 | H50: =F50-G50 -> #REF! | I50: 2110.28 | J50: 2243.4 | K50: =I50-J50 -> -133.12 | L50: =K50/J50*100 -> -5.9338504 | M50: =H50/G50*100 -> #REF!
A51: PGE 1B | B51: 1415.81 | C51: 198 | D51: 198 | E51: 0 | F51: ='SUMMARY - WAGES PT.RJ'!#REF! -> #REF! | G51: 558607092 | H51: =F51-G51 -> #REF! | I51: 1406.39 | J51: 1901.89 | K51: =I51-J51 -> -495.5 | L51: =K51/J51*100 -> -26.053031 | M51: =H51/G51*100 -> #REF!
A52: PGE 2A | B52: 1485.65 | C52: 219 | D52: 218 | E52: 1 | F52: ='SUMMARY - WAGES PT.RJ'!#REF! -> #REF! | G52: 651313920 | H52: =F52-G52 -> #REF! | I52: 1657.05 | J52: 2388.98 | K52: =I52-J52 -> -731.93 | L52: =K52/J52*100 -> -30.637762 | M52: =H52/G52*100 -> #REF!
A53: PGE 2B | B53: 982.11 | C53: 139 | D53: 146 | E53: -7 | F53: ='SUMMARY - WAGES PT.RJ'!#REF! -> #REF! | G53: 425958213 | H53: =F53-G53 -> #REF! | I53: 1223.45 | J53: 2038.17 | K53: =I53-J53 -> -814.72 | L53: =K53/J53*100 -> -39.973113 | M53: =H53/G53*100 -> #REF!
A54: DME | B54: 1518.88 | C54: 203 | D54: 198 | E54: 5 | F54: ='SUMMARY - WAGES PT.RJ'!#REF! -> #REF! | G54: 596364572 | H54: =F54-G54 -> #REF! | I54: 1890.58 | J54: 2692.48 | K54: =I54-J54 -> -801.9 | L54: =K54/J54*100 -> -29.782951 | M54: =H54/G54*100 -> #REF!
A55: ARE A | B55: 1158.2 | C55: 159 | D55: 157 | E55: 2 | F55: ='SUMMARY - WAGES PT.RJ'!#REF! -> #REF! | G55: 4.9918183e+08 | H55: =F55-G55 -> #REF! | I55: 1551.01 | J55: 1945.79 | K55: =I55-J55 -> -394.78 | L55: =K55/J55*100 -> -20.288931 | M55: =H55/G55*100 -> #REF!
A56: ARE B1 | B56: 1210.1 | C56: 145 | D56: 142 | E56: 3 | F56: ='SUMMARY - WAGES PT.RJ'!#REF! -> #REF! | G56: 4.6491012e+08 | H56: =F56-G56 -> #REF! | I56: 1768.12 | J56: 2287.66 | K56: =I56-J56 -> -519.54 | L56: =K56/J56*100 -> -22.710543 | M56: =H56/G56*100 -> #REF!
A57: ARE B2 | B57: 1030.16 | C57: 128 | D57: 141 | E57: -13 | F57: ='SUMMARY - WAGES PT.RJ'!#REF! -> #REF! | G57: 4.6444233e+08 | H57: =F57-G57 -> #REF! | I57: 1605.88 | J57: 1980.47 | K57: =I57-J57 -> -374.59 | L57: =K57/J57*100 -> -18.914197 | M57: =H57/G57*100 -> #REF!
A58: ARE C | B58: 1657.19 | C58: 303 | D58: 290 | E58: 13 | F58: ='SUMMARY - WAGES PT.RJ'!#REF! -> #REF! | G58: 9.552029e+08 | H58: =F58-G58 -> #REF! | I58: 2319.3 | J58: 3118.66 | K58: =I58-J58 -> -799.36 | L58: =K58/J58*100 -> -25.631521 | M58: =H58/G58*100 -> #REF!
A59: MILL PKS | C59: 125 | D59: 125 | E59: 0 | F59: ='SUMMARY - WAGES PT.RJ'!#REF! -> #REF! | G59: 610112222 | H59: =F59-G59 -> #REF! | I59: 0 | J59: 0 | K59: =I59-J59 -> 0 | L59: 0 | M59: =H59/G59*100 -> #REF!
A60: Mill Bio Plant | C60: 2 | D60: 2 | E60: 0 | F60: ='SUMMARY - WAGES PT.RJ'!#REF! -> #REF! | G60: 13179016 | H60: =F60-G60 -> #REF! | I60: 0 | J60: 0 | K60: =I60-J60 -> 0 | L60: 0 | M60: =H60/G60*100 -> #REF!
A61: Workshop ARE | C61: 5 | D61: 5 | E61: 0 | F61: ='SUMMARY - WAGES PT.RJ'!#REF! -> #REF! | G61: 18439197 | H61: =F61-G61 -> #REF! | I61: 0 | J61: 0 | K61: =I61-J61 -> 0 | L61: 0 | M61: =H61/G61*100 -> #REF!
A62: Workshop PGE | C62: 10 | D62: 10 | E62: 0 | F62: ='SUMMARY - WAGES PT.RJ'!#REF! -> #REF! | G62: 49021715 | H62: =F62-G62 -> #REF! | I62: 0 | J62: 0 | K62: =I62-J62 -> 0 | L62: 0 | M62: =H62/G62*100 -> #REF!
A63: Infrastruktur | C63: 27 | D63: 27 | E63: 0 | F63: ='SUMMARY - WAGES PT.RJ'!#REF! -> #REF! | G63: 91570417 | H63: =F63-G63 -> #REF! | I63: 0 | J63: 0 | K63: =I63-J63 -> 0 | L63: 0 | M63: =H63/G63*100 -> #REF!
B64: =SUM(B50:B63) -> 12018.49 | C64: 1891 | D64: 1898 | E64: -7 | F64: =SUM(F50:F63) -> #REF! | G64: 6.0221658e+09 | H64: =SUM(H50:H63) -> #REF! | I64: =SUM(I50:I63) -> 15532.06 | J64: =SUM(J50:J63) -> 20597.5 | K64: =SUM(K50:K63) -> -5065.44 | L64: =K64/J64*100 -> -24.592499 | M64: =H64/G64*100 -> #REF!
A66: Prunning
A68: Estate | B68: This Month
C69: Premi | D69: Total | I69: Penambahan HK ( Mei - Apr ) | M69: =K84 -> 1.8700168e+09
A70: PGE 1A | C70: 0 | D70: 0 | I70: Premi Estate NAIK dari bulan lalu | L70: ( Lampiran I) | M70: =M25 -> -59993946
A71: PGE 1B | C71: 0 | D71: 0 | I71: OT Estate + Mll NAIK dari bulan lalu | L71: ( Lampiran I) | M71: =M26 -> -5940259.2
A72: PGE 2A | C72: 10573400 | D72: 10573400 | I72: Progressive Pruning TURUN dari bulan lalu | L72: ( Lampiran II ) | M72: =M27 -> -134517050
A73: PGE 2B | C73: 0 | D73: 0
A74: DME | C74: 27384050 | D74: 27384050
A75: ARE A | C75: 24467000 | D75: 24467000 | I75: TOTAL | M75: =SUM(M69:M74) -> 1.6695655e+09 | P75: =H64-M75 -> #REF!
A76: ARE B1 | C76: 21814000 | D76: 21814000
A77: ARE B2 | C77: 17712000 | D77: 17712000 | I77: Tonase TBS TURUN dari bulan lalu | M77: =K64 -> -5065.44
A78: ARE C | C78: 33843500 | D78: 33843500
C79: 135793950 | D79: 135793950
A80: Prunning | I80: Hk April | J80: 41743 | K80: 4.5428686e+09 | L80: Periode 01-25 April 2022
A81: PLASMA | C81: Premi | D81: Total | I81: Hk Mei | J81: =50840+8086 -> 58926 | K81: =J81*108829.47 -> 6.4128853e+09
A82: AIR BATU | C82: 0 | D82: 0 | J82: =J81-J80 -> 17183 | K82: =K81-K80 -> 1.8700168e+09
A83: CENDIL | C83: 0 | D83: 0 | I83: Pengurangan Koreksi
A84: TUNGKUP | C84: 3894500 | D84: 3894500 | K84: =K82+K83 -> 1.8700168e+09
A85: SIMPANG TIGE | C85: 2134500 | D85: 2134500
C86: 6029000 | D86: 6029000

Sheet SUMMARY - CASH PG & ARE
A1: PT. REBINMAS JAYA CASH DENOMINATION JUNI 2018
A3: ESTATE/DIVISION | B3: WORKERS | C3: 100000 | D3: 50000 | E3: 20000 | F3: 10000 | G3: 5000 | H3: 1000 | I3: OTHERS
J4: TOTAL
A6: PETTY CASH MILL | B6: =#REF! -> #REF! | C6: =#REF! -> #REF! | D6: =#REF! -> #REF! | E6: =#REF! -> #REF! | F6: =#REF! -> #REF! | G6: =#REF! -> #REF! | H6: =#REF! -> #REF! | I6: =#REF! -> #REF! | J6: =SUM(C6:I6) -> #REF!
A8: PHASE 1A - PREMI | B8: =#REF! -> #REF! | C8: 13400000 | D8: =#REF! -> #REF! | E8: 840000 | F8: 500000 | G8: =#REF! -> #REF! | H8: =#REF! -> #REF! | I8: 29180 | J8: =#REF! -> #REF!
A10: PHASE 1B - PREMI | B10: =#REF! -> #REF! | C10: =#REF! -> #REF! | D10: =#REF! -> #REF! | E10: =#REF! -> #REF! | F10: =#REF! -> #REF! | G10: =#REF! -> #REF! | H10: =#REF! -> #REF! | I10: =#REF! -> #REF! | J10: =SUM(C10:I10) -> #REF!
A12: PHASE 2A - PREMI | B12: =#REF! -> #REF! | C12: =#REF! -> #REF! | D12: =#REF! -> #REF! | E12: =#REF! -> #REF! | F12: =#REF! -> #REF! | G12: =#REF! -> #REF! | H12: =#REF! -> #REF! | I12: =#REF! -> #REF! | J12: =SUM(C12:I12) -> #REF!
A14: PHASE 2B - PREMI | B14: =#REF! -> #REF! | C14: =#REF! -> #REF! | D14: =#REF! -> #REF! | E14: =#REF! -> #REF! | F14: =#REF! -> #REF! | G14: =#REF! -> #REF! | H14: =#REF! -> #REF! | I14: =#REF! -> #REF! | J14: =SUM(C14:I14) -> #REF!
A16: DME 1 - PREMI | B16: =#REF! -> #REF! | C16: =#REF! -> #REF! | D16: =#REF! -> #REF! | E16: =#REF! -> #REF! | F16: =#REF! -> #REF! | G16: =#REF! -> #REF! | H16: =#REF! -> #REF! | I16: =#REF! -> #REF! | J16: =SUM(C16:I16) -> #REF!
A18: DME 2 - PREMI | B18: =#REF! -> #REF! | C18: =#REF! -> #REF! | D18: =#REF! -> #REF! | E18: =#REF! -> #REF! | F18: =#REF! -> #REF! | G18: =#REF! -> #REF! | H18: =#REF! -> #REF! | I18: =#REF! -> #REF! | J18: =SUM(C18:I18) -> #REF!
A20: BULUH TUMBANG - PREMI | B20: =#REF! -> #REF! | C20: =#REF! -> #REF! | D20: =#REF! -> #REF! | E20: =#REF! -> #REF! | F20: =#REF! -> #REF! | G20: =#REF! -> #REF! | H20: =#REF! -> #REF! | I20: =#REF! -> #REF! | J20: =SUM(C20:I20) -> #REF!
A22: MC ALLOWANCE | B22: =#REF! -> #REF! | C22: =#REF! -> #REF! | D22: =#REF! -> #REF! | E22: =#REF! -> #REF! | F22: =#REF! -> #REF! | G22: =#REF! -> #REF! | H22: =#REF! -> #REF! | I22: =#REF! -> #REF! | J22: =#REF! -> #REF!
A24: PETTY CASH ESTATE | B24: =#REF! -> #REF! | C24: =#REF! -> #REF! | D24: =#REF! -> #REF! | E24: =#REF! -> #REF! | F24: =#REF! -> #REF! | G24: =#REF! -> #REF! | H24: =#REF! -> #REF! | I24: =#REF! -> #REF! | J24: =SUM(C24:I24) -> #REF!
A28: SUB TOTAL | B28: =SUM(B5:B27) -> #REF! | C28: =SUM(C5:C27) -> #REF! | D28: =SUM(D5:D27) -> #REF! | E28: =SUM(E5:E27) -> #REF! | F28: =SUM(F5:F27) -> #REF! | G28: =SUM(G5:G27) -> #REF! | H28: =SUM(H5:H27) -> #REF! | I28: =SUM(I5:I27) -> #REF! | J28: =SUM(J5:J27) -> #REF!
A29: =+A1 -> PT. REBINMAS JAYA CASH DENOMINATION JUNI 2018
A32: ARE - A (CASH PAYMENT ) | B32: =#REF! -> #REF! | C32: 3600000 | D32: =#REF! -> #REF! | E32: 260000 | F32: 100000 | G32: =#REF! -> #REF! | H32: =#REF! -> #REF! | I32: 7839 | J32: =#REF! -> #REF!
A34: ARE - B1 PREMI | B34: =#REF! -> #REF! | C34: =#REF! -> #REF! | D34: =#REF! -> #REF! | E34: =#REF! -> #REF! | F34: =#REF! -> #REF! | G34: =#REF! -> #REF! | H34: =#REF! -> #REF! | I34: =#REF! -> #REF! | J34: =SUM(C34:I34) -> #REF!
A36: ARE - B2 PREMI | B36: =#REF! -> #REF! | C36: =#REF! -> #REF! | D36: =#REF! -> #REF! | E36: =#REF! -> #REF! | F36: =#REF! -> #REF! | G36: =#REF! -> #REF! | H36: =#REF! -> #REF! | I36: =#REF! -> #REF! | J36: =SUM(C36:I36) -> #REF!
A38: ARE - C ( CASH PAYMENT ) | B38: 0 | C38: 0 | D38: 0 | E38: 0 | F38: 0 | G38: 0 | H38: 0 | I38: 0 | J38: =#REF! -> #REF!
A40: WORKSHOP ARE - PREMI | B40: =#REF! -> #REF! | C40: =#REF! -> #REF! | D40: =#REF! -> #REF! | E40: =#REF! -> #REF! | F40: =#REF! -> #REF! | G40: =#REF! -> #REF! | H40: =#REF! -> #REF! | I40: =#REF! -> #REF! | J40: =SUM(C40:I40) -> #REF!
A42: SUB TOTAL | B42: =SUM(B31:B41) -> #REF! | C42: =SUM(C31:C41) -> #REF! | D42: =SUM(D31:D41) -> #REF! | E42: =SUM(E31:E41) -> #REF! | F42: =SUM(F31:F41) -> #REF! | G42: =SUM(G31:G41) -> #REF! | H42: =SUM(H31:H41) -> #REF! | I42: =SUM(I31:I41) -> #REF! | J42: =SUM(J31:J41) -> #REF!
A44: GRAND TOTAL | B44: =B28+B42 -> #REF! | C44: =C28+C42 -> #REF! | D44: =D28+D42 -> #REF! | E44: =E28+E42 -> #REF! | F44: =F28+F42 -> #REF! | G44: =G28+G42 -> #REF! | H44: =H28+H42 -> #REF! | I44: =I28+I42 -> #REF! | J44: =J28+J42 -> #REF!
A51: DIBUAT OLEH : | B51: DIPERIKSA OLEH: | F51: DISETUJUI OLEH:
C56: JUMLAH | D56: NILAI | E56: TOTAL ( RP ) | G56: JUMLAH | H56: NILAI | I56: TOTAL ( RP )
C57: 36 | D57: 100000 | E57: =C57*D57 -> 3600000 | G57: 134 | H57: 100000 | I57: 13400000
C58: 0 | D58: 50000 | E58: =C58*D58 -> 0 | G58: 0 | H58: 50000 | I58: 0
C59: 13 | D59: 20000 | E59: =C59*D59 -> 260000 | G59: 42 | H59: 20000 | I59: 840000
C60: 10 | D60: 10000 | E60: =C60*D60 -> 100000 | G60: 50 | H60: 10000 | I60: 500000
C61: 0 | D61: 5000 | E61: =C61*D61 -> 0 | G61: 0 | H61: 5000 | I61: 0
C62: 0 | D62: 1000 | E62: =C62*D62 -> 0 | G62: 0 | H62: 1000 | I62: 0
C63: 10 | D63: 500 | E63: =C63*D63 -> 5000 | G63: 42 | H63: 500 | I63: 21000
C64: 22 | D64: 100 | E64: =C64*D64 -> 2200 | G64: 58 | H64: 100 | I64: 5800
C65: Balance | E65: 638 | G65: Balance | I65: 2370
E66: =SUM(E57:E65) -> 3967838 | I66: 14769170

Sheet JUNI 2018 DIBAYAR JULI 2018 (2)
A3: PT. REBINMAS JAYA
A4: DENOMINATION FOR JULI 2018
A6: ESTATE/DIVISION | B6: WORKERS | M6: Pot. | N6: TOTAL PPH 21 | O6: TOTAL PPH | P6: TOTAL PREMI | Q6: TOTAL LEMBUR | R6: TOTAL | S6: Upah & Astek | T6: Total & | X6: PRUNNING | AA6: TOTAL PREMI
C7: 100000 | D7: 50000 | E7: 20000 | F7: 10000 | G7: 5000 | H7: 1000 | I7: 500 | J7: 100 | K7: 50 | L7: OTHERS | M7: Pinjaman | N7: (MASA JUNI - 2018) | O7: EX-GRATIA | T7: Rata-rata
A9: PHASE IA HARVESTING KHL (AIR HIJAU) | B9: 10 | N9: 0 | P9: =3240140+66990+464000 -> 3771130 | Q9: 0 | R9: 26387252 | X9: 883500 | AA9: =P9+X9 -> 4654630
A10: PHASE IA MAINTENANCE KHT (AIR HIJAU) | B10: 41 | N10: 0 | P10: 1851220 | Q10: 2038710 | R10: 116157613 | X10: 0 | AA10: =P10+X10 -> 1851220
A11: PHASE IA OPERATOR (AIR HIJAU) | B11: 6 | N11: 1304 | P11: 7188000 | Q11: 4186834 | R11: 28463887 | X11: 0 | AA11: =P11+X11 -> 7188000
A12: PHASE IA HARVESTING MANDOR & KERANI (AIR HIJAU) | B12: 28 | N12: 182777 | P12: =20239160+2063530 -> 22302690 | Q12: 2667843 | R12: 106196357 | X12: 7307500 | AA12: =P12+X12 -> 29610190
A13: PHASE IA HARVESTING KHT (AIR BATU) | B13: 25 | N13: 0 | P13: =6633310 -> 6633310 | Q13: 1855544 | R13: 76919231 | X13: 3806000 | AA13: =P13+X13 -> 10439310
A14: PHASE IA MAINTENANCE KHT (AIR BATU) | B14: 33 | N14: 0 | P14: 746900 | Q14: 1242341 | R14: 89870308 | X14: 0 | AA14: =P14+X14 -> 746900
A15: PHASE IA OPERATOR (AIR BATU) | B15: 4 | N15: 0 | P15: 2122245 | Q15: 2110359 | R15: 15540812 | X15: 0 | AA15: =P15+X15 -> 2122245
A16: PHASE IA HARVESTING KHL (AIR BATU) | B16: 6 | N16: 0 | P16: =2984050 -> 2984050 | Q16: 0 | R16: 16995845 | X16: 846000 | AA16: =P16+X16 -> 3830050
A17: PHASE IA HARVESTING KHT (AIR KUNDO) | B17: 23 | N17: 64502 | P17: =13152550+3486700+330605 -> 16969855 | Q17: 2245766 | R17: 86968930 | X17: 6816000 | AA17: =P17+X17 -> 23785855
A18: PHASE IA MAINTENANCE KHT (AIR KUNDO) | B18: 30 | N18: 0 | P18: 533889 | Q18: 2110383 | R18: 83286601 | X18: 0 | AA18: =P18+X18 -> 533889
A19: PHASE IA PANEN KHL (AIR KUNDO) | B19: 7 | N19: 0 | P19: =314710+1533000 -> 1847710 | Q19: 0 | R19: 15841552 | X19: 192000 | AA19: =P19+X19 -> 2039710
A20: PHASE IA OPERATOR (AIR KUNDO) | B20: 4 | N20: 0 | P20: 1542382 | Q20: 2078528 | R20: 14218530 | X20: 0 | AA20: =P20+X20 -> 1542382
A22: TOTAL | B22: =SUM(B8:B21) -> 217 | C22: =SUM(C8:C21) -> 0 | D22: =SUM(D8:D21) -> 0 | E22: =SUM(E8:E21) -> 0 | F22: =SUM(F8:F21) -> 0 | G22: =SUM(G8:G21) -> 0 | H22: =SUM(H8:H21) -> 0 | I22: =SUM(I8:I21) -> 0 | ... R22: =SUM(R8:R21) -> 676846918 | T22: =#REF!/#REF! -> #REF! | U22: Upah rata-rata/ hk | X22: =SUM(X8:X21) -> 19851000 | AA22: =SUM(AA9:AA21) -> 88344381
A28: DIBUAT OLEH : DIPERIKSA OLEH : | D28: DIPERIKSA OLEH : | J28: DISETUJUI OLEH :
A37: PT. REBINMAS JAYA
A38: =A4 -> DENOMINATION FOR JULI 2018
A40: ESTATE/DIVISION | B40: WORKERS | M40: =M6 -> Pot. | N40: TOTAL PPH 21 | O40: TOTAL PPH | P40: =P6 -> TOTAL PREMI | Q40: =Q6 -> TOTAL LEMBUR | R40: TOTAL | S40: Upah & Astek | T40: Total & | X40: PRUNNING
C41: 100000 | D41: 50000 | E41: 20000 | F41: 10000 | G41: 5000 | H41: 1000 | I41: 500 | J41: 100 | K41: 50 | L41: OTHERS | M41: =M7 -> Pinjaman | N41: =N7 -> (MASA JUNI - 2018) | O41: EX-GRATIA | T41: Rata-rata
A43: PHASE IB OPERATOR (GUNUNG RUM) | B43: 4 | N43: 0 | P43: 2861073 | Q43: 2094456 | R43: 15339652 | X43: 0 | AA43: =P43+X43 -> 2861073
A44: PHASE IB HARVESTING KHT (GUNUNG RUM) | B44: 31 | N44: 0 | P44: =3925330+247100 -> 4172430 | Q44: 2548387 | R44: 101467542 | X44: 12593000 | AA44: =P44+X44 -> 16765430
A45: PHASE IB MAINTENANCE KHT (GUNUNG RUM) | B45: 36 | N45: 0 | P45: =26760+1814800 -> 1841560 | Q45: 1258266 | R45: 101352495 | X45: 0 | AA45: =P45+X45 -> 1841560
A46: PHASE IB HARVESTING KHT (GUNUNG PANJANG) | B46: 21 | N46: 0 | P46: =1281130+499100 -> 1780230 | Q46: 1847580 | R46: 62202310 | X46: 3680500 | AA46: =P46+X46 -> 5460730
A47: PHASE IB MAINTENANCE KHT (GUNUNG PANJANG) | B47: 32 | N47: 0 | P47: 0 | Q47: 915827 | R47: 86660331 | X47: 0 | AA47: =P47+X47 -> 0
A48: PHASE IB OPERATOR (GUNUNG PANJANG) | B48: 5 | N48: 0 | P48: 3169027 | Q48: 3201412 | R48: 20687222 | X48: 0 | AA48: =P48+X48 -> 3169027
A49: PHASE IB HARVESTING KHL (GUNUNG PANJANG) | B49: 4 | N49: 0 | P49: =90640+100100 -> 190740 | Q49: 0 | R49: 9055768 | X49: 276000 | AA49: =P49+X49 -> 466740 | AC49: =37+31 -> 68
A50: PHASE IB MAINTENANCE KHL (GUNUNG PANJANG) | B50: 24 | N50: 0 | P50: 0 | Q50: 0 | R50: 5621105 | X50: 0 | AA50: =P50+X50 -> 0
A51: PHASE IB HARVESTING & MANDOR & KERANI (PADANG TEMBALUN) | B51: 23 | N51: 25502 | P51: =9595200 -> 9595200 | Q51: 2182057 | R51: 78686731 | X51: 6705500 | AA51: =P51+X51 -> 16300700
A52: PHASE IB MAINTENANCE KHT (PADANG TEMBALUN) | B52: 46 | N52: 0 | P52: 1666800 | Q52: 1704227 | R52: 128548713 | X52: 0 | AA52: =P52+X52 -> 1666800
A53: PHASE IB PLASMA (PADANG TEMBALUN) | B53: 8 | N53: 0 | P53: =739710+788200 -> 1527910 | Q53: 772480 | R53: 25254834 | X53: 2473500 | AA53: =P53+X53 -> 4001410
A54: PHASE IB HARVESTING KHL (PADANG TEMBALUN) | B54: 21 | N54: 0 | P54: =7561260+189000 -> 7750260 | Q54: 0 | R54: 50038491 | X54: 0 | AA54: =P54+X54 -> 7750260
A55: PHASE IB OPERATOR (PADANG TEMBALUN) | B55: 6 | N55: 0 | P55: 3232953 | Q55: 3550922 | R55: 23950232 | AA55: =P55+X55 -> 3232953
AA56: =P56+X56 -> 0
A57: TOTAL | B57: =SUM(B43:B56) -> 261 | C57: =SUM(C43:C56) -> 0 | D57: =SUM(D43:D56) -> 0 | E57: =SUM(E43:E56) -> 0 | F57: =SUM(F43:F56) -> 0 | G57: =SUM(G43:G56) -> 0 | H57: =SUM(H43:H56) -> 0 | I57: =SUM(I43:I56) -> 0 | ... R57: =SUM(R43:R56) -> 708865426 | T57: =#REF!/#REF! -> #REF! | U57: Upah rata-rata/HK | X57: =SUM(X42:X56) -> 25728500 | AA57: =SUM(AA43:AA56) -> 63516683
A63: DIBUAT OLEH : DIPERIKSA OLEH : | D63: DIPERIKSA OLEH : | J63: DISETUJUI OLEH :
A72: PT. REBINMAS JAYA
A73: =A4 -> DENOMINATION FOR JULI 2018
AB74: =993825+712740+83610+40000 -> 1830175
A75: ESTATE/DIVISION | B75: WORKERS | M75: =M6 -> Pot. | N75: TOTAL PPH 21 | O75: TOTAL PPH | P75: =P6 -> TOTAL PREMI | Q75: =Q6 -> TOTAL LEMBUR | R75: TOTAL | S75: Upah & Astek | T75: Total & | X75: PRUNNING
C76: 100000 | D76: 50000 | E76: 20000 | F76: 10000 | G76: 5000 | H76: 1000 | I76: 500 | J76: 100 | K76: 50 | L76: OTHERS | M76: =M7 -> Pinjaman | N76: =N7 -> (MASA JUNI - 2018) | O76: EX-GRATIA | T76: Rata-rata
A78: PHASE IIA MAINTENANCE KHT AIR JANGKAT 1 | B78: 33 | N78: 0 | P78: 274445 | Q78: 2946573 | R78: 91999396 | X78: 0 | AA78: =P78+X78 -> 274445
A79: PHASE IIA HARVESTING KHT AIR JANGKAT 1 | B79: 29 | N79: 0 | P79: =250000+7188390+2639700 -> 10078090 | Q79: 3169557 | R79: 88673698 | X79: 0 | AA79: =P79+X79 -> 10078090
A80: PHASE IIA HARVESTING KHL AIR JANGKAT 1 | B80: 5 | N80: 0 | P80: =182115+2130210+634900 -> 2947225 | Q80: 1059173 | R80: 13070887 | X80: 0 | AA80: =P80+X80 -> 2947225
A81: PHASE IIA HARVESTING KHT AIR BETANGAN | B81: 31 | N81: 252 | P81: =7682010+168700 -> 7850710 | Q81: 5072883 | R81: 95956499 | X81: 0 | AA81: =P81+X81 -> 7850710
A82: PHASE IIA MAINTENANCE KHT AIR BETANGAN 2 | B82: 31 | N82: 0 | P82: 0 | Q82: 904335 | R82: 86105258 | X82: 0 | AA82: =P82+X82 -> 0
A83: PHASE IIA HARVESTING KHL AIR BETANGAN | B83: 23 | N83: 0 | P83: 2576930 | Q83: 1465323 | R83: 12478614 | X83: 0 | AA83: =P83+X83 -> 2576930
A84: PHASE IIA MAINT KHL AIR BETANGAN | B84: 20 | N84: 0 | P84: 0 | Q84: 0 | R84: 2755444 | AA84: =P84+X84 -> 0
A85: PHASE IIA OPERATOR | B85: 14 | N85: 102275 | P85: 13605394 | Q85: 14136577 | R85: 66513929 | AA85: =P85+X85 -> 13605394
A86: PHASE IIA MAINTENANCE KHT AIR PAPAN 3 | B86: 31 | N86: 0 | P86: 0 | Q86: 1632561 | R86: 85461455 | X86: 0 | AA86: =P86+X86 -> 0
A87: PHASE IIA HARVESTING KHL AIR PAPAN 3 | B87: 6 | N87: 0 | P87: =250000+4441300+690900 -> 5382200 | Q87: 254839 | R87: 16250886 | X87: 0 | AA87: =P87+X87 -> 5382200
A88: PHASE IIA HARVESTING AIR PAPAN 3 | B88: 33 | N88: 0 | P88: =12790190+3829000+689130 -> 17308320 | Q88: 3997782 | R88: 108550853 | X88: 0 | AA88: =P88+X88 -> 17308320
AA89: =P89+X89 -> 0
A90: TOTAL | B90: =SUM(B77:B89) -> 256 | C90: =SUM(C77:C89) -> 0 | D90: =SUM(D77:D89) -> 0 | E90: =SUM(E77:E89) -> 0 | F90: =SUM(F77:F89) -> 0 | G90: =SUM(G77:G89) -> 0 | H90: =SUM(H77:H89) -> 0 | I90: =SUM(I77:I89) -> 0 | ... R90: =SUM(R77:R89) -> 667816919 | T90: =#REF!/#REF! -> #REF! | U90: Upah rata-rata / HK | X90: =SUM(X78:X89) -> 0 | AA90: =P90+X90 -> 60023314
A96: DIBUAT OLEH : DIPERIKSA OLEH : | D96: DIPERIKSA OLEH : | J96: DISETUJUI OLEH :
A104: PT. REBINMAS JAYA
A105: =A4 -> DENOMINATION FOR JULI 2018
A107: ESTATE/DIVISION | B107: WORKERS | M107: =M6 -> Pot. | N107: TOTAL PPH 21 | O107: TOTAL PPH | P107: =P75 -> TOTAL PREMI | Q107: =Q75 -> TOTAL LEMBUR | R107: TOTAL | S107: Upah & Astek | T107: Total & | X107: PRUNNING
C108: 100000 | D108: 50000 | E108: 20000 | F108: 10000 | G108: 5000 | H108: 1000 | I108: 500 | J108: 100 | K108: 50 | L108: OTHERS | M108: =M7 -> Pinjaman | N108: =N76 -> (MASA JUNI - 2018) | O108: EX-GRATIA | T108: Rata-rata
A110: PHASE IIB HARVESTING (AIR LIMPAS) | B110: 38 | N110: 0 | P110: =13448480+5676300+41420 -> 19166200 | Q110: 2285585 | R110: 121338196 | X110: 0 | AA110: =P110+X110 -> 19166200
A111: PHASE IIB HARVESTING KHL (AIR LIMPAS) | B111: 4 | N111: 0 | P111: =5449980+199500 -> 5649480 | Q111: 87604 | R111: 14058521 | X111: 0 | AA111: =P111+X111 -> 5649480
A112: PHASE IIB MAINTENANCE (AIR LIMPAS) | B112: 37 | N112: 0 | P112: 0 | Q112: 2827117 | R112: 101644093 | X112: 0 | AA112: =P112+X112 -> 0
A113: PHASE IIB OPERATOR ( AIK LIMPAS) | B113: 6 | N113: 0 | P113: 5068940 | Q113: 2755444 | R113: 24233404 | X113: 0 | AA113: =P113+X113 -> 5068940
A114: PHASE IIB HARVESTING KHL (AIR LIMPAS) | B114: 8 | N114: 0 | P114: =25120+308000 -> 333120 | Q114: 0 | R114: 1435297 | X114: 0 | AA114: =P114+X114 -> 333120
A115: PHASE IIB OPERATOR ( AIK KUNYAL ) | B115: 5 | N115: 0 | P115: 3572077 | Q115: 2190020 | R115: 19346291 | X115: 0 | AA115: =P115+X115 -> 3572077
A116: PHASE IIB HARVESTING (AIK KUNYAL) | B116: 23 | N116: 231826 | P116: =13979590+3450200+345200+250000 -> 18024990 | Q116: 2078528 | R116: 79551516 | X116: 0 | AA116: =P116+X116 -> 18024990
A117: PHASE IIB HARVESTING KHL (AIK KUNYAL) | B117: 10 | N117: 0 | P117: =4540230+1295000 -> 5835230 | Q117: 3647379 | R117: 30561754 | X117: 0 | AA117: =P117+X117 -> 5835230
A118: PHASE IIB MAINT TRAINNING (AIK KUNYAL) | B118: 17 | N118: 0 | P118: 0 | Q118: 0 | R118: 2342127 | X118: 0 | AA118: =P118+X118 -> 0
A119: PHASE IIB MAINTENANCE (AIR KUNYAL) | B119: 33 | N119: 0 | P119: 0 | Q119: 1393649 | R119: 90576848 | X119: 0 | AA119: =P119+X119 -> 0
AA120: =P120+X120 -> 0
A121: TOTAL | B121: =SUM(B109:B120) -> 181 | C121: =SUM(C109:C120) -> 0 | D121: =SUM(D109:D120) -> 0 | E121: =SUM(E109:E120) -> 0 | F121: =SUM(F109:F120) -> 0 | G121: =SUM(G109:G120) -> 0 | H121: =SUM(H109:H120) -> 0 | I121: =SUM(I109:I120) -> 0 | ... R121: =SUM(R109:R120) -> 485088047 | T121: =#REF!/#REF! -> #REF! | U121: Upah rata-rata / HK | X121: =SUM(X110:X120) -> 0 | AA121: =P121+X121 -> 57650037
A128: DIBUAT OLEH : DIPERIKSA OLEH : | D128: DIPERIKSA OLEH : | J128: DISETUJUI OLEH :
A136: PT. REBINMAS JAYA
A137: =A4 -> DENOMINATION FOR JULI 2018
A139: ESTATE/DIVISION | B139: WORKERS | M139: =M6 -> Pot. | N139: TOTAL PPH 21 | O139: TOTAL PPH | P139: =P107 -> TOTAL PREMI | Q139: =Q107 -> TOTAL LEMBUR | R139: TOTAL | S139: Upah & Astek | T139: Total & | X139: PRUNNING
C140: 100000 | D140: 50000 | E140: 20000 | F140: 10000 | G140: 5000 | H140: 1000 | I140: 500 | J140: 100 | K140: 50 | L140: OTHERS | M140: =M7 -> Pinjaman | N140: =N108 -> (MASA JUNI - 2018) | O140: EX-GRATIA | T140: Rata-rata
A142: DME HARVESTING KHT AIK CENDONG | B142: 36 | N142: 98802 | P142: =39081270 -> 39081270 | Q142: 2046673 | R142: 139630074 | X142: 0 | AA142: =P142+X142 -> 39081270
A143: DME HARVESTING KHL AIK CENDONG | B143: 2 | N143: 0 | P143: 2770350 | Q143: 0 | R143: 7215799 | X143: 0 | AA143: =P143+X143 -> 2770350
A144: DME OPERATOR AIK CENDONG | B144: 4 | N144: 55071 | P144: 3890913 | Q144: 3050101 | R144: 17534063 | AA144: =P144+X144 -> 3890913
A145: DME MAINTENANCE KHT AIK CENDONG | B145: 35 | N145: 0 | P145: 617298 | Q145: 2413004 | R145: 97383160 | X145: 0 | AA145: =P145+X145 -> 617298
A146: DME MAINTENANCE KHT AIK KANDIS | B146: 33 | N146: 0 | P146: 2091038 | Q146: 2468749 | R146: 91257460 | X146: 0 | AA146: =P146+X146 -> 2091038
A147: DME OPERATOR AIK KANDIS | B147: 4 | N147: 42506 | P147: 4674225 | Q147: 2882862 | R147: 17970049 | X147: 0 | AA147: =P147+X147 -> 4674225
A148: DME HARVESTING KHT AIK KANDIS | B148: 28 | N148: 10789 | P148: 16843470 | Q148: 1998889 | R148: 94919142 | X148: 0 | AA148: =P148+X148 -> 16843470
A149: DME HARVESTING KHL AIK KANDIS | B149: 23 | N149: 0 | P149: 0 | Q149: 0 | R149: 3030988 | X149: 0 | AA149: =P149+X149 -> 0
A150: DME HARVESTING KHL AIK KANDIS | B150: 3 | N150: 0 | P150: 903970 | Q150: 0 | R150: 7296599 | X150: 0 | AA150: =P150+X150 -> 903970
A151: DME HARVESTING KHT AIK RAYA | B151: 29 | N151: 138595 | P151: =28637300+459900 -> 29097200 | Q151: 1752017 | R151: 108392651 | X151: 0 | AA151: =P151+X151 -> 29097200
A152: DME HARVESTING KHL AIK RAYA | B152: 17 | N152: 0 | P152: =7891140+2047500 -> 9938640 | Q152: 0 | R152: 47109576 | X152: 0 | AA152: =P152+X152 -> 9938640
A153: DME OPERATOR AIK RAYA | B153: 4 | N153: 0 | P153: 2206211 | Q153: 1672376 | R153: 13729122 | X153: 0 | AA153: =P153+X153 -> 2206211
A154: DME MAINTENANCE KHT AIK RAYA | B154: 35 | N154: 0 | P154: 1058845 | Q154: 1767941 | R154: 98266924 | X154: 0 | AA154: =P154+X154 -> 1058845
AA155: =P155+X155 -> 0
A156: TOTAL | B156: =SUM(B141:B155) -> 253 | C156: =SUM(C141:C155) -> 0 | D156: =SUM(D141:D155) -> 0 | E156: =SUM(E141:E155) -> 0 | F156: =SUM(F141:F155) -> 0 | G156: =SUM(G141:G155) -> 0 | H156: =SUM(H141:H155) -> 0 | I156: =SUM(I141:I155) -> 0 | ... R156: =SUM(R141:R155) -> 743735607 | T156: =#REF!/#REF! -> #REF! | U156: Upah rata-rata / HK | X156: =SUM(X142:X155) -> 0 | AA156: =P156+X156 -> 113173430
A162: DIBUAT OLEH : DIPERIKSA OLEH : | D162: DIPERIKSA OLEH : | J162: DISETUJUI OLEH :
A169: PT. REBINMAS JAYA
A170: =A4 -> DENOMINATION FOR JULI 2018
A172: ESTATE/DIVISION | B172: WORKERS | M172: =M6 -> Pot. | N172: TOTAL PPH 21 | O172: TOTAL PPH | P172: =P139 -> TOTAL PREMI | Q172: =Q139 -> TOTAL LEMBUR | R172: TOTAL | S172: Upah & Astek | T172: Total & | X172: PRUNNING
C173: 100000 | D173: 50000 | E173: 20000 | F173: 10000 | G173: 5000 | H173: 1000 | I173: 500 | J173: 100 | K173: 50 | L173: OTHERS | M173: =M7 -> Pinjaman | N173: =N140 -> (MASA JUNI - 2018) | O173: EX-GRATIA | T173: Rata-rata
A175: ARE-A HARVESTING KHT (BUKIT PANJANG) | B175: 29 | N175: 40465 | P175: =19438595+9733500 -> 29172095 | Q175: 3965928 | R175: 110026128 | X175: 0 | AA175: =P175+X175 -> 29172095
A176: ARE-A MAINTENANCE KHT (BUKIT PANJANG) | B176: 38 | N176: 0 | P176: =1362760+224000 -> 1586760 | Q176: 5502924 | R176: 110104070 | X176: 0 | AA176: =P176+X176 -> 1586760
...

Sheet Sheet5
A5: NO | B5: ESTATE | C5: STATUS
A6: 1 | B6: PGE 1A | C6: ROBY
A7: 2 | B7: PGE 1B | C7: UNKNOWN
A8: 3 | B8: PGE 2A | C8: UNKNOWN
A9: 4 | B9: PGE 2B | C9: UNKNOWN
A10: 5 | B10: DME | C10: UNKNOWN
A11: 6 | B11: ARE A | C11: ROBY
A12: 7 | B12: ARE B1 | C12: UNKNOWN
A13: 8 | B13: ARE B2 | C13: UNKNOWN
A14: 9 | B14: ARE C | C14: UNKNOWN
A15: 10 | B15: INFRASTRUKTUR | C15: ROBY
A16: 11 | B16: WORKSHOP PG | C16: ROBY
A17: 12 | B17: WORKSHOP ARE | C17: UNKNOWN
A18: 13 | B18: IJL | C18: REVISI
E27: 100000 | F27: 50000 | G27: 20000 | H27: 10000 | I27: 5000 | J27: 1000 | K27: 500 | L27: 100 | M27: Balance
B28: 1 | C28: 330653 | E28: =ROUNDDOWN(C28/100000,0) -> 3 | F28: =ROUNDDOWN((C28-E28*100000)/50000,0) -> 0 | G28: =ROUNDDOWN((C28-E28*100000-F28*50000)/20000,0) -> 1 | H28: =ROUNDDOWN((C28-E28*100000-F28*50000-G28*20000)/10000,0) -> 1 | I28: =ROUNDDOWN((C28-E28*100000-F28*50000-G28*20000-H28*10000)/5000,0) -> 0 | J28: =ROUNDDOWN((C28-E28*100000-F28*50000-G28*20000-H28*10000-I28*5000)/1000,0) -> 0 | K28: =ROUNDDOWN((C28-E28*100000-F28*50000-G28*20000-H28*10000-I28*5000-J28*1000)/500,0) -> 1 | L28: =ROUNDDOWN((C28-E28*100000-F28*50000-G28*20000-H28*10000-I28*5000-J28*1000-K28*500)/100,0) -> 1 | M28: =C28-N28 -> 53 | N28: =E28*100000+F28*50000+G28*20000+H28*10000+I28*5000+J28*1000+K28*500+L28*100 -> 330600 | O28: =N28+M28 -> 330653
B29: 2 | C29: 330653 | E29: =ROUNDDOWN(C29/100000,0) -> 3 | F29: =ROUNDDOWN((C29-E29*100000)/50000,0) -> 0 | G29: =ROUNDDOWN((C29-E29*100000-F29*50000)/20000,0) -> 1 | H29: =ROUNDDOWN((C29-E29*100000-F29*50000-G29*20000)/10000,0) -> 1 | I29: =ROUNDDOWN((C29-E29*100000-F29*50000-G29*20000-H29*10000)/5000,0) -> 0 | J29: =ROUNDDOWN((C29-E29*100000-F29*50000-G29*20000-H29*10000-I29*5000)/1000,0) -> 0 | K29: =ROUNDDOWN((C29-E29*100000-F29*50000-G29*20000-H29*10000-I29*5000-J29*1000)/500,0) -> 1 | L29: =ROUNDDOWN((C29-E29*100000-F29*50000-G29*20000-H29*10000-I29*5000-J29*1000-K29*500)/100,0) -> 1 | M29: =C29-N29 -> 53 | N29: =E29*100000+F29*50000+G29*20000+H29*10000+I29*5000+J29*1000+K29*500+L29*100 -> 330600 | O29: =N29+M29 -> 330653
B30: 3 | C30: 330653 | E30: =ROUNDDOWN(C30/100000,0) -> 3 | F30: =ROUNDDOWN((C30-E30*100000)/50000,0) -> 0 | G30: =ROUNDDOWN((C30-E30*100000-F30*50000)/20000,0) -> 1 | H30: =ROUNDDOWN((C30-E30*100000-F30*50000-G30*20000)/10000,0) -> 1 | I30: =ROUNDDOWN((C30-E30*100000-F30*50000-G30*20000-H30*10000)/5000,0) -> 0 | J30: =ROUNDDOWN((C30-E30*100000-F30*50000-G30*20000-H30*10000-I30*5000)/1000,0) -> 0 | K30: =ROUNDDOWN((C30-E30*100000-F30*50000-G30*20000-H30*10000-I30*5000-J30*1000)/500,0) -> 1 | L30: =ROUNDDOWN((C30-E30*100000-F30*50000-G30*20000-H30*10000-I30*5000-J30*1000-K30*500)/100,0) -> 1 | M30: =C30-N30 -> 53 | N30: =E30*100000+F30*50000+G30*20000+H30*10000+I30*5000+J30*1000+K30*500+L30*100 -> 330600 | O30: =N30+M30 -> 330653
B31: 4 | C31: 330653 | E31: =ROUNDDOWN(C31/100000,0) -> 3 | F31: =ROUNDDOWN((C31-E31*100000)/50000,0) -> 0 | G31: =ROUNDDOWN((C31-E31*100000-F31*50000)/20000,0) -> 1 | H31: =ROUNDDOWN((C31-E31*100000-F31*50000-G31*20000)/10000,0) -> 1 | I31: =ROUNDDOWN((C31-E31*100000-F31*50000-G31*20000-H31*10000)/5000,0) -> 0 | J31: =ROUNDDOWN((C31-E31*100000-F31*50000-G31*20000-H31*10000-I31*5000)/1000,0) -> 0 | K31: =ROUNDDOWN((C31-E31*100000-F31*50000-G31*20000-H31*10000-I31*5000-J31*1000)/500,0) -> 1 | L31: =ROUNDDOWN((C31-E31*100000-F31*50000-G31*20000-H31*10000-I31*5000-J31*1000-K31*500)/100,0) -> 1 | M31: =C31-N31 -> 53 | N31: =E31*100000+F31*50000+G31*20000+H31*10000+I31*5000+J31*1000+K31*500+L31*100 -> 330600 | O31: =N31+M31 -> 330653
B32: 5 | C32: 330653 | E32: =ROUNDDOWN(C32/100000,0) -> 3 | F32: =ROUNDDOWN((C32-E32*100000)/50000,0) -> 0 | G32: =ROUNDDOWN((C32-E32*100000-F32*50000)/20000,0) -> 1 | H32: =ROUNDDOWN((C32-E32*100000-F32*50000-G32*20000)/10000,0) -> 1 | I32: =ROUNDDOWN((C32-E32*100000-F32*50000-G32*20000-H32*10000)/5000,0) -> 0 | J32: =ROUNDDOWN((C32-E32*100000-F32*50000-G32*20000-H32*10000-I32*5000)/1000,0) -> 0 | K32: =ROUNDDOWN((C32-E32*100000-F32*50000-G32*20000-H32*10000-I32*5000-J32*1000)/500,0) -> 1 | L32: =ROUNDDOWN((C32-E32*100000-F32*50000-G32*20000-H32*10000-I32*5000-J32*1000-K32*500)/100,0) -> 1 | M32: =C32-N32 -> 53 | N32: =E32*100000+F32*50000+G32*20000+H32*10000+I32*5000+J32*1000+K32*500+L32*100 -> 330600 | O32: =N32+M32 -> 330653
B33: 6 | C33: 330653 | E33: =ROUNDDOWN(C33/100000,0) -> 3 | F33: =ROUNDDOWN((C33-E33*100000)/50000,0) -> 0 | G33: =ROUNDDOWN((C33-E33*100000-F33*50000)/20000,0) -> 1 | H33: =ROUNDDOWN((C33-E33*100000-F33*50000-G33*20000)/10000,0) -> 1 | I33: =ROUNDDOWN((C33-E33*100000-F33*50000-G33*20000-H33*10000)/5000,0) -> 0 | J33: =ROUNDDOWN((C33-E33*100000-F33*50000-G33*20000-H33*10000-I33*5000)/1000,0) -> 0 | K33: =ROUNDDOWN((C33-E33*100000-F33*50000-G33*20000-H33*10000-I33*5000-J33*1000)/500,0) -> 1 | L33: =ROUNDDOWN((C33-E33*100000-F33*50000-G33*20000-H33*10000-I33*5000-J33*1000-K33*500)/100,0) -> 1 | M33: =C33-N33 -> 53 | N33: =E33*100000+F33*50000+G33*20000+H33*10000+I33*5000+J33*1000+K33*500+L33*100 -> 330600 | O33: =N33+M33 -> 330653
B34: 7 | C34: 330653 | E34: =ROUNDDOWN(C34/100000,0) -> 3 | F34: =ROUNDDOWN((C34-E34*100000)/50000,0) -> 0 | G34: =ROUNDDOWN((C34-E34*100000-F34*50000)/20000,0) -> 1 | H34: =ROUNDDOWN((C34-E34*100000-F34*50000-G34*20000)/10000,0) -> 1 | I34: =ROUNDDOWN((C34-E34*100000-F34*50000-G34*20000-H34*10000)/5000,0) -> 0 | J34: =ROUNDDOWN((C34-E34*100000-F34*50000-G34*20000-H34*10000-I34*5000)/1000,0) -> 0 | K34: =ROUNDDOWN((C34-E34*100000-F34*50000-G34*20000-H34*10000-I34*5000-J34*1000)/500,0) -> 1 | L34: =ROUNDDOWN((C34-E34*100000-F34*50000-G34*20000-H34*10000-I34*5000-J34*1000-K34*500)/100,0) -> 1 | M34: =C34-N34 -> 53 | N34: =E34*100000+F34*50000+G34*20000+H34*10000+I34*5000+J34*1000+K34*500+L34*100 -> 330600 | O34: =N34+M34 -> 330653
B35: 8 | C35: 330653 | E35: =ROUNDDOWN(C35/100000,0) -> 3 | F35: =ROUNDDOWN((C35-E35*100000)/50000,0) -> 0 | G35: =ROUNDDOWN((C35-E35*100000-F35*50000)/20000,0) -> 1 | H35: =ROUNDDOWN((C35-E35*100000-F35*50000-G35*20000)/10000,0) -> 1 | I35: =ROUNDDOWN((C35-E35*100000-F35*50000-G35*20000-H35*10000)/5000,0) -> 0 | J35: =ROUNDDOWN((C35-E35*100000-F35*50000-G35*20000-H35*10000-I35*5000)/1000,0) -> 0 | K35: =ROUNDDOWN((C35-E35*100000-F35*50000-G35*20000-H35*10000-I35*5000-J35*1000)/500,0) -> 1 | L35: =ROUNDDOWN((C35-E35*100000-F35*50000-G35*20000-H35*10000-I35*5000-J35*1000-K35*500)/100,0) -> 1 | M35: =C35-N35 -> 53 | N35: =E35*100000+F35*50000+G35*20000+H35*10000+I35*5000+J35*1000+K35*500+L35*100 -> 330600 | O35: =N35+M35 -> 330653
B36: 9 | C36: 330653 | E36: =ROUNDDOWN(C36/100000,0) -> 3 | F36: =ROUNDDOWN((C36-E36*100000)/50000,0) -> 0 | G36: =ROUNDDOWN((C36-E36*100000-F36*50000)/20000,0) -> 1 | H36: =ROUNDDOWN((C36-E36*100000-F36*50000-G36*20000)/10000,0) -> 1 | I36: =ROUNDDOWN((C36-E36*100000-F36*50000-G36*20000-H36*10000)/5000,0) -> 0 | J36: =ROUNDDOWN((C36-E36*100000-F36*50000-G36*20000-H36*10000-I36*5000)/1000,0) -> 0 | K36: =ROUNDDOWN((C36-E36*100000-F36*50000-G36*20000-H36*10000-I36*5000-J36*1000)/500,0) -> 1 | L36: =ROUNDDOWN((C36-E36*100000-F36*50000-G36*20000-H36*10000-I36*5000-J36*1000-K36*500)/100,0) -> 1 | M36: =C36-N36 -> 53 | N36: =E36*100000+F36*50000+G36*20000+H36*10000+I36*5000+J36*1000+K36*500+L36*100 -> 330600 | O36: =N36+M36 -> 330653
B37: 10 | C37: 330653 | E37: =ROUNDDOWN(C37/100000,0) -> 3 | F37: =ROUNDDOWN((C37-E37*100000)/50000,0) -> 0 | G37: =ROUNDDOWN((C37-E37*100000-F37*50000)/20000,0) -> 1 | H37: =ROUNDDOWN((C37-E37*100000-F37*50000-G37*20000)/10000,0) -> 1 | I37: =ROUNDDOWN((C37-E37*100000-F37*50000-G37*20000-H37*10000)/5000,0) -> 0 | J37: =ROUNDDOWN((C37-E37*100000-F37*50000-G37*20000-H37*10000-I37*5000)/1000,0) -> 0 | K37: =ROUNDDOWN((C37-E37*100000-F37*50000-G37*20000-H37*10000-I37*5000-J37*1000)/500,0) -> 1 | L37: =ROUNDDOWN((C37-E37*100000-F37*50000-G37*20000-H37*10000-I37*5000-J37*1000-K37*500)/100,0) -> 1 | M37: =C37-N37 -> 53 | N37: =E37*100000+F37*50000+G37*20000+H37*10000+I37*5000+J37*1000+K37*500+L37*100 -> 330600 | O37: =N37+M37 -> 330653
B38: 11 | C38: 330653 | E38: =ROUNDDOWN(C38/100000,0) -> 3 | F38: =ROUNDDOWN((C38-E38*100000)/50000,0) -> 0 | G38: =ROUNDDOWN((C38-E38*100000-F38*50000)/20000,0) -> 1 | H38: =ROUNDDOWN((C38-E38*100000-F38*50000-G38*20000)/10000,0) -> 1 | I38: =ROUNDDOWN((C38-E38*100000-F38*50000-G38*20000-H38*10000)/5000,0) -> 0 | J38: =ROUNDDOWN((C38-E38*100000-F38*50000-G38*20000-H38*10000-I38*5000)/1000,0) -> 0 | K38: =ROUNDDOWN((C38-E38*100000-F38*50000-G38*20000-H38*10000-I38*5000-J38*1000)/500,0) -> 1 | L38: =ROUNDDOWN((C38-E38*100000-F38*50000-G38*20000-H38*10000-I38*5000-J38*1000-K38*500)/100,0) -> 1 | M38: =C38-N38 -> 53 | N38: =E38*100000+F38*50000+G38*20000+H38*10000+I38*5000+J38*1000+K38*500+L38*100 -> 330600 | O38: =N38+M38 -> 330653
B39: 12 | C39: 330653 | E39: =ROUNDDOWN(C39/100000,0) -> 3 | F39: =ROUNDDOWN((C39-E39*100000)/50000,0) -> 0 | G39: =ROUNDDOWN((C39-E39*100000-F39*50000)/20000,0) -> 1 | H39: =ROUNDDOWN((C39-E39*100000-F39*50000-G39*20000)/10000,0) -> 1 | I39: =ROUNDDOWN((C39-E39*100000-F39*50000-G39*20000-H39*10000)/5000,0) -> 0 | J39: =ROUNDDOWN((C39-E39*100000-F39*50000-G39*20000-H39*10000-I39*5000)/1000,0) -> 0 | K39: =ROUNDDOWN((C39-E39*100000-F39*50000-G39*20000-H39*10000-I39*5000-J39*1000)/500,0) -> 1 | L39: =ROUNDDOWN((C39-E39*100000-F39*50000-G39*20000-H39*10000-I39*5000-J39*1000-K39*500)/100,0) -> 1 | M39: =C39-N39 -> 53 | N39: =E39*100000+F39*50000+G39*20000+H39*10000+I39*5000+J39*1000+K39*500+L39*100 -> 330600 | O39: =N39+M39 -> 330653
... B77: 50 | C77: 330653 | E77: =ROUNDDOWN(C77/100000,0) -> 3 | F77: =ROUNDDOWN((C77-E77*100000)/50000,0) -> 0 | G77: =ROUNDDOWN((C77-E77*100000-F77*50000)/20000,0) -> 1 | H77: =ROUNDDOWN((C77-E77*100000-F77*50000-G77*20000)/10000,0) -> 1 | I77: =ROUNDDOWN((C77-E77*100000-F77*50000-G77*20000-H77*10000)/5000,0) -> 0 | J77: =ROUNDDOWN((C77-E77*100000-F77*50000-G77*20000-H77*10000-I77*5000)/1000,0) -> 0 | K77: =ROUNDDOWN((C77-E77*100000-F77*50000-G77*20000-H77*10000-I77*5000-J77*1000)/500,0) -> 1 | L77: =ROUNDDOWN((C77-E77*100000-F77*50000-G77*20000-H77*10000-I77*5000-J77*1000-K77*500)/100,0) -> 1 | M77: =C77-N77 -> 53 | N77: =E77*100000+F77*50000+G77*20000+H77*10000+I77*5000+J77*1000+K77*500+L77*100 -> 330600 | O77: =N77+M77 -> 330653
C78: =SUM(C28:C77) -> 14769170 | E78: =SUM(E28:E77) -> 134 | F78: =SUM(F28:F77) -> 0 | G78: =SUM(G28:G77) -> 42 | H78: =SUM(H28:H77) -> 50 | I78: =SUM(I28:I77) -> 0 | J78: =SUM(J28:J77) -> 0 | K78: =SUM(K28:K77) -> 42 | L78: =SUM(L28:L77) -> 58 | ... N78: =SUM(N28:N77) -> 14766800 | O78: =N78+M78 -> 14769170
E81: JUMLAH | F81: NILAI | G81: TOTAL ( RP )
E82: =E78 -> 134 | F82: 100000 | G82: =E82*F82 -> 13400000
E83: =F78 -> 0 | F83: 50000 | G83: =E83*F83 -> 0
E84: =G78 -> 42 | F84: 20000 | G84: =E84*F84 -> 840000
E85: =H78 -> 50 | F85: 10000 | G85: =E85*F85 -> 500000
E86: =I78 -> 0 | F86: 5000 | G86: =E86*F86 -> 0
E87: =J78 -> 0 | F87: 1000 | G87: =E87*F87 -> 0
E88: =K78 -> 42 | F88: 500 | G88: =E88*F88 -> 21000
E89: =L78 -> 58 | F89: 100 | G89: =E89*F89 -> 5800
E90: Balance | G90: 2380
G91: =SUM(G82:G90) -> 14769180

Sheet Sheet6
B4: Aik Hijau | C4: Wiwis
B5: Aik Batu | C5: Devi
B6: Aik Kundo | C6: Martini
B7: Gunung Rum | C7: Honsa
B8: Gunung Panjang | C8: Wirda
B9: Padang Tembalun | C9: Ari
B10: Aik Jangkat | C10: Gunawan | D10: 4279901
B11: Aik Betangan | C11: Rati
B12: Aik Papan | C12: Liny
B13: Aik Limpas | C13: Amril
B14: Aik Kunyal | C14: Tari
B15: Aik Raya | C15: Panji
B16: Aik Cendong | C16: Sumiati
B17: Aik Kandis | C17: Doni
B18: Padang Panjang | C18: Helmiadi
B19: Bukit Panjang | C19: Roy Cantona
B20: Timur | C20: Nia
B21: Barat | C21: Fitria
B22: Aik Keminting | C22: Supriyani
... B26: Bukit Pasak | C26: Frans

Sheet Sheet2
A4: ESTATE | B4: DENOMINATION | C4: REKENING | D4: SELISIH
A5: PG IA | D5: =B5-C5 -> 0 | G5: ARE A
A6: PG IB | D6: =B6-C6 -> 0 | G6: ARE B1
A7: PG IIA | D7: =B7-C7 -> 0 | G7: WRKSP PGE
A8: PG IIB | D8: =B8-C8 -> 0 | G8: INFRA
A9: DME | D9: =B9-C9 -> 0 | G9: DME
A10: INFRA | D10: =B10-C10 -> 0 | G10: AREC
A11: WORKSHOP PG | D11: =B11-C11 -> 0
A12: ARE A | D12: =B12-C12 -> 0
A13: ARE B1 | D13: =B13-C13 -> 0
A14: ARE B2 | D14: =B14-C14 -> 0
A15: ARE C + V 36 | D15: =B15-C15 -> 0
A16: WORKSHOP ARE | D16: =B16-C16 -> 0
A17: IJL | D17: =B17-C17 -> 0
B18: =SUM(B5:B17) -> 0 | C18: =SUM(C5:C17) -> 0 | D18: =B18-C18 -> 0
B20: 432058589 | C20: 432058589
B23: =SUM(B18:B22) -> 432058589 | C23: =SUM(C18:C22) -> 432058589 | D23: =C23-B23 -> 0
B31: PG IA
B32: PG IB
B33: PG IIA
B34: PG IIB
B35: DME
B36: INFRA
B37: WORKSHOP PG
B38: ARE A
B39: ARE B1
B40: ARE B2
B41: ARE C + V 36
B42: WORKSHOP ARE
B43: IJL

Sheet HUTANG
A1: DAFTAR PINJAMAN KARYAWAN
A3: No | B3: Nama | C3: Divisi | D3: Pinjaman | E3: Penggantian
E4: Aug`17 | F4: Sept `17 | G4: Okt `17 | H4: Nop `17 | I4: Dec `17
A5: 1 | B5: Markus Maskur Laia | C5: ARE C | D5: 7958800 | G5: 750000 | H5: 750000 | I5: 750000
A6: 2 | B6: Awaludin | C6: PG 1B | D6: 663000 | F6: 250000 | G6: 250000 | H6: 163000
A7: 3 | B7: Baetul Mukaram | C7: PG 1A | D7: 300000 | G7: 150000 | H7: 150000
A8: 4 | B8: M.Nasir | C8: PG 1A | D8: 300000 | G8: 150000 | H8: 150000
A9: 5 | B9: Hardi Afip | C9: PG 1A | D9: 300000 | G9: 748209
A10: 6 | B10: Mikraj | C10: PG 1A | D10: 300000 | G10: 150000 | H10: 150000
A11: 7 | B11: Amsiah | C11: PG 1A | D11: 300000 | G11: 150000 | H11: 150000
A12: 8 | B12: Mudaham | C12: PG 1A | D12: 300000 | G12: 150000 | H12: 150000
A13: 9 | B13: Rudi Hartono | C13: PG 1A | D13: 300000 | G13: 150000 | H13: 150000
A14: 10 | B14: Ma`at | C14: PG 1A | D14: 300000 | G14: 150000 | H14: 150000
A15: 11 | B15: Hairudin | C15: PG 1A | D15: 300000 | G15: 150000 | H15: 150000
A16: 12 | B16: Abdurahman | C16: PG 1A | D16: 300000 | G16: 150000 | H16: 150000
A17: 13 | B17: Ispandi | C17: PG 1A | D17: 300000 | G17: 150000 | H17: 150000
A18: 14 | B18: Mastur | C18: PG 1A | D18: 300000 | G18: 150000 | H18: 150000
A19: 15 | B19: Andi | C19: PG 1A | D19: 300000 | G19: 150000 | H19: 150000
A20: 16 | B20: Maharun | C20: PG 1A | D20: 2000000 | H20: 500000 | I20: 500000
A21: 17 | B21: Tohrudi | C21: ARE C | D21: 994000 | H21: 500000 | I21: 494500
A22: 18 | B22: Badri | C22: ARE C | D22: 1348942 | G22: 500000 | H22: 500000 | I22: 348942
A23: 19 | B23: Yudi Kurniawan | C23: ARE C | D23: 1326000 | G23: 500000 | H23: 500000 | I23: 326000
A24: 20 | B24: Irsan Effendi | C24: PG 2B | D24: 5421000 | E24: 542100 | F24: 542100 | G24: 542100 | H24: 542100

Sheet NOV 2017 DIBAYAR DEC 2 (2)
A3: PT. REBINMAS JAYA
A4: DENOMINATION FOR NOVEMBER 2017
A6: ESTATE/DIVISION | B6: WORKERS | M6: Pot. | N6: TOTAL PPH 21 | O6: TOTAL PPH | P6: TOTAL PREMI | Q6: TOTAL LEMBUR | R6: TOTAL | S6: Upah & Astek | T6: Total & | X6: PRUNNING
C7: 100000 | D7: 50000 | E7: 20000 | F7: 10000 | G7: 5000 | H7: 1000 | I7: 500 | J7: 100 | K7: 50 | L7: OTHERS | M7: Pinjaman | N7: (MASA NOV - 2017) | O7: EX-GRATIA | T7: Rata-rata
A9: PHASE IA HARVESTING KHL (AIR HIJAU) | B9: 10 | N9: 0 | P9: =612510+1275400 -> 1887910 | Q9: 0 | R9: 20245609 | X9: 633000 | AA9: =P9+X9 -> 2520910
A10: PHASE IA MAINTENANCE KHT (AIR HIJAU) | B10: 37 | N10: 0 | P10: 758880 | Q10: 952334 | R10: 96935464 | X10: 3389500 | AA10: =P10+X10 -> 4148380
A11: PHASE IA OPERATOR (AIR HIJAU) | B11: 6 | N11: 0 | P11: 6170820 | Q11: 4512142 | R11: 26611684 | X11: 0 | AA11: =P11+X11 -> 6170820
A12: PHASE IA HARVESTING MANDOR & KERANI (AIR HIJAU) | B12: 24 | N12: 0 | P12: =883600+3140200+141650 -> 4165450 | Q12: 2139089 | R12: 77890103 | X12: 12266500 | AA12: =P12+X12 -> 16431950
A13: PHASE IA MAINTENANCE KHT (AIR HIJAU) | B13: 6 | N13: 0 | P13: 0 | Q13: 0 | R13: 14641265 | X13: 0 | AA13: =P13+X13 -> 0 | AB13: Mudaham,Rudi,Ma`at,Hairudin
A14: PHASE IA HARVESTING KHT (AIR BATU) | B14: 24 | N14: 0 | P14: =429030+1269800 -> 1698830 | Q14: 1692224 | R14: 63080259 | X14: 1704500 | AA14: =P14+X14 -> 3403330 | AB14: Baetul.,M.Nasir,Hardi,Mikraj,Amsiah
A15: PHASE IA HARVESTING KHL (AIR BATU) | B15: 9 | N15: 0 | P15: =271850+537600+133190 -> 942640 | Q15: 0 | R15: 22278677 | X15: 1346000 | AA15: =P15+X15 -> 2288640
A16: PHASE IA MAINTENANCE KHT (AIR BATU) | B16: 32 | N16: 0 | P16: 252395 | Q16: 945008 | R16: 79913879 | X16: 0 | AA16: =P16+X16 -> 252395
A17: PHASE IA OPERATOR (AIR BATU) | B17: 4 | N17: 0 | P17: 2671080 | Q17: 2922828 | R17: 16012188 | X17: 0 | AA17: =P17+X17 -> 2671080
A18: PHASE IA HARVESTING KHT (AIR KUNDO) | B18: 28 | N18: 0 | P18: =1497940+6398700+1105220 -> 9001860 | Q18: 2710489 | R18: 89643819 | X18: 10758000 | AA18: =P18+X18 -> 19759860
A19: PHASE IA HARVESTING KHL (AIR KUNDO) | B19: 2 | N19: 0 | P19: =21210+255500 -> 276710 | Q19: 0 | R19: 2677258 | X19: 285500 | AA19: =P19+X19 -> 562210
A20: PHASE IA MAINTENANCE KHT (AIR KUNDO) | B20: 30 | N20: 0 | P20: 78830 | Q20: 981637 | R20: 73924867 | X20: 0 | AA20: =P20+X20 -> 78830
A21: PHASE IA MAINTENANCE KHL (AIR KUNDO) | B21: 7 | N21: 0 | P21: =52160+666400+52305 -> 770865 | Q21: 820472 | R21: 15475973 | X21: 1338000 | AA21: =P21+X21 -> 2108865
A22: PHASE IA OPERATOR (AIR KUNDO) | B22: 4 | N22: 0 | P22: 2310700 | Q22: 2100120 | R22: 14279666 | X22: 0 | AA22: =P22+X22 -> 2310700
A23: TOTAL | B23: =SUM(B8:B22) -> 223 | C23: =SUM(C8:C22) -> 0 | D23: =SUM(D8:D22) -> 0 | E23: =SUM(E8:E22) -> 0 | F23: =SUM(F8:F22) -> 0 | G23: =SUM(G8:G22) -> 0 | H23: =SUM(H8:H22) -> 0 | I23: =SUM(I8:I22) -> 0 | ... R23: =SUM(R8:R22) -> 613610711 | T23: =#REF!/#REF! -> #REF! | U23: Upah rata-rata/ hk | X23: =SUM(X8:X22) -> 31721000 | AA23: =SUM(AA9:AA22) -> 62707970
A29: DIBUAT OLEH : DIPERIKSA OLEH : | D29: DIPERIKSA OLEH : | J29: DISETUJUI OLEH :
A38: PT. REBINMAS JAYA
A39: =A4 -> DENOMINATION FOR NOVEMBER 2017
A41: ESTATE/DIVISION | B41: WORKERS | M41: =M6 -> Pot. | N41: TOTAL PPH 21 | O41: TOTAL PPH | P41: =P6 -> TOTAL PREMI | Q41: =Q6 -> TOTAL LEMBUR | R41: TOTAL | S41: Upah & Astek | T41: Total & | X41: PRUNNING
C42: 100000 | D42: 50000 | E42: 20000 | F42: 10000 | G42: 5000 | H42: 1000 | I42: 500 | J42: 100 | K42: 50 | L42: OTHERS | M42: =M7 -> Pinjaman | N42: =N7 -> (MASA NOV - 2017) | O42: EX-GRATIA | T42: Rata-rata
A44: PHASE IB OPERATOR (GUNUNG RUM) | B44: 4 | N44: 0 | P44: 3956498 | Q44: 2864320 | R44: 16715553 | AA44: =P44+X44 -> 3956498
A45: PHASE IB HARVESTING KHT (GUNUNG RUM) | B45: 32 | N45: 76763 | P45: =396870+893870+5586000 -> 6876740 | Q45: 2424789 | R45: 104786109 | S45: =20846315+948633 -> 21794948 | X45: 14674500 | AA45: =P45+X45 -> 21551240
A46: PHASE IB MAINTENANCE KHT (GUNUNG RUM) | B46: 32 | N46: 0 | P46: =1050588 -> 1050588 | Q46: 1219720 | R46: 79135153 | X46: 0 | AA46: =P46+X46 -> 1050588
A47: PHASE IB HARVESTING KHT (GUNUNG PANJANG) | B47: 32 | N47: 0 | P47: =203160+2163700 -> 2366860 | Q47: 2131764 | R47: 97138812 | X47: 14651000 | AA47: =P47+X47 -> 17017860
A48: PHASE IB MAINTENANCE KHT (GUNUNG PANJANG) | B48: 33 | N48: 0 | P48: =12060+116900 -> 128960 | Q48: 1090522 | R48: 83501305 | X48: 936000 | AA48: =P48+X48 -> 1064960
A49: PHASE IB OPERATOR (GUNUNG PANJANG) | B49: 6 | N49: 0 | P49: 3172356 | Q49: 4014454 | R49: 23053400 | AA49: =P49+X49 -> 3172356
A50: PHASE IB HARVESTING & MANDOR & KERANI (PADANG TEMBALUN) | B50: 25 | N50: 0 | P50: =246330+2908500 -> 3154830 | Q50: 1838737 | R50: 73568728 | X50: 9755500 | AA50: =P50+X50 -> 12910330
A51: PHASE IB MAINTENANCE KHT (PADANG TEMBALUN) | B51: 50 | N51: 0 | P51: 1892960 | Q51: 1472452 | R51: 127757915 | X51: 0 | AA51: =P51+X51 -> 1892960
A52: PHASE IB PLASMA (PADANG TEMBALUN) | B52: 8 | N52: 0 | P52: =240650+466900 -> 707550 | Q52: 461516 | R52: 22847827 | X52: 1484000 | AA52: =P52+X52 -> 2191550
A53: PHASE IB OPERATOR (PADANG TEMBALUN) | B53: 8 | N53: 0 | P53: 2660257 | Q53: 5215739 | R53: 29218292 | X53: 0 | AA53: =P53+X53 -> 2660257
A55: TOTAL | B55: =SUM(B44:B54) -> 230 | C55: =SUM(C44:C54) -> 0 | D55: =SUM(D44:D54) -> 0 | E55: =SUM(E44:E54) -> 0 | F55: =SUM(F44:F54) -> 0 | G55: =SUM(G44:G54) -> 0 | H55: =SUM(H44:H54) -> 0 | I55: =SUM(I44:I54) -> 0 | ... R55: =SUM(R44:R54) -> 657723094 | T55: =#REF!/#REF! -> #REF! | U55: Upah rata-rata/HK | X55: =SUM(X43:X54) -> 41501000 | AA55: =SUM(AA44:AA54) -> 67468599
A61: DIBUAT OLEH : DIPERIKSA OLEH : | D61: DIPERIKSA OLEH : | J61: DISETUJUI OLEH :
A70: PT. REBINMAS JAYA
A71: =A4 -> DENOMINATION FOR NOVEMBER 2017
A73: ESTATE/DIVISION | B73: WORKERS | M73: =M6 -> Pot. | N73: TOTAL PPH 21 | O73: TOTAL PPH | P73: =P6 -> TOTAL PREMI | Q73: =Q6 -> TOTAL LEMBUR | R73: TOTAL | S73: Upah & Astek | T73: Total & | X73: PRUNNING
C74: 100000 | D74: 50000 | E74: 20000 | F74: 10000 | G74: 5000 | H74: 1000 | I74: 500 | J74: 100 | K74: 50 | L74: OTHERS | M74: =M7 -> Pinjaman | N74: =N7 -> (MASA NOV - 2017) | O74: EX-GRATIA | T74: Rata-rata
A76: PHASE IIA MAINTENANCE KHT AIR JANGKAT 1 | B76: 33 | N76: 0 | P76: 185820 | Q76: 1450458.3 | R76: 84827613 | AA76: =P76+X76 -> 185820
A77: PHASE IIA HARVESTING KHL AIR JANGKAT 1 | B77: 2 | N77: 0 | P77: 636000 | Q77: 0 | R77: 8141924.4 | X77: 2508000 | AA77: =P77+X77 -> 3144000
A78: PHASE IIA HARVESTING KHT AIR JANGKAT 1 | B78: 28 | N78: 0 | P78: 5588250 | Q78: 739890.35 | R78: 1.0197665e+08 | X78: 25767000 | AA78: =P78+X78 -> 31355250
A79: PHASE IIA HARVESTING KHT AIR BETANGAN | B79: 31 | N79: 0 | P79: =26190+4162200+59470 -> 4247860 | Q79: 901055 | R79: 112391516 | X79: 29528500 | AA79: =P79+X79 -> 33776360
A80: PHASE IIA MAINTENANCE KHT AIR BETANGAN 2 | B80: 33 | N80: 0 | P80: 0 | Q80: 1025591 | R80: 83277889 | X80: 0 | AA80: =P80+X80 -> 0
A81: PHASE IIA OPERATOR | B81: 14 | N81: 19442 | P81: 9825561 | Q81: 9779739 | R81: 55752311 | X81: 0 | AA81: =P81+X81 -> 9825561
A82: PHASE IIA MAINTENANCE KHT AIR PAPAN 3 | B82: 32 | N82: 0 | P82: 58188 | Q82: 754542 | R82: 80234570 | X82: 0 | AA82: =P82+X82 -> 58188
A83: PHASE IIA HARVESTING AIR PAPAN 3 | B83: 33 | N83: 0 | P83: =250000+241290+5095650 -> 5586940 | Q83: 1721527 | R83: 127899888 | X83: 36680500 | AA83: =P83+X83 -> 42267440
A84: PHASE IIA HARVESTING KHL AIR PAPAN 3 | B84: 1 | N84: 0 | P84: =6220+163100 -> 169320 | Q84: 0 | R84: 3988494 | X84: 1284500 | AA84: =P84+X84 -> 1453820
AA85: =P85+X85 -> 0
A86: TOTAL | B86: =SUM(B75:B85) -> 207 | C86: =SUM(C75:C85) -> 0 | D86: =SUM(D75:D85) -> 0 | E86: =SUM(E75:E85) -> 0 | F86: =SUM(F75:F85) -> 0 | G86: =SUM(G75:G85) -> 0 | H86: =SUM(H75:H85) -> 0 | I86: =SUM(I75:I85) -> 0 | ... R86: =SUM(R75:R85) -> 6.5849085e+08 | T86: =#REF!/#REF! -> #REF! | U86: Upah rata-rata / HK | X86: =SUM(X76:X85) -> 95768500 | AA86: =P86+X86 -> 122066439
A92: DIBUAT OLEH : DIPERIKSA OLEH : | D92: DIPERIKSA OLEH : | J92: DISETUJUI OLEH :
A100: PT. REBINMAS JAYA
A101: =A4 -> DENOMINATION FOR NOVEMBER 2017
A103: ESTATE/DIVISION | B103: WORKERS | M103: =M6 -> Pot. | N103: TOTAL PPH 21 | O103: TOTAL PPH | P103: =P73 -> TOTAL PREMI | Q103: =Q73 -> TOTAL LEMBUR | R103: TOTAL | S103: Upah & Astek | T103: Total & | X103: PRUNNING
C104: 100000 | D104: 50000 | E104: 20000 | F104: 10000 | G104: 5000 | H104: 1000 | I104: 500 | J104: 100 | K104: 50 | L104: OTHERS | M104: =M7 -> Pinjaman | N104: =N74 -> (MASA NOV - 2017) | O104: EX-GRATIA | T104: Rata-rata
A106: PHASE IIB HARVESTING (AIR LIMPAS) | B106: 37 | N106: 0 | P106: =294350+1988700 -> 2283050 | Q106: 1692225 | R106: 133693088 | S106: =22974544+948633 -> 23923177 | X106: 35258500 | AA106: =P106+X106 -> 37541550
A107: PHASE IIB MAINTENANCE (AIR LIMPAS) | B107: 37 | N107: 0 | P107: 0 | Q107: 615349 | R107: 93041726 | X107: 0 | AA107: =P107+X107 -> 0
A108: PHASE IIB OPERATOR | B108: 8 | N108: 0 | P108: 4962891 | Q108: 5230512 | R108: 30959264 | X108: 0 | AA108: =P108+X108 -> 4962891
A109: PHASE IIB HARVESTING (AIR KUNYAL) | B109: 30 | N109: 0 | P109: =1958510+1416100+250000 -> 3624610 | Q109: 1340593 | R109: 110995538 | X109: 30538000 | AA109: =P109+X109 -> 34162610
A110: PHASE IIB MAINTENANCE (AIR KUNYAL) | B110: 33 | N110: 0 | P110: 0 | Q110: 1413850 | R110: 84346150 | X110: 0 | AA110: =P110+X110 -> 0
AA111: =P111+X111 -> 0
A112: TOTAL | B112: =SUM(B105:B111) -> 145 | C112: =SUM(C105:C111) -> 0 | D112: =SUM(D105:D111) -> 0 | E112: =SUM(E105:E111) -> 0 | F112: =SUM(F105:F111) -> 0 | G112: =SUM(G105:G111) -> 0 | H112: =SUM(H105:H111) -> 0 | I112: =SUM(I105:I111) -> 0 | ... R112: =SUM(R105:R111) -> 453035766 | T112: =#REF!/#REF! -> #REF! | U112: Upah rata-rata / HK | X112: =SUM(X106:X111) -> 65796500 | AA112: =P112+X112 -> 76667051
A119: DIBUAT OLEH : DIPERIKSA OLEH : | D119: DIPERIKSA OLEH : | J119: DISETUJUI OLEH :
A127: PT. REBINMAS JAYA
A128: =A4 -> DENOMINATION FOR NOVEMBER 2017
A130: ESTATE/DIVISION | B130: WORKERS | M130: =M6 -> Pot. | N130: TOTAL PPH 21 | O130: TOTAL PPH | P130: =P103 -> TOTAL PREMI | Q130: =Q103 -> TOTAL LEMBUR | R130: TOTAL | S130: Upah & Astek | T130: Total & | X130: PRUNNING
C131: 100000 | D131: 50000 | E131: 20000 | F131: 10000 | G131: 5000 | H131: 1000 | I131: 500 | J131: 100 | K131: 50 | L131: OTHERS | M131: =M7 -> Pinjaman | N131: =N104 -> (MASA NOV - 2017) | O131: EX-GRATIA | T131: Rata-rata
A133: DME HARVESTING KHT AIK CENDONG | B133: 36 | N133: 0 | P133: =799921+6769000 -> 7568921 | Q133: 1106172 | R133: 133573541 | X133: 33718500 | AA133: =P133+X133 -> 41287421
A134: DME OPERATOR AIK CENDONG | B134: 6 | N134: 0 | P134: 4883532 | Q134: 5315859 | R134: 25506428 | X134: 0 | AA134: =P134+X134 -> 4883532
A135: DME MAINTENANCE KHT AIK CENDONG | B135: 32 | N135: 0 | P135: 0 | Q135: 1230708 | R135: 79785049 | X135: 0 | AA135: =P135+X135 -> 0
A136: DME MAINTENANCE KHT AIK KANDIS | B136: 32 | N136: 0 | P136: 751332 | Q136: 2219670 | R136: 83018497 | X136: 0 | AA136: =P136+X136 -> 751332
A137: DME OPERATOR AIK KANDIS | B137: 4 | N137: 4037 | P137: 3781632 | Q137: 2644557 | R137: 15673192 | X137: 0 | AA137: =P137+X137 -> 3781632
A138: DME HARVESTING KHT AIK KANDIS | B138: 31 | N138: 0 | P138: =993240+7227500 -> 8220740 | Q138: 1662921 | R138: 121763505 | X138: 35412500 | AA138: =P138+X138 -> 43633240
A139: DME MAINTENANCE KHL AIK KANDIS | B139: 1 | N139: 0 | P139: 35880 | Q139: 183140 | R139: 2779040
A140: DME HARVESTING KHT AIK RAYA | B140: 31 | N140: 0 | P140: =1292120+6379100 -> 7671220 | Q140: 1113498 | R140: 119231720 | X140: 32900500 | AA140: =P140+X140 -> 40571720
A141: DME OPERATOR AIK RAYA | B141: 4 | N141: 0 | P141: 3019612 | Q141: 3428396 | R141: 16766190 | X141: 0 | AA141: =P141+X141 -> 3019612
A142: DME MAINTENANCE KHT AIK RAYA | B142: 41 | N142: 0 | P142: 380432 | Q142: 1238032 | R142: 99556488 | X142: 0 | AA142: =P142+X142 -> 380432
AA143: =P143+X143 -> 0
A144: TOTAL | B144: =SUM(B132:B143) -> 218 | C144: =SUM(C132:C143) -> 0 | D144: =SUM(D132:D143) -> 0 | E144: =SUM(E132:E143) -> 0 | F144: =SUM(F132:F143) -> 0 | G144: =SUM(G132:G143) -> 0 | H144: =SUM(H132:H143) -> 0 | I144: =SUM(I132:I143) -> 0 | ... R144: =SUM(R132:R143) -> 697653650 | T144: =#REF!/#REF! -> #REF! | U144: Upah rata-rata / HK | X144: =SUM(X133:X143) -> 102031500 | AA144: =P144+X144 -> 138344801
A150: DIBUAT OLEH : DIPERIKSA OLEH : | D150: DIPERIKSA OLEH : | J150: DISETUJUI OLEH :
A157: PT. REBINMAS JAYA
A158: =A4 -> DENOMINATION FOR NOVEMBER 2017
A160: ESTATE/DIVISION | B160: WORKERS | M160: =M6 -> Pot. | N160: TOTAL PPH 21 | O160: TOTAL PPH | P160: =P130 -> TOTAL PREMI | Q160: =Q130 -> TOTAL LEMBUR | R160: TOTAL | S160: Upah & Astek | T160: Total & | X160: PRUNNING
C161: 100000 | D161: 50000 | E161: 20000 | F161: 10000 | G161: 5000 | H161: 1000 | I161: 500 | J161: 100 | K161: 50 | L161: OTHERS | M161: =M7 -> Pinjaman | N161: =N131 -> (MASA NOV - 2017) | O161: EX-GRATIA | T161: Rata-rata
A163: ARE-A HARVESTING KHT (BUKIT PANJANG) | B163: 27 | N163: 43778 | P163: =7079925+6979700 -> 14059625 | Q163: 703262 | R163: 91345331 | X163: 14909500 | AA163: =P163+X163 -> 28969125
A164: ARE-A MAINTENANCE KHT (BUKIT PANJANG) | B164: 37 | N164: 0 | P164: =76720+171500 -> 248220 | Q164: 4996091 | R164: 97664215 | X164: 387500 | AA164: =P164+X164 -> 635720
A165: ARE-A HARVESTING BHL (BUKIT PANJANG) | B165: 3 | N165: 0 | P165: =1127140+553700 -> 1680840 | Q165: 549424 | R165: 11464365 | X165: 1403000 | AA165: =P165+X165 -> 3083840
A166: ARE-A TRANSPORT (BUKIT PANJANG) | B166: 6 | N166: 0 | P166: 6750505 | Q166: 4146316 | R166: 26618465 | X166: 0 | AA166: =P166+X166 -> 6750505
A167: ARE-A UPKEEP BHL(PADANG PANJANG) | B167: 1 | N167: 0 | P167: 0 | Q167: 0 | R167: 2560020 | X167: 0 | AA167: =P167+X167 -> 0
A168: ARE-A HARVESTING BHL(PADANG PANJANG) | B168: 2 | N168: 0 | P168: =443630+500500 -> 944130 | Q168: 80582 | R168: 6174341 | X168: 217000 | AA168: =P168+X168 -> 1161130
A169: ARE-A HARVESTING KHT (PADANG PANJANG) | B169: 37 | N169: 0 | P169: =4391920+7275100+250000 -> 11917020 | Q169: 1824086 | R169: 112321962 | X169: 6016500 | AA169: =P169+X169 -> 17933520
A170: ARE-A MAINTENANTE (PADANG PANJANG) | B170: 28 | N170: 0 | P170: =411410+129500 -> 540910 | Q170: 2025541 | R170: 71165090 | X170: 0 | AA170: =P170+X170 -> 540910
A171: ARE-A TRANSPORT (PADANG PANJANG) | B171: 6 | N171: 0 | P171: 6700975 | Q171: 3853290 | R171: 26459845 | X171: 0 | AA171: =P171+X171 -> 6700975
A173: TOTAL | B173: =SUM(B162:B172) -> 147 | C173: =SUM(C162:C172) -> 0 | D173: =SUM(D162:D172) -> 0 | E173: =SUM(E162:E172) -> 0 | F173: =SUM(F162:F172) -> 0 | G173: =SUM(G162:G172) -> 0 | H173: =SUM(H162:H172) -> 0 | I173: =SUM(I162:I172) -> 0 | ... R173: =SUM(R162:R172) -> 445773634 | T173: =#REF!/#REF! -> #REF! | U173: Upah rata-rata / HK | X173: =SUM(X163:X172) -> 22933500 | AA173: =SUM(AA163:AA172) -> 65775725
A179: DIBUAT OLEH : DIPERIKSA OLEH : | D179: DIPERIKSA OLEH : | J179: DISETUJUI OLEH :
A186: PT. REBINMAS JAYA
A187: =A4 -> DENOMINATION FOR NOVEMBER 2017
A189: ESTATE/DIVISION | B189: WORKERS | M189: =M6 -> Pot. | N189: TOTAL PPH 21 | O189: TOTAL PPH | P189: =P160 -> TOTAL PREMI | Q189: =Q160 -> TOTAL LEMBUR | R189: TOTAL | X189: PRUNNING
C190: 100000 | D190: 50000 | E190: 20000 | F190: 10000 | G190: 5000 | H190: 1000 | I190: 500 | J190: 100 | K190: 50 | L190: OTHERS | M190: =M7 -> Pinjaman | N190: =N161 -> (MASA NOV - 2017) | O190: EX-GRATIA
...

Sheet Sheet4
B1: DAFTAR LEBIH PAJAK 2016
B3: DIVISI | C3: JUMLAH
B4: PHASE IA HARVESTING KHL (AIR HIJAU) | C4: 0
B5: PHASE IA MAINTENANCE KHT (AIR HIJAU) | C5: 3193
B6: PHASE IA OPERATOR (AIR HIJAU) | C6: 1322580
B7: PHASE IA HARVESTING MANDOR & KERANI (AIR HIJAU) | C7: 1170370
B8: PHASE IA HARVESTING KHT (AIR BATU) | C8: 715164
B9: PHASE IA HARVESTING KHL (AIR BATU) | C9: 0
B10: PHASE IA MAINTENANCE KHT (AIR BATU) | C10: 533325
B11: PHASE IA OPERATOR (AIR BATU) | C11: 398667
B12: PHASE IA MAINTENANTE KONTRAK (AIR BATU) | C12: 0
B13: PHASE IA HARVESTING KHT (AIR KUNDO) | C13: 898790
B14: PHASE IA HARVESTING KHL (AIR KUNDO) | C14: 0
B15: PHASE IA MAINTENANCE KHT (AIR KUNDO) | C15: 11792
B16: PHASE IA OPERATOR (AIR KUNDO) | C16: 230488
C17: =SUM(C4:C16) -> 5284369
B18: PHASE IB OPERATOR (GUNUNG RUM) | C18: 245259
B19: PHASE IB HARVESTING KHT (GUNUNG RUM) | C19: 381616
B20: PHASE IB HARVESTING KHL (GUNUNG RUM) | C20: 0
B21: PHASE IB MAINTENANCE KHT (GUNUNG RUM) | C21: 44890
B22: PHASE IB HARVESTING KHT (GUNUNG PANJANG) | C22: 68938
B23: PHASE IB HARVESTING KHL (GUNUNG PANJANG) | C23: 0
B24: PHASE IB MAINTENANCE KHT (GUNUNG PANJANG) | C24: 73664
B25: PHASE IB OPERATOR (GUNUNG PANJANG) | C25: 616966
B26: PHASE IB HARVESTING & MANDOR & KERANI (PADANG TEMBALUN) | C26: 3095919
B27: PHASE IB MAINTENANCE KHT (PADANG TEMBALUN) | C27: 789316
B28: PHASE IB PLASMA (PADANG TEMBALUN) | C28: 0
B29: PHASE IB OPERATOR (PADANG TEMBALUN) | C29: 857904
C30: =SUM(C18:C29) -> 6174472
B31: PHASE IIA MAINTENANCE KHT AIR JANGKAT 1 | C31: 1104
B32: PHASE IIA HARVESTING KHL AIR JANGKAT 1 | C32: 0
B33: PHASE IIA HARVESTING KHT AIR JANGKAT 1 | C33: 526560
B34: PHASE IIA MAINTENANTE KHL AIR JANGKAT 1 | C34: 0
B35: PHASE IIA KERANI AIR JANGKAT | C35: 62893
B36: PHASE IIA OPERATOR AIR JANGKAT | C36: 733992
B37: PHASE IIA OPERATOR AIR BETANGAN | C37: 785892
B38: PHASE IIA KERANI AIR BETANGAN | C38: 82575
B39: PHASE IIA HARVESTING KHT AIR BETANGAN | C39: 743350
B40: PHASE IIA HARVESTING KHL AIR BETANGAN 2 | C40: 0
B41: PHASE IIA MAINTENANCE KHT AIR BETANGAN 2 | C41: 0
B42: PHASE IIA OPERATOR AIR PAPAN | C42: 470993
... B46: PHASE IIA HARVESTING KHL AIR PAPAN 3 | C46: 0
C47: =SUM(C31:C46) -> 4092743
B48: PHASE IIB HARVESTING (AIR KUNYAL) | C48: 3648048
B49: PHASE IIB MAINTENANCE (AIR KUNYAL) | C49: 330293
B50: PHASE IIB OPERATOR (AIR KUNYAL) | C50: 230663
B51: PHASE IIB HARVESTING (AIR LIMPAS) | C51: 591035
B52: PHASE IIB MAINTENANCE (AIR LIMPAS) | C52: 68955
B53: PHASE IIB OPERATOR (AIR LIMPAS) | C53: 204266
C54: =SUM(C48:C53) -> 5073260
B55: DME HARVESTING KHT AIK CENDONG | C55: 860158
B56: DME OPERATOR AIK CENDONG | C56: 862065
B57: DME MAINTENANCE KHT AIK CENDONG | C57: 139916
B58: DME MAINTENANCE KHT AIK KANDIS | C58: 179138
B59: DME OPERATOR AIK KANDIS | C59: 859060
B60: DME HARVESTING KHT AIK KANDIS | C60: 287233
B61: DME HARVESTING KHT AIK RAYA | C61: 1433640
B62: DME OPERATOR AIK RAYA | C62: 729785
B63: DME MAINTENANCE KHT AIK RAYA | C63: 70200
C64: =SUM(C55:C63) -> 5421195
B65: ARE-A HARVESTING KHT (BUKIT PANJANG) | C65: 133030
B66: ARE-A MAINTENANCE KHT (BUKIT PANJANG) | C66: 461713
B67: ARE-A KONTRAK (BUKIT PANJANG) | C67: 0
B68: ARE-A TRANSPORT (BUKIT PANJANG) | C68: 1072153
B69: ARE-A KONTRAK (PADANG PANJANG) | C69: 0
B70: ARE-A HARVESTING KHT (PADANG PANJANG) | C70: 364182
B71: ARE-A MAINTENANTE (PADANG PANJANG) | C71: 0
B72: ARE-A TRANSPORT (PADANG PANJANG) | C72: 798873
C73: =SUM(C65:C72) -> 2829951
B74: ARE-B1 HARVESTING PHT (TIMUR) | C74: 470693
B75: ARE-B1 MAINTENANCE PHT (TIMUR) | C75: 181866
B76: ARE-B1 OPERATOR (TIMUR) | C76: 413611
B77: ARE-B1 HARVESTING PHT (BARAT) | C77: 468541
B78: ARE-B1 MAINTENANCE PHT (BARAT) | C78: 15456
B79: ARE-B1 HARVESTING BHL (TIMUR)
B80: ARE-B1 OPERATOR (BARAT) | C80: 271067
B81: ARE-B1 KONTRAK (TIMUR)
C82: =SUM(C74:C81) -> 1821234
B83: ARE-B2 KHT UPKEEP AIK KEMINTING | C83: 223450
B84: ARE-B2 KHT HARVESTING AIK KEMINTING | C84: 2023128
B85: ARE-B2 KHL HARVESTING AIK KEMINTING | C85: 0
B86: ARE-B2 KHT TRANSPORT AIK KEMINTING | C86: 605589
B87: ARE-B2 KONTRAK AIK KEMINTING | C87: 0
B88: ARE-B2 KHT TRANSPORT AIK BANGEK | C88: 330380
B89: ARE-B2 KHT UPKEEP AIK BANGEK | C89: 138688
B90: ARE-B2 KHT HARVESTING AIK BANGEK | C90: 1567507
B91: ARE-B2 KHL AIK BANGEK | C91: 0
C92: =SUM(C83:C91) -> 4888742
B93: ARE C.1 UPKEEP AIR PENYENGAT | C93: 33591
B94: ARE-C.1 HARVESTING AIR PENYENGAT | C94: 436042
B95: ARE-C.1 TRANSPORT AIR PENYENGAT | C95: 873866
B96: ARE-C.1 HARVESTING KHL AIR PENYENGAT | C96: 0
B97: ARE-C.2 UPKEEP AIR LENGGANG | C97: 2689
B98: ARE-C.2 TRANSPORT AIR LENGGANG | C98: 1001353
B99: ARE-C.2 HARVESTING AIR LENGGANG | C99: 582353
B100: ARE-C.3 UPKEEP BUKIT PASAK | C100: 231304
B101: ARE-C.3 BHL BUKIT PASAK | C101: 0
B102: ARE-C.3 TRANSPORT BUKIT PASAK | C102: 16526
B103: ARE-C.3 KASTRASI BUKIT PASAK | C103: 8190
B104: ARE-TRANSPORT EXAVATOR (V80) | C104: 47537
...

Sheet DENO TO BANK
A3: PT. REBINMAS JAYA | F3: PT. REBINMAS JAYA
A4: DENOMINATION TO BANK - OKTOBER 2016 | F4: =A4 -> DENOMINATION TO BANK - OKTOBER 2016
A6: DENO | B6: AMOUNT | F6: DENO | G6: PCS. | H6: AMOUNT
A8: 100000 | B8: =#REF! -> #REF! | F8: 100000 | G8: =H8/F8 -> #REF! | H8: =B8 -> #REF!
A9: 50000 | B9: =#REF! -> #REF! | F9: 50000 | G9: =H9/F9 -> #REF! | H9: =B9 -> #REF!
A10: 20000 | B10: =#REF! -> #REF! | F10: 20000 | G10: =H10/F10 -> #REF! | H10: =B10 -> #REF!
A11: 10000 | B11: =#REF! -> #REF! | F11: 10000 | G11: =H11/F11 -> #REF! | H11: =B11 -> #REF! | L11: 1779176
A12: 5000 | B12: =#REF! -> #REF! | F12: 5000 | G12: =H12/F12 -> #REF! | H12: =B12 -> #REF! | L12: 817106
A13: 1000 | B13: =#REF! -> #REF! | F13: 1000 | G13: =H13/F13 -> #REF! | H13: =B13 -> #REF! | L13: 1588081
H14: =B14 -> 0 | L14: 2754422
A15: OTH | L15: 1818714
L16: 1871430
L17: 1884608
A18: TOTAL | B18: =SUM(B8:B17) -> #REF! | F18: TOTAL | H18: =SUM(H8:H17) -> #REF! | L18: 2576507
L19: 1113635
L20: 2648990
L21: 1047741
A22: DIUANGKAN HARI : | F22: =A22 -> DIUANGKAN HARI : | L22: 1166353
L23: 612831
L24: 2372232
L25: 1298142
L26: 1594670
L27: 1298143
L28: 1607850
L29: 1970271
L30: 2200904
L31: 1647386
L32: 1930735
L33: 1792356
L34: 2102061
... L56: 1785767
L57: =SUM(L11:L56) -> 78969079

Sheet DENO TO BANK ATM
A3: PT. REBINMAS JAYA | G3: PT. REBINMAS JAYA
A4: ='DENO TO BANK'!A4 -> DENOMINATION TO BANK - OKTOBER 2016 | G4: =A4 -> DENOMINATION TO BANK - OKTOBER 2016
A6: DENO | B6: PCS. | C6: AMOUNT | G6: DENO | H6: PCS. | I6: AMOUNT
A9: 100000 | B9: =C9/A9 -> 0 | C9: ='SUMMARY - WAGES PT.RJ'!O41 -> 0 | G9: 100000 | H9: =I9/G9 -> 0 | I9: =C9 -> 0
A11: 50000 | B11: =C11/A11 -> 0 | C11: ='SUMMARY - WAGES PT.RJ'!P41 -> 0 | G11: 50000 | H11: =I11/G11 -> 0 | I11: =C11 -> 0
A13: 20000 | B13: =C13/A13 -> 0 | C13: ='SUMMARY - WAGES PT.RJ'!Q41 -> 0 | G13: 20000 | H13: =I13/G13 -> 0 | I13: =C13 -> 0
A15: 10000 | B15: =C15/A15 -> 0 | C15: ='SUMMARY - WAGES PT.RJ'!R41 -> 0 | G15: 10000 | H15: =I15/G15 -> 0 | I15: =C15 -> 0
A17: 5000 | B17: =C17/A17 -> 0 | C17: ='SUMMARY - WAGES PT.RJ'!S41 -> 0 | G17: 5000 | H17: =I17/G17 -> 0 | I17: =C17 -> 0
A19: 1000 | B19: =C19/A19 -> 0 | C19: ='SUMMARY - WAGES PT.RJ'!T41 -> 0 | G19: 1000 | H19: =I19/G19 -> 0 | I19: =C19 -> 0
A21: 100 | B21: =C21/A21 -> 0 | C21: ='SUMMARY - WAGES PT.RJ'!U41+'SUMMARY - WAGES PT.RJ'!V41+'SUMMARY - WAGES PT.RJ'!W41+'SUMMARY - WAGES PT.RJ'!X41 -> 0 | G21: 100 | H21: =B21 -> 0 | I21: =C21 -> 0
A25: TOTAL | C25: =SUM(C8:C24) -> 0 | G25: TOTAL | I25: =SUM(I9:I24) -> 0
A29: ='DENO TO BANK'!A22 -> DIUANGKAN HARI : | G29: =A29 -> DIUANGKAN HARI :

Sheet DENO CASH TO BANK PGE
A3: PT. REBINMAS JAYA | F3: PT. REBINMAS JAYA
A4: DENOMINATION TO BANK - SEPTEMBER 2016 | F4: =A4 -> DENOMINATION TO BANK - SEPTEMBER 2016
A6: DENO | B6: PCS. | C6: AMOUNT | F6: DENO | G6: PCS. | H6: AMOUNT
A9: 100000 | B9: =C9/A9 -> #REF! | C9: ='SUMMARY - CASH PG & ARE'!C44 -> #REF! | F9: 100000 | G9: =H9/F9 -> #REF! | H9: =C9 -> #REF!
A11: 50000 | B11: =C11/A11 -> #REF! | C11: ='SUMMARY - CASH PG & ARE'!D44 -> #REF! | F11: 50000 | G11: =H11/F11 -> #REF! | H11: =C11 -> #REF!
A13: 20000 | B13: =C13/A13 -> #REF! | C13: ='SUMMARY - CASH PG & ARE'!E44 -> #REF! | F13: 20000 | G13: =H13/F13 -> #REF! | H13: =C13 -> #REF!
A15: 10000 | B15: =C15/A15 -> #REF! | C15: ='SUMMARY - CASH PG & ARE'!F44 -> #REF! | F15: 10000 | G15: =H15/F15 -> #REF! | H15: =C15 -> #REF!
A17: 5000 | B17: =C17/A17 -> #REF! | C17: ='SUMMARY - CASH PG & ARE'!G44 -> #REF! | F17: 5000 | G17: =H17/F17 -> #REF! | H17: =C17 -> #REF!
A19: 1000 | B19: =C19/A19 -> #REF! | C19: ='SUMMARY - CASH PG & ARE'!H44 -> #REF! | F19: 1000 | G19: =H19/F19 -> #REF! | H19: =C19 -> #REF!
A21: 100 | B21: =C21/A21 -> #REF! | C21: ='SUMMARY - CASH PG & ARE'!I44+'SUMMARY - CASH PG & ARE'!#REF! -> #REF! | F21: 100 | G21: =B21 -> #REF! | H21: =C21 -> #REF!
A25: TOTAL | C25: =SUM(C8:C24) -> #REF! | F25: TOTAL | H25: =SUM(H9:H24) -> #REF!
A29: ='DENO TO BANK'!A22 -> DIUANGKAN HARI : | F29: =A29 -> DIUANGKAN HARI :

Sheet SUMMARY GABUNGAN
A1: SUMMARY GABUNGAN
A2: SUMMARY WAGES OKTOBER 2016
A4: ESTATE/DIVISION | B4: WORKERS | C4: 100000 | D4: 50000 | E4: 20000 | F4: 10000 | G4: 5000 | H4: 1000 | I4: 500 | J4: 100 | K4: 50 | L4: OTHERS | M4: TOTAL
A6: PHASE IA | B6: ='SUMMARY - WAGES PT.RJ'!Y7 -> 193 | C6: ='SUMMARY - WAGES PT.RJ'!O7 -> 0 | D6: ='SUMMARY - WAGES PT.RJ'!P7 -> 0 | E6: ='SUMMARY - WAGES PT.RJ'!Q7 -> 0 | F6: ='SUMMARY - WAGES PT.RJ'!R7 -> 0 | G6: ='SUMMARY - WAGES PT.RJ'!S7 -> 0 | H6: ='SUMMARY - WAGES PT.RJ'!T7 -> 0 | I6: ='SUMMARY - WAGES PT.RJ'!U7 -> 0 | J6: ='SUMMARY - WAGES PT.RJ'!V7 -> 0 | ... L6: ='SUMMARY - WAGES PT.RJ'!X7 -> 0 | M6: ='SUMMARY - WAGES PT.RJ'!AF7 -> 9.0199714e+08
A8: PHASE IB | B8: ='SUMMARY - WAGES PT.RJ'!Y9 -> 172 | C8: ='SUMMARY - WAGES PT.RJ'!O9 -> 0 | D8: ='SUMMARY - WAGES PT.RJ'!P9 -> 0 | E8: ='SUMMARY - WAGES PT.RJ'!Q9 -> 0 | F8: ='SUMMARY - WAGES PT.RJ'!R9 -> 0 | G8: ='SUMMARY - WAGES PT.RJ'!S9 -> 0 | H8: ='SUMMARY - WAGES PT.RJ'!T9 -> 0 | I8: ='SUMMARY - WAGES PT.RJ'!U9 -> 0 | J8: ='SUMMARY - WAGES PT.RJ'!V9 -> 0 | ... L8: ='SUMMARY - WAGES PT.RJ'!X9 -> 0 | M8: ='SUMMARY - WAGES PT.RJ'!AF9 -> 6.722109e+08
A10: PHASE IIA | B10: ='SUMMARY - WAGES PT.RJ'!Y11 -> 176 | C10: ='SUMMARY - WAGES PT.RJ'!O11 -> 0 | D10: ='SUMMARY - WAGES PT.RJ'!P11 -> 0 | E10: ='SUMMARY - WAGES PT.RJ'!Q11 -> 0 | F10: ='SUMMARY - WAGES PT.RJ'!R11 -> 0 | G10: ='SUMMARY - WAGES PT.RJ'!S11 -> 0 | H10: ='SUMMARY - WAGES PT.RJ'!T11 -> 0 | I10: ='SUMMARY - WAGES PT.RJ'!U11 -> 0 | J10: ='SUMMARY - WAGES PT.RJ'!V11 -> 0 | ... L10: ='SUMMARY - WAGES PT.RJ'!X11 -> 0 | M10: ='SUMMARY - WAGES PT.RJ'!AF11 -> 8.0045532e+08
A12: PHASE IIB | B12: ='SUMMARY - WAGES PT.RJ'!Y13 -> 125 | C12: ='SUMMARY - WAGES PT.RJ'!O13 -> 0 | D12: ='SUMMARY - WAGES PT.RJ'!P13 -> 0 | E12: ='SUMMARY - WAGES PT.RJ'!Q13 -> 0 | F12: ='SUMMARY - WAGES PT.RJ'!R13 -> 0 | G12: ='SUMMARY - WAGES PT.RJ'!S13 -> 0 | H12: ='SUMMARY - WAGES PT.RJ'!T13 -> 0 | I12: ='SUMMARY - WAGES PT.RJ'!U13 -> 0 | J12: ='SUMMARY - WAGES PT.RJ'!V13 -> 0 | ... L12: ='SUMMARY - WAGES PT.RJ'!X13 -> 0 | M12: ='SUMMARY - WAGES PT.RJ'!AF13 -> 6.3890182e+08
A14: ='SUMMARY - WAGES PT.RJ'!A15 -> DARUL MAKMUR | B14: ='SUMMARY - WAGES PT.RJ'!Y15 -> 205 | C14: ='SUMMARY - WAGES PT.RJ'!O15 -> 0 | D14: ='SUMMARY - WAGES PT.RJ'!P15 -> 0 | E14: ='SUMMARY - WAGES PT.RJ'!Q15 -> 0 | F14: ='SUMMARY - WAGES PT.RJ'!R15 -> 0 | G14: ='SUMMARY - WAGES PT.RJ'!S15 -> 0 | H14: ='SUMMARY - WAGES PT.RJ'!T15 -> 0 | I14: ='SUMMARY - WAGES PT.RJ'!U15 -> 0 | J14: ='SUMMARY - WAGES PT.RJ'!V15 -> 0 | ... L14: ='SUMMARY - WAGES PT.RJ'!X15 -> 0 | M14: ='SUMMARY - WAGES PT.RJ'!AF15 -> 9.4818318e+08
A16: WORKSHOP PG | B16: ='SUMMARY - WAGES PT.RJ'!Y17 -> 14 | C16: ='SUMMARY - WAGES PT.RJ'!O17 -> 0 | D16: ='SUMMARY - WAGES PT.RJ'!P17 -> 0 | E16: ='SUMMARY - WAGES PT.RJ'!Q17 -> 0 | F16: ='SUMMARY - WAGES PT.RJ'!R17 -> 0 | G16: ='SUMMARY - WAGES PT.RJ'!S17 -> 0 | H16: ='SUMMARY - WAGES PT.RJ'!T17 -> 0 | I16: ='SUMMARY - WAGES PT.RJ'!U17 -> 0 | J16: ='SUMMARY - WAGES PT.RJ'!V17 -> 0 | ... L16: ='SUMMARY - WAGES PT.RJ'!X17 -> 0 | M16: ='SUMMARY - WAGES PT.RJ'!AF17 -> 80279506
A18: INFRASTRUKTUR | B18: ='SUMMARY - WAGES PT.RJ'!Y19 -> 29 | C18: ='SUMMARY - WAGES PT.RJ'!O19 -> 0 | D18: ='SUMMARY - WAGES PT.RJ'!P19 -> 0 | E18: ='SUMMARY - WAGES PT.RJ'!Q19 -> 0 | F18: ='SUMMARY - WAGES PT.RJ'!R19 -> 0 | G18: ='SUMMARY - WAGES PT.RJ'!S19 -> 0 | H18: ='SUMMARY - WAGES PT.RJ'!T19 -> 0 | I18: ='SUMMARY - WAGES PT.RJ'!U19 -> 0 | J18: ='SUMMARY - WAGES PT.RJ'!V19 -> 0 | ... L18: ='SUMMARY - WAGES PT.RJ'!X19 -> 0 | M18: ='SUMMARY - WAGES PT.RJ'!AF19 -> 163108145
A20: MILL | B20: ='SUMMARY - WAGES PT.RJ'!Y23 -> 167 | C20: 0 | D20: 0 | E20: 0 | F20: 0 | G20: 0 | H20: 0 | I20: 0 | J20: 0 | K20: 0 | L20: 0 | M20: =#REF! -> #REF!
A22: Sub Total | B22: =SUM(B5:B21) -> 1081 | C22: =SUM(C5:C21) -> 0 | D22: =SUM(D5:D21) -> 0 | E22: =SUM(E5:E21) -> 0 | F22: =SUM(F5:F21) -> 0 | G22: =SUM(G5:G21) -> 0 | H22: =SUM(H5:H21) -> 0 | I22: =SUM(I5:I21) -> 0 | ... M22: =SUM(M5:M21) -> #REF!
A24: ='SUMMARY - WAGES PT.RJ'!A29 -> ARE - A | B24: ='SUMMARY - WAGES PT.RJ'!Y29 -> 140 | C24: ='SUMMARY - WAGES PT.RJ'!O29 -> 0 | D24: ='SUMMARY - WAGES PT.RJ'!P29 -> 0 | E24: ='SUMMARY - WAGES PT.RJ'!Q29 -> 0 | F24: ='SUMMARY - WAGES PT.RJ'!R29 -> 0 | G24: ='SUMMARY - WAGES PT.RJ'!S29 -> 0 | H24: ='SUMMARY - WAGES PT.RJ'!T29 -> 0 | I24: ='SUMMARY - WAGES PT.RJ'!U29 -> 0 | J24: ='SUMMARY - WAGES PT.RJ'!V29 -> 0 | ... L24: ='SUMMARY - WAGES PT.RJ'!X29 -> 0 | M24: ='SUMMARY - WAGES PT.RJ'!AF29 -> 6.6607642e+08
A26: ='SUMMARY - WAGES PT.RJ'!A31 -> ARE - B1 | B26: ='SUMMARY - WAGES PT.RJ'!Y31 -> 139 | C26: ='SUMMARY - WAGES PT.RJ'!O31 -> 0 | D26: ='SUMMARY - WAGES PT.RJ'!P31 -> 0 | E26: ='SUMMARY - WAGES PT.RJ'!Q31 -> 0 | F26: ='SUMMARY - WAGES PT.RJ'!R31 -> 0 | G26: ='SUMMARY - WAGES PT.RJ'!S31 -> 0 | H26: ='SUMMARY - WAGES PT.RJ'!T31 -> 0 | I26: ='SUMMARY - WAGES PT.RJ'!U31 -> 0 | J26: ='SUMMARY - WAGES PT.RJ'!V31 -> 0 | ... L26: ='SUMMARY - WAGES PT.RJ'!X31 -> 0 | M26: ='SUMMARY - WAGES PT.RJ'!AF31 -> 668699821
A28: ='SUMMARY - WAGES PT.RJ'!A33 -> ARE - B2 | B28: ='SUMMARY - WAGES PT.RJ'!Y33 -> 124 | C28: ='SUMMARY - WAGES PT.RJ'!O33 -> 0 | D28: ='SUMMARY - WAGES PT.RJ'!P33 -> 0 | E28: ='SUMMARY - WAGES PT.RJ'!Q33 -> 0 | F28: ='SUMMARY - WAGES PT.RJ'!R33 -> 0 | G28: ='SUMMARY - WAGES PT.RJ'!S33 -> 0 | H28: ='SUMMARY - WAGES PT.RJ'!T33 -> 0 | I28: ='SUMMARY - WAGES PT.RJ'!U33 -> 0 | J28: ='SUMMARY - WAGES PT.RJ'!V33 -> 0 | ... L28: ='SUMMARY - WAGES PT.RJ'!X33 -> 0 | M28: ='SUMMARY - WAGES PT.RJ'!AF33 -> 622111088
A30: ='SUMMARY - WAGES PT.RJ'!A35 -> ARE - C | B30: ='SUMMARY - WAGES PT.RJ'!Y35 -> 260 | C30: ='SUMMARY - WAGES PT.RJ'!O35 -> 0 | D30: ='SUMMARY - WAGES PT.RJ'!P35 -> 0 | E30: ='SUMMARY - WAGES PT.RJ'!Q35 -> 0 | F30: ='SUMMARY - WAGES PT.RJ'!R35 -> 0 | G30: ='SUMMARY - WAGES PT.RJ'!S35 -> 0 | H30: ='SUMMARY - WAGES PT.RJ'!T35 -> 0 | I30: ='SUMMARY - WAGES PT.RJ'!U35 -> 0 | J30: ='SUMMARY - WAGES PT.RJ'!V35 -> 0 | ... L30: ='SUMMARY - WAGES PT.RJ'!X35 -> 0 | M30: ='SUMMARY - WAGES PT.RJ'!AF35 -> 1.2927092e+09
A32: ='SUMMARY - WAGES PT.RJ'!A37 -> WORKSHOP ARE | B32: ='SUMMARY - WAGES PT.RJ'!Y37 -> 5 | C32: ='SUMMARY - WAGES PT.RJ'!O37 -> 0 | D32: ='SUMMARY - WAGES PT.RJ'!P37 -> 0 | E32: ='SUMMARY - WAGES PT.RJ'!Q37 -> 0 | F32: ='SUMMARY - WAGES PT.RJ'!R37 -> 0 | G32: ='SUMMARY - WAGES PT.RJ'!S37 -> 0 | H32: ='SUMMARY - WAGES PT.RJ'!T37 -> 0 | I32: ='SUMMARY - WAGES PT.RJ'!U37 -> 0 | J32: ='SUMMARY - WAGES PT.RJ'!V37 -> 0 | ... L32: ='SUMMARY - WAGES PT.RJ'!X37 -> 0 | M32: ='SUMMARY - WAGES PT.RJ'!AF37 -> 26805912
A35: Sub Total | B35: =SUM(B22:B34) -> 1749 | C35: =SUM(C22:C34) -> 0 | D35: =SUM(D22:D34) -> 0 | E35: =SUM(E22:E34) -> 0 | F35: =SUM(F22:F34) -> 0 | G35: =SUM(G22:G34) -> 0 | H35: =SUM(H22:H34) -> 0 | I35: =SUM(I22:I34) -> 0 | ... M35: =SUM(M22:M34) -> #REF!
A37: BLT+AM | B37: =+'SUMMARY - WAGES PT.RJ'!#REF! -> #REF! | C37: =#REF! -> #REF! | D37: =+'SUMMARY - WAGES PT.RJ'!#REF! -> #REF! | E37: =+'SUMMARY - WAGES PT.RJ'!#REF! -> #REF! | F37: =+'SUMMARY - WAGES PT.RJ'!#REF! -> #REF! | G37: =+'SUMMARY - WAGES PT.RJ'!#REF! -> #REF! | H37: =+'SUMMARY - WAGES PT.RJ'!#REF! -> #REF! | I37: =+'SUMMARY - WAGES PT.RJ'!#REF! -> #REF! | J37: =+'SUMMARY - WAGES PT.RJ'!#REF! -> #REF! | K37: =+'SUMMARY - WAGES PT.RJ'!#REF! -> #REF! | L37: =+'SUMMARY - WAGES PT.RJ'!#REF! -> #REF! | M37: ='SUMMARY - WAGES PT.RJ'!#REF! -> #REF!
A39: TOTAL C/ROLL | B39: =+B35+B37 -> #REF! | C39: =+C35+C37 -> #REF! | D39: =+D35+D37 -> #REF! | E39: =+E35+E37 -> #REF! | F39: =+F35+F37 -> #REF! | G39: =+G35+G37 -> #REF! | H39: =+H35+H37 -> #REF! | I39: =+I35+I37 -> #REF! | ... M39: =+M35+M37 -> #REF!
A41: ='SUMMARY - CASH PG & ARE'!A1 -> PT. REBINMAS JAYA CASH DENOMINATION JUNI 2018
A43: PETTY CASH MILL | B43: ='SUMMARY - CASH PG & ARE'!B6 -> #REF! | C43: ='SUMMARY - CASH PG & ARE'!C6 -> #REF! | D43: ='SUMMARY - CASH PG & ARE'!D6 -> #REF! | E43: ='SUMMARY - CASH PG & ARE'!E6 -> #REF! | F43: ='SUMMARY - CASH PG & ARE'!F6 -> #REF! | G43: ='SUMMARY - CASH PG & ARE'!G6 -> #REF! | H43: ='SUMMARY - CASH PG & ARE'!H6 -> #REF! | I43: ='SUMMARY - CASH PG & ARE'!#REF! -> #REF! | J43: ='SUMMARY - CASH PG & ARE'!#REF! -> #REF! | K43: ='SUMMARY - CASH PG & ARE'!#REF! -> #REF! | L43: ='SUMMARY - CASH PG & ARE'!I6 -> #REF! | M43: =SUM(C43:L43) -> #REF!
A45: PHASE 1A - PREMI | B45: ='SUMMARY - CASH PG & ARE'!B8 -> #REF! | C45: ='SUMMARY - CASH PG & ARE'!C8 -> 13400000 | D45: ='SUMMARY - CASH PG & ARE'!D8 -> #REF! | E45: ='SUMMARY - CASH PG & ARE'!E8 -> 840000 | F45: ='SUMMARY - CASH PG & ARE'!F8 -> 500000 | G45: ='SUMMARY - CASH PG & ARE'!G8 -> #REF! | H45: ='SUMMARY - CASH PG & ARE'!H8 -> #REF! | I45: ='SUMMARY - CASH PG & ARE'!#REF! -> #REF! | J45: ='SUMMARY - CASH PG & ARE'!#REF! -> #REF! | K45: ='SUMMARY - CASH PG & ARE'!#REF! -> #REF! | L45: ='SUMMARY - CASH PG & ARE'!I8 -> 29180 | M45: =SUM(C45:L45) -> #REF!
A47: PHASE 1B - PREMI | B47: ='SUMMARY - CASH PG & ARE'!B10 -> #REF! | C47: ='SUMMARY - CASH PG & ARE'!C10 -> #REF! | D47: ='SUMMARY - CASH PG & ARE'!D10 -> #REF! | E47: ='SUMMARY - CASH PG & ARE'!E10 -> #REF! | F47: ='SUMMARY - CASH PG & ARE'!F10 -> #REF! | G47: ='SUMMARY - CASH PG & ARE'!G10 -> #REF! | H47: ='SUMMARY - CASH PG & ARE'!H10 -> #REF! | I47: ='SUMMARY - CASH PG & ARE'!#REF! -> #REF! | J47: ='SUMMARY - CASH PG & ARE'!#REF! -> #REF! | K47: ='SUMMARY - CASH PG & ARE'!#REF! -> #REF! | L47: ='SUMMARY - CASH PG & ARE'!I10 -> #REF! | M47: =SUM(C47:L47) -> #REF!
A49: PHASE 2A - PREMI | B49: ='SUMMARY - CASH PG & ARE'!B12 -> #REF! | C49: ='SUMMARY - CASH PG & ARE'!C12 -> #REF! | D49: ='SUMMARY - CASH PG & ARE'!D12 -> #REF! | E49: ='SUMMARY - CASH PG & ARE'!E12 -> #REF! | F49: ='SUMMARY - CASH PG & ARE'!F12 -> #REF! | G49: ='SUMMARY - CASH PG & ARE'!G12 -> #REF! | H49: ='SUMMARY - CASH PG & ARE'!H12 -> #REF! | I49: ='SUMMARY - CASH PG & ARE'!#REF! -> #REF! | J49: ='SUMMARY - CASH PG & ARE'!#REF! -> #REF! | K49: ='SUMMARY - CASH PG & ARE'!#REF! -> #REF! | L49: ='SUMMARY - CASH PG & ARE'!I12 -> #REF! | M49: =SUM(C49:L49) -> #REF!
A51: PHASE 2A KONTRAK (PENGGANTI SURHADI) | B51: =#REF! -> #REF! | C51: =#REF! -> #REF! | D51: =#REF! -> #REF! | E51: =#REF! -> #REF! | F51: =#REF! -> #REF! | G51: =#REF! -> #REF! | H51: =#REF! -> #REF! | I51: =#REF! -> #REF! | ... L51: =#REF! -> #REF! | M51: =SUM(C51:L51) -> #REF!
A53: PHASE 2B - PREMI | B53: ='SUMMARY - CASH PG & ARE'!B14 -> #REF! | C53: ='SUMMARY - CASH PG & ARE'!C14 -> #REF! | D53: ='SUMMARY - CASH PG & ARE'!D14 -> #REF! | E53: ='SUMMARY - CASH PG & ARE'!E14 -> #REF! | F53: ='SUMMARY - CASH PG & ARE'!F14 -> #REF! | G53: ='SUMMARY - CASH PG & ARE'!G14 -> #REF! | H53: ='SUMMARY - CASH PG & ARE'!H14 -> #REF! | I53: ='SUMMARY - CASH PG & ARE'!#REF! -> #REF! | J53: ='SUMMARY - CASH PG & ARE'!#REF! -> #REF! | K53: ='SUMMARY - CASH PG & ARE'!#REF! -> #REF! | L53: ='SUMMARY - CASH PG & ARE'!I14 -> #REF! | M53: =SUM(C53:L53) -> #REF!
A55: DME 1 - PREMI | B55: ='SUMMARY - CASH PG & ARE'!B16 -> #REF! | C55: ='SUMMARY - CASH PG & ARE'!C18 -> #REF! | D55: ='SUMMARY - CASH PG & ARE'!D18 -> #REF! | E55: ='SUMMARY - CASH PG & ARE'!E16 -> #REF! | F55: ='SUMMARY - CASH PG & ARE'!F16 -> #REF! | G55: ='SUMMARY - CASH PG & ARE'!G18 -> #REF! | H55: ='SUMMARY - CASH PG & ARE'!H18 -> #REF! | I55: ='SUMMARY - CASH PG & ARE'!#REF! -> #REF! | J55: ='SUMMARY - CASH PG & ARE'!#REF! -> #REF! | K55: ='SUMMARY - CASH PG & ARE'!#REF! -> #REF! | L55: ='SUMMARY - CASH PG & ARE'!I18 -> #REF! | M55: =SUM(C55:L55) -> #REF!
A57: DME 2 - PREMI | B57: ='SUMMARY - CASH PG & ARE'!B18 -> #REF! | C57: ='SUMMARY - CASH PG & ARE'!C18 -> #REF! | D57: ='SUMMARY - CASH PG & ARE'!D18 -> #REF! | E57: ='SUMMARY - CASH PG & ARE'!E18 -> #REF! | F57: ='SUMMARY - CASH PG & ARE'!F18 -> #REF! | G57: ='SUMMARY - CASH PG & ARE'!G18 -> #REF! | H57: ='SUMMARY - CASH PG & ARE'!H18 -> #REF! | I57: ='SUMMARY - CASH PG & ARE'!#REF! -> #REF! | J57: ='SUMMARY - CASH PG & ARE'!#REF! -> #REF! | K57: ='SUMMARY - CASH PG & ARE'!#REF! -> #REF! | L57: ='SUMMARY - CASH PG & ARE'!I18 -> #REF! | M57: =SUM(C57:L57) -> #REF!
A59: BULU TUMBANG - KONTRAK
A61: BULU TUMBANG - PREMI | B61: ='SUMMARY - CASH PG & ARE'!B20 -> #REF! | C61: ='SUMMARY - CASH PG & ARE'!C20 -> #REF! | D61: ='SUMMARY - CASH PG & ARE'!D20 -> #REF! | E61: ='SUMMARY - CASH PG & ARE'!E20 -> #REF! | F61: ='SUMMARY - CASH PG & ARE'!F20 -> #REF! | G61: ='SUMMARY - CASH PG & ARE'!G20 -> #REF! | H61: ='SUMMARY - CASH PG & ARE'!H20 -> #REF! | I61: ='SUMMARY - CASH PG & ARE'!#REF! -> #REF! | J61: ='SUMMARY - CASH PG & ARE'!#REF! -> #REF! | K61: ='SUMMARY - CASH PG & ARE'!#REF! -> #REF! | L61: ='SUMMARY - CASH PG & ARE'!I20 -> #REF! | M61: =SUM(C61:L61) -> #REF!
A63: MC ALLOWANCE | B63: 0 | C63: =#REF! -> #REF! | D63: =#REF! -> #REF! | E63: =#REF! -> #REF! | F63: =#REF! -> #REF! | G63: =#REF! -> #REF! | H63: =#REF! -> #REF! | I63: =#REF! -> #REF! | J63: =#REF! -> #REF! | ... L63: =#REF! -> #REF! | M63: =SUM(C63:L63) -> #REF! | N63: 103125424
A65: PETTY CASH ESTATE | B65: ='SUMMARY - CASH PG & ARE'!B24 -> #REF! | C65: ='SUMMARY - CASH PG & ARE'!C24 -> #REF! | D65: ='SUMMARY - CASH PG & ARE'!D24 -> #REF! | E65: ='SUMMARY - CASH PG & ARE'!E24 -> #REF! | F65: ='SUMMARY - CASH PG & ARE'!F24 -> #REF! | G65: ='SUMMARY - CASH PG & ARE'!G24 -> #REF! | H65: ='SUMMARY - CASH PG & ARE'!H24 -> #REF! | I65: =#REF! -> #REF! | J65: ='SUMMARY - CASH PG & ARE'!#REF! -> #REF! | K65: ='SUMMARY - CASH PG & ARE'!#REF! -> #REF! | L65: ='SUMMARY - CASH PG & ARE'!I24 -> #REF! | M65: =SUM(C65:L65) -> #REF!
A69: Sub Total | B69: =SUM(B42:B68) -> #REF! | C69: =SUM(C42:C68) -> #REF! | D69: =SUM(D42:D68) -> #REF! | E69: =SUM(E42:E68) -> #REF! | F69: =SUM(F42:F68) -> #REF! | G69: =SUM(G42:G68) -> #REF! | H69: =SUM(H42:H68) -> #REF! | I69: =SUM(I42:I68) -> #REF! | ... L69: =SUM(L42:L68) -> #REF! | M69: =SUM(M43:M68) -> #REF! | N69: =SUM(N43:N68) -> 103125424 | O69: =SUM(O43:O68) -> 0 | P69: =SUM(P43:P68) -> 0 | Q69: =SUM(Q43:Q68) -> 0 | R69: =SUM(R43:R68) -> 0 | S69: =SUM(S43:S68) -> 0 | T69: =SUM(T43:T68) -> 0 | ... W69: =SUM(W43:W68) -> 0
A71: ='SUMMARY - CASH PG & ARE'!A29 -> PT. REBINMAS JAYA CASH DENOMINATION JUNI 2018
A73: ARE - A PREMI | B73: ='SUMMARY - CASH PG & ARE'!B32 -> #REF! | C73: ='SUMMARY - CASH PG & ARE'!C32 -> 3600000 | D73: ='SUMMARY - CASH PG & ARE'!D32 -> #REF! | E73: ='SUMMARY - CASH PG & ARE'!E32 -> 260000 | F73: ='SUMMARY - CASH PG & ARE'!F32 -> 100000 | G73: ='SUMMARY - CASH PG & ARE'!G32 -> #REF! | H73: ='SUMMARY - CASH PG & ARE'!H32 -> #REF! | I73: ='SUMMARY - CASH PG & ARE'!#REF! -> #REF! | J73: ='SUMMARY - CASH PG & ARE'!#REF! -> #REF! | K73: ='SUMMARY - CASH PG & ARE'!#REF! -> #REF! | L73: ='SUMMARY - CASH PG & ARE'!I32 -> 7839 | M73: =SUM(C73:L73) -> #REF!
A75: ARE - B1 PREMI | B75: ='SUMMARY - CASH PG & ARE'!B34 -> #REF! | C75: ='SUMMARY - CASH PG & ARE'!C34 -> #REF! | D75: ='SUMMARY - CASH PG & ARE'!D34 -> #REF! | E75: ='SUMMARY - CASH PG & ARE'!E34 -> #REF! | F75: ='SUMMARY - CASH PG & ARE'!F34 -> #REF! | G75: ='SUMMARY - CASH PG & ARE'!G34 -> #REF! | H75: ='SUMMARY - CASH PG & ARE'!H34 -> #REF! | I75: ='SUMMARY - CASH PG & ARE'!#REF! -> #REF! | J75: ='SUMMARY - CASH PG & ARE'!#REF! -> #REF! | K75: ='SUMMARY - CASH PG & ARE'!#REF! -> #REF! | L75: ='SUMMARY - CASH PG & ARE'!I34 -> #REF! | M75: =SUM(C75:L75) -> #REF!
A77: ARE - B2 PREMI | B77: ='SUMMARY - CASH PG & ARE'!B36 -> #REF! | C77: ='SUMMARY - CASH PG & ARE'!C36 -> #REF! | D77: ='SUMMARY - CASH PG & ARE'!D36 -> #REF! | E77: ='SUMMARY - CASH PG & ARE'!E36 -> #REF! | F77: ='SUMMARY - CASH PG & ARE'!F36 -> #REF! | G77: ='SUMMARY - CASH PG & ARE'!G36 -> #REF! | H77: ='SUMMARY - CASH PG & ARE'!H36 -> #REF! | I77: ='SUMMARY - CASH PG & ARE'!#REF! -> #REF! | J77: ='SUMMARY - CASH PG & ARE'!#REF! -> #REF! | K77: ='SUMMARY - CASH PG & ARE'!#REF! -> #REF! | L77: ='SUMMARY - CASH PG & ARE'!I36 -> #REF! | M77: =SUM(C77:L77) -> #REF!
A79: ARE - C PREMI | B79: ='SUMMARY - CASH PG & ARE'!B38 -> 0 | C79: ='SUMMARY - CASH PG & ARE'!C38 -> 0 | D79: ='SUMMARY - CASH PG & ARE'!D38 -> 0 | E79: ='SUMMARY - CASH PG & ARE'!E38 -> 0 | F79: ='SUMMARY - CASH PG & ARE'!F38 -> 0 | G79: ='SUMMARY - CASH PG & ARE'!G38 -> 0 | H79: ='SUMMARY - CASH PG & ARE'!H38 -> 0 | I79: ='SUMMARY - CASH PG & ARE'!#REF! -> #REF! | J79: ='SUMMARY - CASH PG & ARE'!#REF! -> #REF! | K79: ='SUMMARY - CASH PG & ARE'!#REF! -> #REF! | L79: ='SUMMARY - CASH PG & ARE'!I38 -> 0 | M79: =SUM(C79:L79) -> #REF!
A81: WORKSHOP ARE - PREMI | B81: ='SUMMARY - CASH PG & ARE'!B40 -> #REF! | C81: ='SUMMARY - CASH PG & ARE'!C40 -> #REF! | D81: ='SUMMARY - CASH PG & ARE'!D40 -> #REF! | E81: ='SUMMARY - CASH PG & ARE'!E40 -> #REF! | F81: ='SUMMARY - CASH PG & ARE'!F40 -> #REF! | G81: ='SUMMARY - CASH PG & ARE'!G40 -> #REF! | H81: ='SUMMARY - CASH PG & ARE'!H40 -> #REF! | I81: ='SUMMARY - CASH PG & ARE'!#REF! -> #REF! | J81: ='SUMMARY - CASH PG & ARE'!#REF! -> #REF! | K81: ='SUMMARY - CASH PG & ARE'!#REF! -> #REF! | L81: ='SUMMARY - CASH PG & ARE'!I40 -> #REF! | M81: =SUM(C81:L81) -> #REF!
A83: Sub Total | B83: =SUM(B72:B82) -> #REF! | C83: =SUM(C72:C82) -> #REF! | D83: =SUM(D72:D82) -> #REF! | E83: =SUM(E72:E82) -> #REF! | F83: =SUM(F72:F82) -> #REF! | G83: =SUM(G72:G82) -> #REF! | H83: =SUM(H72:H82) -> #REF! | I83: =SUM(I72:I82) -> #REF! | ... M83: =SUM(M72:M82) -> #REF!
A84: GRAND TOTAL | B84: =B39+B69+B83 -> #REF! | C84: =C39+C69+C83 -> #REF! | D84: =D39+D69+D83 -> #REF! | E84: =E39+E69+E83 -> #REF! | F84: =F39+F69+F83 -> #REF! | G84: =G39+G69+G83 -> #REF! | H84: =H39+H69+H83 -> #REF! | I84: =I39+I69+I83 -> #REF! | ... L84: =L39+L69+L83 -> #REF! | M84: =SUM(C84:L84) -> #REF! | O84: =SUM(M83,M69,M35) -> #REF!

Sheet IMPACT IJL
A1: ='IMPACT RMJ'!A1 -> MONTH OF OKTOBER 2025
A4: Estate | B4: Luas Ha Productive | C4: Jumlah Karyawan | F4: Nilai Gaji ( All) | I4: Tonase TBS | L4: % TBS Naik / Turun | M4: % Gaji Naik/Turun
C5: 45901 | D5: 45931 | E5: Diff | F5: 45901 | G5: 45931 | H5: Diff | I5: 45901 | J5: 45931 | K5: Diff | L5: ='IMPACT RMJ'!L4 -> (Okt`25 - Sept`25 )
A6: BLT + AM | B6: 326.26 | C6: 43 | D6: ='SEPTEMBER DIBAYAR OKT 2025 '!C456 -> 43 | E6: =D6-C6 -> 0 | F6: 236957607 | G6: ='SEPTEMBER DIBAYAR OKT 2025 '!V556 -> 2.2267996e+08 | H6: =G6-F6 -> -14277642 | I6: 480.87 | J6: ='SUMMARY - WAGES IJL'!AF14 -> 587.88 | K6: =J6-I6 -> 107.01 | L6: =K6/J6*100 -> 18.202694 | M6: =H6/G6*100 -> -6.4117318 | N6: =F6-#REF! -> #REF!
R7: =2976705.97 -> 2976706
B8: =SUM(B6:B7) -> 326.26 | C8: 43 | D8: =SUM(D6:D7) -> 43 | E8: =SUM(E6:E7) -> 0 | F8: =F6 -> 236957607 | G8: =+G6 -> 2.2267996e+08 | H8: =SUM(H6:H7) -> -14277642 | I8: =I6 -> 480.87 | J8: =SUM(J6:J7) -> 587.88 | K8: =SUM(K6:K7) -> 107.01 | L8: =K8/J8*100 -> 18.202694 | M8: =H8/G8*100 -> -6.4117318 | R8: =91848.13*30 -> 2755443.9
R9: =R7-R8 -> 221262.07
R10: =R9/R8*100 -> 8.0299973
A12: September'25 | D12: =F6 -> 236957607
A13: Oktober'25 | D13: =G6 -> 2.2267996e+08 | I13: NAIK HK OKt`25 - Sept`25 ) | M13: =K26 -> 258440
A14: Different | D14: =D12-D13 -> 14277642 | I14: Premi NAIK dari bulan lalu | L14: ( Lampiran I) | M14: =Rekapitulasi!F344 -> 7969043
I15: OT TURUN dari bulan lalu | L15: ( Lampiran I) | M15: =Rekapitulasi!G344 -> -1008363.8
I16: Prunning TURUN dari bulan lalu | L16: ( Lampiran II ) | M16: =Prunning!G25 -> -22557200
I17: Insentif Panen NAIK dari bulan lalu | M17: =M26 -> 2700000
I18: TOTAL | M18: =SUM(M13:M17) -> -12638081
P19: =H8-M18 -> -1639561.3
I20: Tonase TBS NAIK dari bulan lalu | M20: =K8 -> 107.01 | N20: Ton
P21: =P19/J25 -> -1287.9508
I24: Hk Sept | J24: 1271 | K24: =J24*129220 -> 164238620 | L24: Insentif Sept 2025 | M24: 3800000
I25: Hk Okt | J25: ='SEPTEMBER DIBAYAR OKT 2025 '!E456 -> 1273 | K25: =J25*129220 -> 164497060 | L25: Insentif Okt 2025 | M25: ='SEPTEMBER DIBAYAR OKT 2025 '!AG556 -> 6500000
J26: =J25-J24 -> 2 | K26: =K25-K24 -> 258440 | M26: =M25-M24 -> 2700000
A48: =A1 -> MONTH OF OKTOBER 2025
A49: ='SUMMARY - WAGES IJL'!A64:AI64 -> 01-31 MEI 2022 & 26-30 APRIL 2022
A51: Estate | B51: Luas Ha Productive | C51: Jumlah Karyawan | F51: Nilai Gaji ( All) | I51: Tonase TBS | L51: % TBS Naik / Turun | M51: % Gaji Naik/Turun
C52: 44682 | D52: 44652 | E52: Diff | F52: 44682 | G52: 44652 | H52: Diff | I52: 44682 | J52: 44652 | K52: Diff | L52: ='IMPACT RMJ'!L49 -> (Mei `22 - Apr`22 )
A53: BLT + AM | B53: 312.26 | C53: ='SEPTEMBER DIBAYAR OKT 2025 '!C532 -> 14 | D53: 44 | E53: =C53-D53 -> -30 | F53: ='SUMMARY - WAGES IJL'!AF71 -> 2.5310678e+08 | G53: 1.4580889e+08 | H53: =F53-G53 -> 1.0729789e+08 | I53: 572.82 | J53: 675.69 | K53: =I53-J53 -> -102.87 | L53: =K53/J53*100 -> -15.224437 | M53: =H53/G53*100 -> 73.588028
B55: =SUM(B53:B54) -> 312.26 | C55: =SUM(C53:C54) -> 14 | D55: =SUM(D53:D54) -> 44 | E55: =SUM(E53:E54) -> -30 | F55: =SUM(F53:F54) -> 2.5310678e+08 | G55: =SUM(G53:G54) -> 1.4580889e+08 | H55: =SUM(H53:H54) -> 1.0729789e+08 | I55: =SUM(I53:I54) -> 572.82 | ... K55: =SUM(K53:K54) -> -102.87 | L55: =K55/J55*100 -> -15.224437 | M55: =H55/G55*100 -> 73.588028
A59: Apr -22 ( 01 s/d 25 ) | D59: =F53 -> 2.5310678e+08
A60: 44682 | D60: =G53 -> 1.4580889e+08 | I60: Penambahan HK (Mei - Apr ) | M60: =K73 -> 43967106
A61: Different | D61: =D59-D60 -> 1.0729789e+08 | I61: Premi NAIK dari bulan lalu | L61: ( Lampiran I) | M61: =M14 -> 7969043
I62: OT TURUN dari bulan lalu | L62: ( Lampiran I) | M62: =M15 -> -1008363.8
I63: Prunning TURUN dari bulan lalu | L63: ( Lampiran II ) | M63: =Prunning!G72 -> 0
I65: TOTAL | M65: =SUM(M60:M64) -> 50927785
I67: Tonase TBS TURUN dari bulan lalu | M67: =K55 -> -102.87
I71: Hk April | J71: 1073 | K71: =J71*108829.47 -> 1.1677402e+08 | L71: Periode 01-25 April 2022
I72: Hk Mei | J72: =J25+204 -> 1477 | K72: =J72*108829.47 -> 1.6074113e+08
K73: =K72-K71 -> 43967106

Sheet Prunning
A1: LAMPIRAN II
B3: PRUNNING
D4: 45931
B5: Estate | D5: 45901 | F5: 45931 | G5: Balance
C6: Labour | D6: Premi | E6: Labour | F6: Premi | G6: Sept - Oct
B7: PGE 1A | C7: 0 | D7: 79134600 | E7: 0 | F7: ='SEPTEMBER DIBAYAR OKT 2025 '!AD35 -> 15466750 | G7: =F7-D7 -> -63667850
B8: PGE 1B | C8: 0 | D8: 0 | E8: 0 | F8: ='SEPTEMBER DIBAYAR OKT 2025 '!AD90 -> 0 | G8: =F8-D8 -> 0
B9: PGE 2A | C9: 0 | D9: 39745300 | E9: 0 | F9: ='SEPTEMBER DIBAYAR OKT 2025 '!AD135 -> 16282050 | G9: =F9-D9 -> -23463250
B10: PGE 2B | C10: 0 | D10: 54555850 | E10: 0 | F10: ='SEPTEMBER DIBAYAR OKT 2025 '!AD175 -> 8599500 | G10: =F10-D10 -> -45956350
B11: DME | C11: 0 | D11: 39455250 | E11: 0 | F11: ='SEPTEMBER DIBAYAR OKT 2025 '!AD226 -> 45629800 | G11: =F11-D11 -> 6174550
B12: ARE A | C12: 0 | D12: 28264500 | E12: 0 | F12: ='SEPTEMBER DIBAYAR OKT 2025 '!AD261 -> 26023250 | G12: =F12-D12 -> -2241250
B13: ARE B1 | C13: 0 | D13: 29461300 | E13: 0 | F13: ='SEPTEMBER DIBAYAR OKT 2025 '!AD296 -> 29981600 | G13: =F13-D13 -> 520300
B14: ARE B2 | C14: 0 | D14: 23009250 | E14: 0 | F14: ='SEPTEMBER DIBAYAR OKT 2025 '!AD332 -> 20870600 | G14: =F14-D14 -> -2138650
B15: ARE C | C15: 0 | D15: 48772550 | E15: 0 | F15: ='SEPTEMBER DIBAYAR OKT 2025 '!AD385 -> 45028000 | G15: =F15-D15 -> -3744550
C16: =SUM(C7:C15) -> 0 | D16: 342398600 | E16: =SUM(E7:E15) -> 0 | F16: =SUM(F7:F15) -> 207881550 | G16: =SUM(G7:G15) -> -134517050
A19: LAMPIRAN II
B21: PRUNNING
B23: Estate | C23: =D5 -> 45901 | E23: =F5 -> 45931 | G23: Balance
C24: Labour | D24: Premi | E24: Labour | F24: Premi | G24: =G6 -> Sept - Oct
B25: BLT + AM | C25: 0 | D25: 22557200 | E25: 0 | F25: ='SUMMARY - WAGES IJL'!AC8 -> 0 | G25: =F25-D25 -> -22557200

Sheet Rekapitulasi
A3: PT. REBINMAS JAYA
A4: DENOMINATION FOR JUNI 2019 ( 24-31 MEI 2019 s/d 01-30 JUNI 2019)
A6: ESTATE/DIVISION | D6: TOTAL PREMI | E6: TOTAL LEMBUR
A9: PHASE IA HARVESTING KHL (AIR HIJAU) | D9: =#REF!+'SEPTEMBER DIBAYAR OKT 2025 '!#REF! -> #REF! | E9: =#REF!+'SEPTEMBER DIBAYAR OKT 2025 '!#REF! -> #REF!
A11: PHASE IA MAINTENANCE KHT (AIR HIJAU) | D11: =#REF!+'SEPTEMBER DIBAYAR OKT 2025 '!T9 -> #REF! | E11: =#REF!+'SEPTEMBER DIBAYAR OKT 2025 '!U9 -> #REF!
A13: PHASE IA OPERATOR (AIR HIJAU) | D13: =#REF!+'SEPTEMBER DIBAYAR OKT 2025 '!T11 -> #REF! | E13: =#REF!+'SEPTEMBER DIBAYAR OKT 2025 '!U11 -> #REF!
A15: PHASE IA HARVESTING MANDOR & KERANI (AIR HIJAU) | D15: =#REF!+'SEPTEMBER DIBAYAR OKT 2025 '!T13 -> #REF! | E15: =#REF!+'SEPTEMBER DIBAYAR OKT 2025 '!U13 -> #REF!
A17: PHASE IA HARVESTING KHT (AIR BATU) | D17: =#REF!+'SEPTEMBER DIBAYAR OKT 2025 '!T17 -> #REF! | E17: =#REF!+'SEPTEMBER DIBAYAR OKT 2025 '!U17 -> #REF!
A19: PHASE IA MAINTENANCE KHT (AIR BATU) | D19: =#REF!+'SEPTEMBER DIBAYAR OKT 2025 '!T19 -> #REF! | E19: =#REF!+'SEPTEMBER DIBAYAR OKT 2025 '!U19 -> #REF!
A21: PHASE IA OPERATOR (AIR BATU) | D21: =#REF!+'SEPTEMBER DIBAYAR OKT 2025 '!T23 -> #REF! | E21: =#REF!+'SEPTEMBER DIBAYAR OKT 2025 '!U23 -> #REF!
A23: PHASE IA HARVESTING KHL (AIR BATU) | D23: =#REF!+'SEPTEMBER DIBAYAR OKT 2025 '!#REF! -> #REF! | E23: =#REF!+'SEPTEMBER DIBAYAR OKT 2025 '!#REF! -> #REF!
A24: rae
A25: PHASE IA HARVESTING KHT (AIR KUNDO) | D25: =#REF!+'SEPTEMBER DIBAYAR OKT 2025 '!T25 -> #REF! | E25: =#REF!+'SEPTEMBER DIBAYAR OKT 2025 '!U25 -> #REF!
A27: PHASE IA MAINTENANCE KHT (AIR KUNDO) | D27: =#REF!+'SEPTEMBER DIBAYAR OKT 2025 '!T27 -> #REF! | E27: =#REF!+'SEPTEMBER DIBAYAR OKT 2025 '!U27 -> #REF!
A29: PHASE IA PANEN KHL (AIR KUNDO) | D29: =#REF!+'SEPTEMBER DIBAYAR OKT 2025 '!#REF! -> #REF! | E29: =#REF!+'SEPTEMBER DIBAYAR OKT 2025 '!#REF! -> #REF!
A31: PHASE IA OPERATOR (AIR KUNDO) | D31: =#REF!+'SEPTEMBER DIBAYAR OKT 2025 '!T29 -> #REF! | E31: =#REF!+'SEPTEMBER DIBAYAR OKT 2025 '!U29 -> #REF!
A33: TOTAL | D33: =SUM(D8:D32) -> #REF! | E33: =SUM(E8:E32) -> #REF!
A35: PHASE IB OPERATOR (GUNUNG RUM) | D35: =#REF!+'SEPTEMBER DIBAYAR OKT 2025 '!T56 -> #REF! | E35: =#REF!+'SEPTEMBER DIBAYAR OKT 2025 '!U56 -> #REF!
A37: PHASE IB HARVESTING KHT (GUNUNG RUM) | D37: =#REF!+'SEPTEMBER DIBAYAR OKT 2025 '!T58 -> #REF! | E37: =#REF!+'SEPTEMBER DIBAYAR OKT 2025 '!U58 -> #REF!
A39: PHASE IB HARVESTING KHL (GUNUNG RUM) | D39: =#REF!+'SEPTEMBER DIBAYAR OKT 2025 '!#REF! -> #REF! | E39: =#REF!+'SEPTEMBER DIBAYAR OKT 2025 '!#REF! -> #REF!
A41: PHASE IB MAINTENANCE KHT (GUNUNG RUM) | D41: =#REF!+'SEPTEMBER DIBAYAR OKT 2025 '!T60 -> #REF! | E41: =#REF!+'SEPTEMBER DIBAYAR OKT 2025 '!U60 -> #REF!
A43: PHASE IB HARVESTING KHT (GUNUNG PANJANG) | D43: =#REF!+'SEPTEMBER DIBAYAR OKT 2025 '!#REF! -> #REF! | E43: =#REF!+'SEPTEMBER DIBAYAR OKT 2025 '!#REF! -> #REF!
A45: PHASE IB MAINTENANCE KHT (GUNUNG PANJANG) | D45: =#REF!+'SEPTEMBER DIBAYAR OKT 2025 '!T68 -> #REF! | E45: =#REF!+'SEPTEMBER DIBAYAR OKT 2025 '!U68 -> #REF!
A47: PHASE IB OPERATOR (GUNUNG PANJANG) | D47: =#REF!+'SEPTEMBER DIBAYAR OKT 2025 '!T72 -> #REF! | E47: =#REF!+'SEPTEMBER DIBAYAR OKT 2025 '!U72 -> #REF!
A49: PHASE IB HARVESTING KHL (GUNUNG PANJANG) | D49: =#REF!+'SEPTEMBER DIBAYAR OKT 2025 '!#REF! -> #REF! | E49: =#REF!+'SEPTEMBER DIBAYAR OKT 2025 '!#REF! -> #REF! | F49: =37+31 -> 68
D50: =#REF!+'SEPTEMBER DIBAYAR OKT 2025 '!#REF! -> #REF! | E50: =#REF!+'SEPTEMBER DIBAYAR OKT 2025 '!#REF! -> #REF!
A51: PHASE IB HARVESTING & MANDOR & KERANI (PADANG TEMBALUN) | D51: =#REF!+'SEPTEMBER DIBAYAR OKT 2025 '!T80 -> #REF! | E51: =#REF!+'SEPTEMBER DIBAYAR OKT 2025 '!U80 -> #REF!
D52: =#REF!+'SEPTEMBER DIBAYAR OKT 2025 '!#REF! -> #REF! | E52: =#REF!+'SEPTEMBER DIBAYAR OKT 2025 '!#REF! -> #REF!
A53: PHASE IB MAINTENANCE KHT (PADANG TEMBALUN) | D53: =#REF!+'SEPTEMBER DIBAYAR OKT 2025 '!T82 -> #REF! | E53: =#REF!+'SEPTEMBER DIBAYAR OKT 2025 '!U82 -> #REF!
D54: =#REF!+'SEPTEMBER DIBAYAR OKT 2025 '!#REF! -> #REF! | E54: =#REF!+'SEPTEMBER DIBAYAR OKT 2025 '!#REF! -> #REF!
A55: PHASE IB PLASMA (PADANG TEMBALUN) | D55: =#REF!+'SEPTEMBER DIBAYAR OKT 2025 '!T84 -> #REF! | E55: =#REF!+'SEPTEMBER DIBAYAR OKT 2025 '!U84 -> #REF!
A57: PHASE IB OPERATOR (PADANG TEMBALUN) | D57: =#REF!+'SEPTEMBER DIBAYAR OKT 2025 '!#REF! -> #REF! | E57: =#REF!+'SEPTEMBER DIBAYAR OKT 2025 '!#REF! -> #REF!
D59: =SUM(D35:D58) -> #REF! | E59: =SUM(E35:E58) -> #REF!
A61: PHASE IIA MAINTENANCE KHT AIR JANGKAT 1 | D61: =#REF!+'SEPTEMBER DIBAYAR OKT 2025 '!T111 -> #REF! | E61: =#REF!+'SEPTEMBER DIBAYAR OKT 2025 '!U111 -> #REF!
A63: PHASE IIA HARVESTING KHT AIR JANGKAT 1 | D63: =#REF!+'SEPTEMBER DIBAYAR OKT 2025 '!T113 -> #REF! | E63: =#REF!+'SEPTEMBER DIBAYAR OKT 2025 '!U113 -> #REF!
A65: PHASE IIA HARVESTING KHL AIR JANGKAT 1 | D65: =#REF!+'SEPTEMBER DIBAYAR OKT 2025 '!#REF! -> #REF! | E65: =#REF!+'SEPTEMBER DIBAYAR OKT 2025 '!#REF! -> #REF!
A67: PHASE IIA HARVESTING KHT AIR BETANGAN | D67: =#REF!+'SEPTEMBER DIBAYAR OKT 2025 '!T117 -> #REF! | E67: =#REF!+'SEPTEMBER DIBAYAR OKT 2025 '!U117 -> #REF!
A69: PHASE IIA HARVESTING KHL AIR BETANGAN | D69: =#REF!+'SEPTEMBER DIBAYAR OKT 2025 '!#REF! -> #REF! | E69: =#REF!+'SEPTEMBER DIBAYAR OKT 2025 '!#REF! -> #REF!
A71: PHASE IIA MAINTENANCE KHT AIR BETANGAN 2 | D71: =#REF!+'SEPTEMBER DIBAYAR OKT 2025 '!T121 -> #REF! | E71: =#REF!+'SEPTEMBER DIBAYAR OKT 2025 '!U121 -> #REF!
A73: PHASE IIA OPERATOR | D73: =#REF!+'SEPTEMBER DIBAYAR OKT 2025 '!T123 -> #REF! | E73: =#REF!+'SEPTEMBER DIBAYAR OKT 2025 '!U123 -> #REF!
A75: PHASE IIA MAINTENANCE KHT AIR PAPAN 3 | D75: =#REF!+'SEPTEMBER DIBAYAR OKT 2025 '!T127 -> #REF! | E75: =#REF!+'SEPTEMBER DIBAYAR OKT 2025 '!U127 -> #REF!
A77: PHASE IIA HARVESTING KHL AIR PAPAN 3 | D77: =#REF!+'SEPTEMBER DIBAYAR OKT 2025 '!#REF! -> #REF! | E77: =#REF!+'SEPTEMBER DIBAYAR OKT 2025 '!#REF! -> #REF!
A79: PHASE IIA HARVESTING AIR PAPAN 3 | D79: =#REF!+'SEPTEMBER DIBAYAR OKT 2025 '!T133 -> #REF! | E79: =#REF!+'SEPTEMBER DIBAYAR OKT 2025 '!U133 -> #REF!
A81: TOTAL | D81: =SUM(D60:D80) -> #REF! | E81: =SUM(E60:E80) -> #REF!
A83: PHASE IIB HARVESTING (AIR LIMPAS) | D83: =#REF!+'SEPTEMBER DIBAYAR OKT 2025 '!T155 -> #REF! | E83: =#REF!+'SEPTEMBER DIBAYAR OKT 2025 '!U155 -> #REF!
A85: PHASE IIB MAINTENANCE (AIR LIMPAS) | D85: =#REF!+'SEPTEMBER DIBAYAR OKT 2025 '!T157 -> #REF! | E85: =#REF!+'SEPTEMBER DIBAYAR OKT 2025 '!U157 -> #REF!
A87: PHASE IIB OPERATOR ( AIK LIMPAS) | D87: =#REF!+'SEPTEMBER DIBAYAR OKT 2025 '!T159 -> #REF! | E87: =#REF!+'SEPTEMBER DIBAYAR OKT 2025 '!U159 -> #REF!
A89: PHASE IIB HARVESTING (AIK KUNYAL) | D89: =#REF!+'SEPTEMBER DIBAYAR OKT 2025 '!#REF! -> #REF! | E89: =#REF!+'SEPTEMBER DIBAYAR OKT 2025 '!#REF! -> #REF!
A91: PHASE IIB MAINTENANTE ( Plasma ) | D91: =#REF!+'SEPTEMBER DIBAYAR OKT 2025 '!#REF! -> #REF! | E91: =#REF!+'SEPTEMBER DIBAYAR OKT 2025 '!#REF! -> #REF!
A93: PHASE IIB MAINT (AIK KUNYAL) | D93: =#REF!+'SEPTEMBER DIBAYAR OKT 2025 '!T163 -> #REF! | E93: =#REF!+'SEPTEMBER DIBAYAR OKT 2025 '!U163 -> #REF!
A95: PHASE IIB HARVESTING ( Plasma ) | D95: =#REF!+'SEPTEMBER DIBAYAR OKT 2025 '!T173 -> #REF! | E95: =#REF!+'SEPTEMBER DIBAYAR OKT 2025 '!U173 -> #REF!
A97: TOTAL | D97: =SUM(D82:D96) -> #REF! | E97: =SUM(E82:E96) -> #REF!
A99: DME HARVESTING KHT AIK CENDONG | D99: =#REF!+'SEPTEMBER DIBAYAR OKT 2025 '!T196 -> #REF! | E99: =#REF!+'SEPTEMBER DIBAYAR OKT 2025 '!U196 -> #REF!
A101: DME MASA PERCOBAAN HARVESTING AIK CENDONG | D101: =#REF!+'SEPTEMBER DIBAYAR OKT 2025 '!#REF! -> #REF! | E101: =#REF!+'SEPTEMBER DIBAYAR OKT 2025 '!#REF! -> #REF!
A103: DME OPERATOR AIK CENDONG | D103: =#REF!+'SEPTEMBER DIBAYAR OKT 2025 '!T200 -> #REF! | E103: =#REF!+'SEPTEMBER DIBAYAR OKT 2025 '!U200 -> #REF!
A105: DME MAINTENANCE KHT AIK CENDONG | D105: =#REF!+'SEPTEMBER DIBAYAR OKT 2025 '!T202 -> #REF! | E105: =#REF!+'SEPTEMBER DIBAYAR OKT 2025 '!U202 -> #REF!
A107: DME MAINTENANCE KHT AIK KANDIS | D107: =#REF!+'SEPTEMBER DIBAYAR OKT 2025 '!T204 -> #REF! | E107: =#REF!+'SEPTEMBER DIBAYAR OKT 2025 '!U204 -> #REF!
A109: DME OPERATOR AIK KANDIS | D109: =#REF!+'SEPTEMBER DIBAYAR OKT 2025 '!T206 -> #REF! | E109: =#REF!+'SEPTEMBER DIBAYAR OKT 2025 '!U206 -> #REF!
A111: DME HARVESTING KHT AIK KANDIS | D111: =#REF!+'SEPTEMBER DIBAYAR OKT 2025 '!T212 -> #REF! | E111: =#REF!+'SEPTEMBER DIBAYAR OKT 2025 '!U212 -> #REF!
A113: DME MASA PERCOBAAN HARVESTING AIK KANDIS | D113: =#REF!+'SEPTEMBER DIBAYAR OKT 2025 '!#REF! -> #REF! | E113: =#REF!+'SEPTEMBER DIBAYAR OKT 2025 '!#REF! -> #REF!
A115: DME HARVESTING KHT AIK RAYA | D115: =#REF!+'SEPTEMBER DIBAYAR OKT 2025 '!T216 -> #REF! | E115: =#REF!+'SEPTEMBER DIBAYAR OKT 2025 '!U216 -> #REF!
A117: DME OPERATOR AIK RAYA | D117: =#REF!+'SEPTEMBER DIBAYAR OKT 2025 '!T220 -> #REF! | E117: =#REF!+'SEPTEMBER DIBAYAR OKT 2025 '!U220 -> #REF!
A119: DME MAINTENANCE KHT AIK RAYA | D119: =#REF!+'SEPTEMBER DIBAYAR OKT 2025 '!T224 -> #REF! | E119: =#REF!+'SEPTEMBER DIBAYAR OKT 2025 '!U224 -> #REF!
A121: TOTAL | D121: =SUM(D98:D120) -> #REF! | E121: =SUM(E98:E120) -> #REF!
A123: ARE-A HARVESTING KHT (BUKIT PANJANG) | D123: =#REF!+'SEPTEMBER DIBAYAR OKT 2025 '!T245 -> #REF! | E123: =#REF!+'SEPTEMBER DIBAYAR OKT 2025 '!U245 -> #REF!
A125: ARE-A MAINTENANCE KHT (BUKIT PANJANG) | D125: =#REF!+'SEPTEMBER DIBAYAR OKT 2025 '!T247 -> #REF! | E125: =#REF!+'SEPTEMBER DIBAYAR OKT 2025 '!U247 -> #REF!
A127: ARE-A TRANSPORT (BUKIT PANJANG) | D127: =#REF!+'SEPTEMBER DIBAYAR OKT 2025 '!T249 -> #REF! | E127: =#REF!+'SEPTEMBER DIBAYAR OKT 2025 '!U249 -> #REF!
A129: ARE-A HARVESTING KHT (PADANG PANJANG) | D129: =#REF!+'SEPTEMBER DIBAYAR OKT 2025 '!T253 -> #REF! | E129: =#REF!+'SEPTEMBER DIBAYAR OKT 2025 '!U253 -> #REF!
A131: ARE-A MAINTENANTE (PADANG PANJANG) | D131: =#REF!+'SEPTEMBER DIBAYAR OKT 2025 '!T255 -> #REF! | E131: =#REF!+'SEPTEMBER DIBAYAR OKT 2025 '!U255 -> #REF!
A133: ARE-A TRANSPORT (PADANG PANJANG) | D133: =#REF!+'SEPTEMBER DIBAYAR OKT 2025 '!T259 -> #REF! | E133: =#REF!+'SEPTEMBER DIBAYAR OKT 2025 '!U259 -> #REF!
A135: TOTAL | D135: =SUM(D122:D134) -> #REF! | E135: =SUM(E122:E134) -> #REF!
A137: ARE-B1 HARVESTING PHT (TIMUR) | D137: =#REF!+'SEPTEMBER DIBAYAR OKT 2025 '!T280 -> #REF! | E137: =#REF!+'SEPTEMBER DIBAYAR OKT 2025 '!U280 -> #REF!
A139: ARE-B1 MAINTENANCE PHT (TIMUR) | D139: =#REF!+'SEPTEMBER DIBAYAR OKT 2025 '!T282 -> #REF! | E139: =#REF!+'SEPTEMBER DIBAYAR OKT 2025 '!U282 -> #REF!
A141: ARE-B1 OPERATOR (TIMUR) | D141: =#REF!+'SEPTEMBER DIBAYAR OKT 2025 '!T284 -> #REF! | E141: =#REF!+'SEPTEMBER DIBAYAR OKT 2025 '!U284 -> #REF!
A143: ARE-B1 HARVESTING KHL (TIMUR) | D143: =#REF!+'SEPTEMBER DIBAYAR OKT 2025 '!#REF! -> #REF! | E143: =#REF!+'SEPTEMBER DIBAYAR OKT 2025 '!#REF! -> #REF!
A145: ARE-B1 MAINTENANCE PHT (BARAT) | D145: =#REF!+'SEPTEMBER DIBAYAR OKT 2025 '!T288 -> #REF! | E145: =#REF!+'SEPTEMBER DIBAYAR OKT 2025 '!U288 -> #REF!
A147: ARE-B1 HARVESTING PHT (BARAT) | D147: =#REF!+'SEPTEMBER DIBAYAR OKT 2025 '!T290 -> #REF! | E147: =#REF!+'SEPTEMBER DIBAYAR OKT 2025 '!U290 -> #REF!
A149: ARE-B1 OPERATOR (BARAT) | D149: =#REF!+'SEPTEMBER DIBAYAR OKT 2025 '!T294 -> #REF! | E149: =#REF!+'SEPTEMBER DIBAYAR OKT 2025 '!U294 -> #REF!
A151: ARE-B1 HARVESTING KHL (BARAT) | D151: =#REF!+'SEPTEMBER DIBAYAR OKT 2025 '!#REF! -> #REF! | E151: =#REF!+'SEPTEMBER DIBAYAR OKT 2025 '!#REF! -> #REF!
A153: TOTAL | D153: =SUM(D136:D152) -> #REF! | E153: =SUM(E136:E152) -> #REF!
A155: ARE-B2 KHT UPKEEP AIK KEMINTING | D155: =#REF!+'SEPTEMBER DIBAYAR OKT 2025 '!T316 -> #REF! | E155: =#REF!+'SEPTEMBER DIBAYAR OKT 2025 '!U316 -> #REF!
A157: ARE-B2 KHT HARVESTING AIK KEMINTING | D157: =#REF!+'SEPTEMBER DIBAYAR OKT 2025 '!T318 -> #REF! | E157: =#REF!+'SEPTEMBER DIBAYAR OKT 2025 '!U318 -> #REF!
A159: ARE-B2 KHT TRANSPORT AIK KEMINTING | D159: =#REF!+'SEPTEMBER DIBAYAR OKT 2025 '!T322 -> #REF! | E159: =#REF!+'SEPTEMBER DIBAYAR OKT 2025 '!U322 -> #REF!
A161: ARE-B2 KHT TRANSPORT AIK BANGEK | D161: =#REF!+'SEPTEMBER DIBAYAR OKT 2025 '!T324 -> #REF! | E161: =#REF!+'SEPTEMBER DIBAYAR OKT 2025 '!U324 -> #REF!
A163: ARE-B2 KHT UPKEEP AIK BANGEK | D163: =#REF!+'SEPTEMBER DIBAYAR OKT 2025 '!T328 -> #REF! | E163: =#REF!+'SEPTEMBER DIBAYAR OKT 2025 '!U328 -> #REF!
A165: ARE-B2 KHT HARVESTING AIK BANGEK | D165: =#REF!+'SEPTEMBER DIBAYAR OKT 2025 '!T330 -> #REF! | E165: =#REF!+'SEPTEMBER DIBAYAR OKT 2025 '!U330 -> #REF!
A167: ARE-B2 KHL HARVESTING AIK BANGEK | D167: =#REF!+'SEPTEMBER DIBAYAR OKT 2025 '!#REF! -> #REF! | E167: =#REF!+'SEPTEMBER DIBAYAR OKT 2025 '!#REF! -> #REF!
A169: TOTAL | D169: =SUM(D155:D168) -> #REF! | E169: =SUM(E155:E168) -> #REF!
A171: ARE C.1 UPKEEP AIR PENYENGAT | D171: =#REF!+'SEPTEMBER DIBAYAR OKT 2025 '!T352 -> #REF! | E171: =#REF!+'SEPTEMBER DIBAYAR OKT 2025 '!U352 -> #REF!
A173: ARE-C.1 HARVESTING AIR PENYENGAT | D173: =#REF!+'SEPTEMBER DIBAYAR OKT 2025 '!T354 -> #REF! | E173: =#REF!+'SEPTEMBER DIBAYAR OKT 2025 '!U354 -> #REF!
A175: ARE-C.1 TRANSPORT AIR PENYENGAT | D175: =#REF!+'SEPTEMBER DIBAYAR OKT 2025 '!#REF! -> #REF! | E175: =#REF!+'SEPTEMBER DIBAYAR OKT 2025 '!#REF! -> #REF!
A177: ARE-C.1 UPKEEP AIR PENYENGAT | D177: =#REF!+'SEPTEMBER DIBAYAR OKT 2025 '!#REF! -> #REF! | E177: =#REF!+'SEPTEMBER DIBAYAR OKT 2025 '!#REF! -> #REF!
A179: ARE-C.1 AIR PENYENGAT( MASA PERCOBAAN ) | D179: =#REF!+'SEPTEMBER DIBAYAR OKT 2025 '!#REF! -> #REF! | E179: =#REF!+'SEPTEMBER DIBAYAR OKT 2025 '!#REF! -> #REF!
A181: ARE-C.2 UPKEEP AIR LENGGANG | D181: =#REF!+'SEPTEMBER DIBAYAR OKT 2025 '!T362 -> #REF! | E181: =#REF!+'SEPTEMBER DIBAYAR OKT 2025 '!U362 -> #REF!
A183: ARE-C.2 TRANSPORT AIR LENGGANG | D183: =#REF!+'SEPTEMBER DIBAYAR OKT 2025 '!#REF! -> #REF! | E183: =#REF!+'SEPTEMBER DIBAYAR OKT 2025 '!#REF! -> #REF!
A185: ARE-C.2 HARVESTING AIR LENGGANG | D185: =#REF!+'SEPTEMBER DIBAYAR OKT 2025 '!T364 -> #REF! | E185: =#REF!+'SEPTEMBER DIBAYAR OKT 2025 '!U364 -> #REF!
A187: ARE-C.2 HARVESTING KHL AIR LENGGANG | D187: =#REF!+'SEPTEMBER DIBAYAR OKT 2025 '!#REF! -> #REF! | E187: =#REF!+'SEPTEMBER DIBAYAR OKT 2025 '!#REF! -> #REF!
A189: ARE-C.3 UPKEEP BUKIT PASAK | D189: =#REF!+'SEPTEMBER DIBAYAR OKT 2025 '!T370 -> #REF! | E189: =#REF!+'SEPTEMBER DIBAYAR OKT 2025 '!U370 -> #REF!
A191: ARE-C.3 HARVESTING BUKIT PASAK | D191: =#REF!+'SEPTEMBER DIBAYAR OKT 2025 '!#REF! -> #REF! | E191: =#REF!+'SEPTEMBER DIBAYAR OKT 2025 '!#REF! -> #REF!
A193: ARE-C.3 TRANSPORT BUKIT PASAK | D193: =#REF!+'SEPTEMBER DIBAYAR OKT 2025 '!#REF! -> #REF! | E193: =#REF!+'SEPTEMBER DIBAYAR OKT 2025 '!#REF! -> #REF!
...

Sheet Ifest
A1: Selisih Ifest
A3: DME
A5: HK Payroll | B5: 6487 | G5: 1B
A6: HK Ifest | B6: 6586
A7: Selisih | B7: =B6-B5 -> 99
A9: No | B9: Nama | C9: HK | D9: Ket | G9: 2288
A10: E0233 | B10: Muji Widodo | C10: 5 | D10: Assisten | G10: 2232
A11: E0014 | B11: Irwan | C11: 5 | D11: Keluar | G11: =G9-G10 -> 56
A12: E0015 | B12: Sumardi | C12: 5 | D12: Keluar
A13: E0029 | B13: M.Satriadi | C13: 5 | D13: Keluar
A14: E0257 | B14: Jamiludin | C14: 5 | D14: Keluar
A15: E0191 | B15: Mahmudi | C15: 5 | D15: Keluar
A16: E0256 | B16: Maryandi | C16: 5 | D16: Keluar
A17: E0179 | B17: Sahdan | C17: 5 | D17: Keluar
A18: E0189 | B18: Mursidin | C18: 5 | D18: Keluar
A19: E0190 | B19: Lalu Wire Bakti | C19: 5 | D19: Keluar
A20: E0202 | B20: Ari Trisna W | C20: 5 | D20: Keluar
A21: E0219 | B21: Remina | C21: 5 | D21: Keluar
A22: E0234 | B22: Sopian | C22: 24 | D22: Keluar
A23: E0258 | B23: Samsul Islam | C23: 5 | D23: Keluar
... A25: E0092 | B25: Rahmat | C25: 5 | D25: Keluar
C26: =SUM(C10:C25) -> 99
